Workbook

Sheet Cover
A1: Paket FP&A Tambang Batubara – Global Energy Group
A2: Disusun oleh FP&A | Laporan keuangan contoh, analisa struktur biaya & KPI, dan template pelaporan bulanan GEG
A4: DAFTAR ISI
A5: BAGIAN A – CONTOH LAPORAN KEUANGAN LENGKAP (perusahaan fiktif, format emiten batubara Tbk, PSAK)
A6: A1 Asumsi Contoh | B6: Asumsi & driver: harga, kurs, volume, SR, tarif kontraktor, BBM, logistik, royalti, overhead, capex, modal kerja
A7: A2 Laba Rugi Contoh | B7: Laba rugi rinci: breakdown pendapatan (ekspor/DMO/non-DMO/penalti/jasa), BPP (tambang, logistik, royalti, overhead, D&A), beban penjualan, G&A, lain-lain
A8: A3 Neraca Contoh | B8: Neraca 3 periode, terhubung dengan laba rugi & arus kas (cek keseimbangan = 0)
A9: A4 Arus Kas Contoh | B9: Arus kas metode tidak langsung + rekonsiliasi metode langsung
A10: BAGIAN B – ANALISA UNTUK MANAJEMEN
A11: B1 Struktur Rev-Cost | B11: Struktur pendapatan (bauran pasar, ASP) & struktur biaya (porsi, sifat tetap/variabel, pemicu), titik impas
A12: B2 COP dan KPI | B12: Cost of production per unit (USD/bcm, USD/t, USD/t-km, cash cost, AISC) + penilaian KPI COP dengan skor
A13: B3 KPI Cost vs Revenue | B13: 27 KPI cost vs revenue (jaws, rasio biaya, marjin, harga impas, leverage, konversi kas) + kesimpulan otomatis
A14: B4 Efisiensi Biaya | B14: Varians biaya: efek volume vs tarif vs kurs; jembatan pendapatan & EBITDA (pasar vs manajemen); inisiatif penghematan
A15: B5 Benchmark Emiten | B15: Emiten batubara BEI sebagai acuan & kisaran KPI industri (indikatif)
A16: BAGIAN C – TEMPLATE PELAPORAN BULANAN GLOBAL ENERGY GROUP
A17: C0 GEG Petunjuk | B17: Petunjuk, kode warna, jadwal closing bulanan
A18: C1 GEG Setting | B18: Pengaturan bulan laporan & skala KPI
A19: C2 GEG Ops Budget | B19: Input budget operasional bulanan
A20: C3 GEG Ops Aktual | B20: Input aktual operasional bulanan
A21: C4 GEG LR Budget | B21: Input budget laba rugi bulanan (kode akun)
A22: C5 GEG LR Aktual | B22: Input aktual laba rugi bulanan (kode akun)
A23: C6 GEG Neraca Aktual | B23: Input neraca akhir bulan
A24: C7 GEG Arus Kas | B24: Arus kas bulanan otomatis
A25: C8 GEG Lap LR | B25: Laporan laba rugi MTD & YTD vs budget
A26: C9 GEG Lap Ops | B26: Laporan operasional MTD & YTD vs budget
A27: C10 GEG COP | B27: Cost of production per unit vs budget
A28: C11 GEG KPI Scorecard | B28: KPI scorecard manajemen (skor & predikat)
A29: C12 GEG Dashboard | B29: DASHBOARD: tile KPI, 8 grafik kinerja (pendapatan, EBITDA, produksi, SR, cash cost vs ASP, fuel ratio, struktur biaya, skor perspektif) + tabel KPI Scored
A30: FORMAT LAPORAN BULANAN ALA "AAT FINANCIAL & OPERATIONAL PERFORMANCE REPORT" – disesuaikan untuk batubara
A31: C13 GEG Financial Highlight | B31: Key indicators operasional & keuangan: bulan lalu vs bulan ini (MoM), vs budget, YTD, EBITDA normalisasi, CADS, DSCR + kolom catatan
A32: C14 GEG Analisa Biaya | B32: Analisa biaya per akun & unit cost (USD/bcm, USD/t) – MoM, vs budget, YTD + catatan penjelasan varians
A33: C15 GEG Tren Volume | B33: Tren volume bulanan: aktual tahun lalu vs budget vs aktual (OB, produksi, SR, penjualan, barging, stok) + grafik
A34: C16 GEG Pit dan Pembeli | B34: Rincian produksi/OB/SR per pit & kontraktor serta penjualan per pembeli, dengan cek rekonsiliasi ke C3
A35: C17 GEG Arus Kas Langsung | B35: Arus kas metode langsung: kas operasi, debt service, CADS, capex, DSCR – aktual otomatis vs budget
A36: C18 GEG Cost per BCM dan MT | B36: Analisa COST PER BCM (OB) & COST PER MT batubara terjual: MoM, vs budget, YTD, jembatan efek tarif vs efek SR, tren bulanan + grafik
A37: REVISI MENGACU MIS AAT (Dec-23): ALUR DATA GL → MIS, COVENANT, BRIDGE & KONTROL
A38: C19 GEG GL Trial Balance | B38: INPUT UTAMA KEUANGAN: tempel trial balance GL per akun (aktual & budget) + Tag MIS; C4/C5 terisi otomatis via SUMIFS, dengan kontrol akun belum dimapping
A39: C20 GEG Covenant Bank | B39: Kepatuhan covenant bank bulanan: adjusted current ratio, debt to tangible net worth, DSCR, ICR, net debt/EBITDA → MEET / NOT MEET
A40: C21 GEG Bridge EBITDA | B40: Bridge EBITDA budget → aktual (bulan ini & YTD): efek volume, harga, kurs, tiap kelompok biaya + grafik kontribusi
A41: C22 GEG Kontrol Data | B41: Checklist kontrol & rekonsiliasi seluruh workbook → status SIAP KIRIM / BELUM SIAP
A43: KODE WARNA
A44: 1.234 | B44: Teks biru / sel kuning muda = input (hardcode) – ganti dengan data Anda
A45: 1.234 | B45: Teks hitam = rumus
A46: 1.234 | B46: Teks hijau = tautan antar-sheet
A47: 1.234 | B47: Sel kuning terang = parameter kunci / selector
A49: CATATAN PENTING
A50: • | B50: Bagian A & B memakai perusahaan FIKTIF "PT Batubara Contoh Tbk" dengan format penyajian yang lazim di emiten batubara BEI. Angka ilustratif, BUKAN data emiten mana pun.
A51: • | B51: Laporan keuangan asli emiten (PTBA, ITMG, AADI, BUMI, BYAN, dll.) dapat diunduh di www.idx.co.id untuk pembanding angka riil.
A52: • | B52: Bagian C terisi DATA CONTOH (Jan–Agu 2026) agar semua rumus terlihat bekerja. Ganti seluruh sel input dengan data GEG.
A53: • | B53: Satuan uang: Rp juta. Harga & tarif: USD. Volume: ton / bcm. Kurs dipakai untuk konversi per unit.
A54: • | B54: Semua angka di laporan, COP dan KPI adalah rumus – bila input diubah, seluruh laporan ikut terhitung ulang.

Sheet A1 Asumsi Contoh
A1: PT Batubara Contoh Tbk (fiktif) – Asumsi & Pemicu (Driver) Operasional
A2: Lembar input model contoh. Teks biru/sel kuning = input; hitam = rumus; hijau = tautan antar-sheet. Satuan uang: Rp juta.
A5: Parameter | B5: Satuan | C5: FY2024 | D5: FY2025 | E5: Keterangan / sumber
A6: 1. MAKRO & HARGA
A7: Kurs rata-rata | B7: Rp/USD | C7: 15850 | D7: 16250 | E7: Asumsi ilustratif, mendekati rata-rata JISDOR tahun berjalan
A8: Harga indeks acuan setara CV produk (HBA/ICI) | B8: USD/t | C8: 72 | D8: 64 | E8: Ilustratif; gunakan HBA (Kepmen ESDM) / ICI sesuai CV
A9: ASP – Ekspor (FOB/CIF) | B9: USD/t | C9: 70 | D9: 62 | E9: Harga realisasi rata-rata tertimbang
A10: ASP – Domestik DMO (kelistrikan/PLN) | B10: USD/t | C10: 50 | D10: 50 | E10: Harga DMO dibatasi (cap USD 70/t @6.322 GAR), disesuaikan CV
A11: ASP – Domestik non-DMO (industri) | B11: USD/t | C11: 65 | D11: 58
A12: Nilai kalori rata-rata produk | B12: kcal/kg GAR | C12: 4600 | D12: 4600
A13: 2. VOLUME OPERASI
A14: Produksi batubara (ROM) | B14: ton | C14: 10800000 | D14: 11800000
A15: Stripping ratio (SR) | B15: bcm/ton | C15: 7.8 | D15: 7.4 | E15: Sesuai rencana tambang (RKAB)
A16: Pengupasan tanah penutup (OB removal) | B16: bcm | C16: =C14*C15 | D16: =D14*D15
A17: Jarak hauling tambang – pelabuhan | B17: km | C17: 42 | D17: 42
A18: Penjualan – Ekspor | B18: ton | C18: 6900000 | D18: 7600000
A19: Penjualan – Domestik DMO | B19: ton | C19: 2700000 | D19: 2900000
A20: Penjualan – Domestik non-DMO | B20: ton | C20: 1100000 | D20: 1150000
A21: Total penjualan | B21: ton | C21: =SUM(C18:C20) | D21: =SUM(D18:D20)
A22: Porsi DMO terhadap total penjualan | B22: % | C22: =IFERROR(C19/C21,0) | D22: =IFERROR(D19/D21,0) | E22: Kewajiban DMO minimal 25% (Kepmen ESDM)
A23: Stok batubara awal tahun | B23: ton | C23: 450000 | D23: =C24 | E23: 2025 = stok akhir 2024
A24: Stok batubara akhir tahun | B24: ton | C24: =C23+C14-C21 | D24: =D23+D14-D21
A25: Jumlah karyawan organik | B25: orang | C25: 1150 | D25: 1180
A26: 3. TARIF BIAYA TAMBANG & LOGISTIK
A27: Tarif kontraktor OB (excl. BBM) | B27: USD/bcm | C27: 1.85 | D27: 1.8 | E27: BBM disuplai pemilik (owner-supplied fuel)
A28: Tarif coal getting | B28: USD/ton | C28: 0.95 | D28: 0.95
A29: Rasio BBM (fuel ratio) | B29: liter/bcm | C29: 0.95 | D29: 0.9
A30: Harga BBM solar industri | B30: Rp/liter | C30: 13500 | D30: 13000
A31: Porsi OB yang diledakkan | B31: % | C31: 0.4 | D31: 0.4
A32: Tarif drill & blast | B32: USD/bcm | C32: 0.45 | D32: 0.45
A33: Tarif crushing & pengolahan (CPP) | B33: USD/ton | C33: 0.85 | D33: 0.82
A34: Tarif hauling | B34: USD/ton-km | C34: 0.105 | D34: 0.1
A35: Tarif pelabuhan & stockpile | B35: USD/ton | C35: 1.25 | D35: 1.2 | E35: Basis ton penjualan
A36: Tarif tongkang & transshipment | B36: USD/ton | C36: 4.1 | D36: 3.95 | E36: Basis ton penjualan
A37: Tarif royalti efektif (PNBP) | B37: % pendapatan | C37: 0.07 | D37: 0.065 | E37: IUP: bertingkat per CV & HBA (PP 26/2022); IUPK: PP 15/2022
A38: Penyesuaian harga / penalti kualitas | B38: % pendapatan | C38: 0.006 | D38: 0.005 | E38: Penalti CV, TM, ash, sulfur
A39: 4. BIAYA TETAP TAMBANG & OVERHEAD SITE (Rp juta)
A40: Sewa alat berat & sarana penunjang | B40: Rp juta | C40: 120000 | D40: 115000
A41: Pemeliharaan jalan tambang & infrastruktur | B41: Rp juta | C41: 65000 | D41: 68000
A42: Pengelolaan air tambang (dewatering) | B42: Rp juta | C42: 48000 | D42: 52000
A43: Survei, geologi & grade control | B43: Rp juta | C43: 18000 | D43: 19000
A44: Gaji & tunjangan karyawan site | B44: Rp juta | C44: 210000 | D44: 225000
A45: Camp, mess & katering | B45: Rp juta | C45: 55000 | D45: 58000
A46: K3 / HSE | B46: Rp juta | C46: 22000 | D46: 24000
A47: Lingkungan & reklamasi (provisi) | B47: Rp juta | C47: 60000 | D47: 66000
A48: PPM / CSR | B48: Rp juta | C48: 30000 | D48: 33000
A49: Iuran tetap & kompensasi lahan | B49: Rp juta | C49: 25000 | D49: 27000
A50: 5. PENYUSUTAN & AMORTISASI (Rp juta)
A51: Penyusutan aset tetap (produksi) | B51: Rp juta | C51: 310000 | D51: 335000
A52: Amortisasi properti pertambangan | B52: Rp juta | C52: 140000 | D52: 150000
A53: Amortisasi biaya pengupasan tangguhan | B53: Rp juta | C53: 90000 | D53: 95000
A54: Penyusutan aset kantor (G&A) | B54: Rp juta | C54: 12000 | D54: 12500
A55: 6. BEBAN PENJUALAN
A56: Porsi ekspor dijual CIF | B56: % | C56: 0.2 | D56: 0.15
A57: Tarif pengapalan laut (CIF) | B57: USD/ton | C57: 13 | D57: 11.5
A58: Komisi agen penjualan ekspor | B58: % pendapatan ekspor | C58: 0.01 | D58: 0.01
A59: Surveyor independen & analisa kualitas | B59: USD/ton | C59: 0.18 | D59: 0.18
A60: Demurrage | B60: Rp juta | C60: 38000 | D60: 29000
A61: Dokumen ekspor & pungutan | B61: Rp juta | C61: 14000 | D61: 15000
A62: Pemasaran & promosi | B62: Rp juta | C62: 6000 | D62: 6500
A63: 7. BEBAN UMUM & ADMINISTRASI (Rp juta)
A64: Gaji & tunjangan kantor pusat | B64: Rp juta | C64: 185000 | D64: 198000
A65: Jasa profesional (hukum, audit, konsultan) | B65: Rp juta | C65: 42000 | D65: 45000
A66: Sewa kantor | B66: Rp juta | C66: 18000 | D66: 18500
A67: Perjalanan dinas | B67: Rp juta | C67: 16000 | D67: 15000
A68: Asuransi | B68: Rp juta | C68: 21000 | D68: 22000
A69: Pajak, perizinan & iuran | B69: Rp juta | C69: 12000 | D69: 13000
A70: Teknologi informasi & komunikasi | B70: Rp juta | C70: 15000 | D70: 17000
A71: Beban umum lainnya | B71: Rp juta | C71: 20000 | D71: 19000
A72: 8. PENDAPATAN JASA & LAIN-LAIN
A73: Pendapatan jasa pelabuhan/hauling pihak ketiga | B73: Rp juta | C73: 85000 | D73: 92000
A74: Bunga deposito (atas kas awal tahun) | B74: % | C74: 0.035 | D74: 0.0325 | E74: Dihitung atas saldo awal untuk hindari circular
A75: Laba (rugi) selisih kurs | B75: Rp juta | C75: 25000 | D75: -18000
A76: Bagian laba entitas asosiasi | B76: Rp juta | C76: 12000 | D76: 14000
A77: Pendapatan (beban) lain-lain – neto | B77: Rp juta | C77: 5000 | D77: -3000
A78: 9. PENDANAAN, PAJAK & DIVIDEN
A79: Penarikan pinjaman bank jangka panjang | B79: Rp juta | C79: 0 | D79: 400000
A80: Pembayaran pokok pinjaman | B80: Rp juta | C80: 350000 | D80: 300000
A81: Jadwal pembayaran pokok tahun berikutnya | B81: Rp juta | C81: 300000 | D81: 320000 | E81: Untuk klasifikasi bagian lancar
A82: Saldo pinjaman bank jangka panjang akhir tahun | B82: Rp juta | C82: ='A3 Neraca Contoh'!C35+'A3 Neraca Contoh'!C38+C79-C80 | D82: =C82+D79-D80
A83: Pinjaman bank jangka pendek (akhir tahun) | B83: Rp juta | C83: 100000 | D83: 150000
A84: Suku bunga pinjaman rata-rata | B84: % | C84: 0.08 | D84: 0.0775
A85: Tarif pajak penghasilan badan | B85: % | C85: 0.22 | D85: 0.22 | E85: UU HPP
A86: Rasio pembayaran dividen (atas laba tahun lalu) | B86: % | C86: 0.4 | D86: 0.4
A87: Laba bersih tahun sebelumnya | B87: Rp juta | C87: 2100000 | D87: ='A2 Laba Rugi Contoh'!C89 | E87: 2024: laba 2023 (input); 2025: dari A2
A88: Dividen tunai dibayar | B88: Rp juta | C88: =C87*C86 | D88: =D87*D86
A89: 10. BELANJA MODAL (Rp juta)
A90: Capex aset tetap | B90: Rp juta | C90: 420000 | D90: 560000
A91: Penambahan properti pertambangan | B91: Rp juta | C91: 150000 | D91: 180000
A92: Biaya pengupasan tangguhan dikapitalisasi | B92: Rp juta | C92: 110000 | D92: 100000
A93: Belanja eksplorasi & evaluasi | B93: Rp juta | C93: 5000 | D93: 10000
A94: 11. MODAL KERJA & POS NERACA LAIN
A95: Hari piutang (DSO) | B95: hari | C95: 30 | D95: 32
A96: Hari utang usaha (DPO) atas biaya kas produksi | B96: hari | C96: 45 | D96: 48
A97: Persediaan suku cadang & BBM | B97: Rp juta | C97: 210000 | D97: 225000
A98: Piutang lain-lain | B98: Rp juta | C98: 60000 | D98: 58000
A99: Uang muka & biaya dibayar dimuka | B99: Rp juta | C99: 95000 | D99: 102000
A100: Pajak dibayar dimuka | B100: Rp juta | C100: 140000 | D100: 150000
A101: Beban akrual | B101: Rp juta | C101: 150000 | D101: 162000
A102: Utang royalti (bulan royalti) | B102: bulan | C102: 1 | D102: 1
...

Sheet A2 Laba Rugi Contoh
A1: PT Batubara Contoh Tbk (fiktif) – Laporan Laba Rugi Konsolidasian
A2: Untuk tahun yang berakhir 31 Desember | dalam Rp juta | angka ilustratif, bukan data emiten sebenarnya
A5: Uraian | B5: Basis perhitungan | C5: FY2024 | D5: FY2025 | E5: Δ% YoY | F5: % thd pendapatan FY2025
A6: PENDAPATAN
A7: Penjualan batubara – Ekspor | B7: Vol × ASP × kurs | C7: ='A1 Asumsi Contoh'!C18*'A1 Asumsi Contoh'!C9*'A1 Asumsi Contoh'!C7/1000000 | D7: ='A1 Asumsi Contoh'!D18*'A1 Asumsi Contoh'!D9*'A1 Asumsi Contoh'!D7/1000000 | E7: =IFERROR((D7-C7)/ABS(C7),"") | F7: =IFERROR(D7/D$13,"")
A8: Penjualan batubara – Domestik DMO | B8: Vol × ASP × kurs | C8: ='A1 Asumsi Contoh'!C19*'A1 Asumsi Contoh'!C10*'A1 Asumsi Contoh'!C7/1000000 | D8: ='A1 Asumsi Contoh'!D19*'A1 Asumsi Contoh'!D10*'A1 Asumsi Contoh'!D7/1000000 | E8: =IFERROR((D8-C8)/ABS(C8),"") | F8: =IFERROR(D8/D$13,"")
A9: Penjualan batubara – Domestik non-DMO | B9: Vol × ASP × kurs | C9: ='A1 Asumsi Contoh'!C20*'A1 Asumsi Contoh'!C11*'A1 Asumsi Contoh'!C7/1000000 | D9: ='A1 Asumsi Contoh'!D20*'A1 Asumsi Contoh'!D11*'A1 Asumsi Contoh'!D7/1000000 | E9: =IFERROR((D9-C9)/ABS(C9),"") | F9: =IFERROR(D9/D$13,"")
A10: Subtotal penjualan batubara | C10: =SUM(C7:C9) | D10: =SUM(D7:D9) | E10: =IFERROR((D10-C10)/ABS(C10),"") | F10: =IFERROR(D10/D$13,"")
A11: Penyesuaian harga / penalti kualitas | B11: % × penjualan | C11: =-C10*'A1 Asumsi Contoh'!C38 | D11: =-D10*'A1 Asumsi Contoh'!D38 | E11: =IFERROR((D11-C11)/ABS(C11),"") | F11: =IFERROR(D11/D$13,"")
A12: Pendapatan jasa pelabuhan/hauling pihak ketiga | C12: ='A1 Asumsi Contoh'!C73 | D12: ='A1 Asumsi Contoh'!D73 | E12: =IFERROR((D12-C12)/ABS(C12),"") | F12: =IFERROR(D12/D$13,"")
A13: PENDAPATAN BERSIH | C13: =C10+C11+C12 | D13: =D10+D11+D12 | E13: =IFERROR((D13-C13)/ABS(C13),"") | F13: =IFERROR(D13/D$13,"")
A15: BEBAN POKOK PENDAPATAN
A16: A. Biaya penambangan
A17: Pengupasan OB – jasa kontraktor | B17: bcm × tarif × kurs | C17: ='A1 Asumsi Contoh'!C16*'A1 Asumsi Contoh'!C27*'A1 Asumsi Contoh'!C7/1000000 | D17: ='A1 Asumsi Contoh'!D16*'A1 Asumsi Contoh'!D27*'A1 Asumsi Contoh'!D7/1000000 | E17: =IFERROR((D17-C17)/ABS(C17),"") | F17: =IFERROR(D17/D$13,"")
A18: Bahan bakar (BBM) | B18: bcm × L/bcm × Rp/L | C18: ='A1 Asumsi Contoh'!C16*'A1 Asumsi Contoh'!C29*'A1 Asumsi Contoh'!C30/1000000 | D18: ='A1 Asumsi Contoh'!D16*'A1 Asumsi Contoh'!D29*'A1 Asumsi Contoh'!D30/1000000 | E18: =IFERROR((D18-C18)/ABS(C18),"") | F18: =IFERROR(D18/D$13,"")
A19: Peledakan (drill & blast) | B19: bcm × % × tarif | C19: ='A1 Asumsi Contoh'!C16*'A1 Asumsi Contoh'!C31*'A1 Asumsi Contoh'!C32*'A1 Asumsi Contoh'!C7/1000000 | D19: ='A1 Asumsi Contoh'!D16*'A1 Asumsi Contoh'!D31*'A1 Asumsi Contoh'!D32*'A1 Asumsi Contoh'!D7/1000000 | E19: =IFERROR((D19-C19)/ABS(C19),"") | F19: =IFERROR(D19/D$13,"")
A20: Penggalian batubara (coal getting) | B20: ton × tarif | C20: ='A1 Asumsi Contoh'!C14*'A1 Asumsi Contoh'!C28*'A1 Asumsi Contoh'!C7/1000000 | D20: ='A1 Asumsi Contoh'!D14*'A1 Asumsi Contoh'!D28*'A1 Asumsi Contoh'!D7/1000000 | E20: =IFERROR((D20-C20)/ABS(C20),"") | F20: =IFERROR(D20/D$13,"")
A21: Sewa alat berat & sarana penunjang | C21: ='A1 Asumsi Contoh'!C40 | D21: ='A1 Asumsi Contoh'!D40 | E21: =IFERROR((D21-C21)/ABS(C21),"") | F21: =IFERROR(D21/D$13,"")
A22: Pemeliharaan jalan tambang & infrastruktur | C22: ='A1 Asumsi Contoh'!C41 | D22: ='A1 Asumsi Contoh'!D41 | E22: =IFERROR((D22-C22)/ABS(C22),"") | F22: =IFERROR(D22/D$13,"")
A23: Pengelolaan air tambang (dewatering) | C23: ='A1 Asumsi Contoh'!C42 | D23: ='A1 Asumsi Contoh'!D42 | E23: =IFERROR((D23-C23)/ABS(C23),"") | F23: =IFERROR(D23/D$13,"")
A24: Survei, geologi & grade control | C24: ='A1 Asumsi Contoh'!C43 | D24: ='A1 Asumsi Contoh'!D43 | E24: =IFERROR((D24-C24)/ABS(C24),"") | F24: =IFERROR(D24/D$13,"")
A25: Subtotal biaya penambangan | C25: =SUM(C17:C24) | D25: =SUM(D17:D24) | E25: =IFERROR((D25-C25)/ABS(C25),"") | F25: =IFERROR(D25/D$13,"")
A26: B. Pengolahan & logistik
A27: Crushing & pengolahan (CPP) | B27: ton produksi × tarif | C27: ='A1 Asumsi Contoh'!C14*'A1 Asumsi Contoh'!C33*'A1 Asumsi Contoh'!C7/1000000 | D27: ='A1 Asumsi Contoh'!D14*'A1 Asumsi Contoh'!D33*'A1 Asumsi Contoh'!D7/1000000 | E27: =IFERROR((D27-C27)/ABS(C27),"") | F27: =IFERROR(D27/D$13,"")
A28: Hauling tambang – pelabuhan | B28: ton × km × tarif | C28: ='A1 Asumsi Contoh'!C14*'A1 Asumsi Contoh'!C17*'A1 Asumsi Contoh'!C34*'A1 Asumsi Contoh'!C7/1000000 | D28: ='A1 Asumsi Contoh'!D14*'A1 Asumsi Contoh'!D17*'A1 Asumsi Contoh'!D34*'A1 Asumsi Contoh'!D7/1000000 | E28: =IFERROR((D28-C28)/ABS(C28),"") | F28: =IFERROR(D28/D$13,"")
A29: Penanganan pelabuhan & stockpile | B29: ton jual × tarif | C29: ='A1 Asumsi Contoh'!C21*'A1 Asumsi Contoh'!C35*'A1 Asumsi Contoh'!C7/1000000 | D29: ='A1 Asumsi Contoh'!D21*'A1 Asumsi Contoh'!D35*'A1 Asumsi Contoh'!D7/1000000 | E29: =IFERROR((D29-C29)/ABS(C29),"") | F29: =IFERROR(D29/D$13,"")
A30: Tongkang & transshipment (barging) | B30: ton jual × tarif | C30: ='A1 Asumsi Contoh'!C21*'A1 Asumsi Contoh'!C36*'A1 Asumsi Contoh'!C7/1000000 | D30: ='A1 Asumsi Contoh'!D21*'A1 Asumsi Contoh'!D36*'A1 Asumsi Contoh'!D7/1000000 | E30: =IFERROR((D30-C30)/ABS(C30),"") | F30: =IFERROR(D30/D$13,"")
A31: Subtotal pengolahan & logistik | C31: =SUM(C27:C30) | D31: =SUM(D27:D30) | E31: =IFERROR((D31-C31)/ABS(C31),"") | F31: =IFERROR(D31/D$13,"")
A32: C. Royalti
A33: Royalti / PNBP (DHPB) | B33: penjualan neto × tarif | C33: =(C10+C11)*'A1 Asumsi Contoh'!C37 | D33: =(D10+D11)*'A1 Asumsi Contoh'!D37 | E33: =IFERROR((D33-C33)/ABS(C33),"") | F33: =IFERROR(D33/D$13,"")
A34: D. Biaya tidak langsung tambang (site overhead)
A35: Gaji & tunjangan karyawan site | C35: ='A1 Asumsi Contoh'!C44 | D35: ='A1 Asumsi Contoh'!D44 | E35: =IFERROR((D35-C35)/ABS(C35),"") | F35: =IFERROR(D35/D$13,"")
A36: Camp, mess & katering | C36: ='A1 Asumsi Contoh'!C45 | D36: ='A1 Asumsi Contoh'!D45 | E36: =IFERROR((D36-C36)/ABS(C36),"") | F36: =IFERROR(D36/D$13,"")
A37: K3 / HSE | C37: ='A1 Asumsi Contoh'!C46 | D37: ='A1 Asumsi Contoh'!D46 | E37: =IFERROR((D37-C37)/ABS(C37),"") | F37: =IFERROR(D37/D$13,"")
A38: Lingkungan & reklamasi (provisi) | C38: ='A1 Asumsi Contoh'!C47 | D38: ='A1 Asumsi Contoh'!D47 | E38: =IFERROR((D38-C38)/ABS(C38),"") | F38: =IFERROR(D38/D$13,"")
A39: PPM / CSR | C39: ='A1 Asumsi Contoh'!C48 | D39: ='A1 Asumsi Contoh'!D48 | E39: =IFERROR((D39-C39)/ABS(C39),"") | F39: =IFERROR(D39/D$13,"")
A40: Iuran tetap & kompensasi lahan | C40: ='A1 Asumsi Contoh'!C49 | D40: ='A1 Asumsi Contoh'!D49 | E40: =IFERROR((D40-C40)/ABS(C40),"") | F40: =IFERROR(D40/D$13,"")
A41: Subtotal overhead site | C41: =SUM(C35:C40) | D41: =SUM(D35:D40) | E41: =IFERROR((D41-C41)/ABS(C41),"") | F41: =IFERROR(D41/D$13,"")
A42: E. Penyusutan & amortisasi
A43: Penyusutan aset tetap | C43: ='A1 Asumsi Contoh'!C51 | D43: ='A1 Asumsi Contoh'!D51 | E43: =IFERROR((D43-C43)/ABS(C43),"") | F43: =IFERROR(D43/D$13,"")
A44: Amortisasi properti pertambangan | C44: ='A1 Asumsi Contoh'!C52 | D44: ='A1 Asumsi Contoh'!D52 | E44: =IFERROR((D44-C44)/ABS(C44),"") | F44: =IFERROR(D44/D$13,"")
A45: Amortisasi biaya pengupasan tangguhan | C45: ='A1 Asumsi Contoh'!C53 | D45: ='A1 Asumsi Contoh'!D53 | E45: =IFERROR((D45-C45)/ABS(C45),"") | F45: =IFERROR(D45/D$13,"")
A46: Subtotal penyusutan & amortisasi | C46: =SUM(C43:C45) | D46: =SUM(D43:D45) | E46: =IFERROR((D46-C46)/ABS(C46),"") | F46: =IFERROR(D46/D$13,"")
A47: Total biaya produksi | C47: =C25+C31+C33+C41+C46 | D47: =D25+D31+D33+D41+D46 | E47: =IFERROR((D47-C47)/ABS(C47),"") | F47: =IFERROR(D47/D$13,"")
A48: Perubahan persediaan batubara (awal – akhir) | B48: dari neraca | C48: ='A3 Neraca Contoh'!C11-'A3 Neraca Contoh'!D11 | D48: ='A3 Neraca Contoh'!D11-'A3 Neraca Contoh'!E11 | E48: =IFERROR((D48-C48)/ABS(C48),"") | F48: =IFERROR(D48/D$13,"")
A49: BEBAN POKOK PENDAPATAN | C49: =C47+C48 | D49: =D47+D48 | E49: =IFERROR((D49-C49)/ABS(C49),"") | F49: =IFERROR(D49/D$13,"")
A51: LABA KOTOR | C51: =C13-C49 | D51: =D13-D49 | E51: =IFERROR((D51-C51)/ABS(C51),"") | F51: =IFERROR(D51/D$13,"")
A52: Marjin laba kotor | C52: =IFERROR(C51/C13,0) | D52: =IFERROR(D51/D13,0)
A54: BEBAN USAHA
A55: Beban penjualan
A56: Pengapalan laut (penjualan CIF) | B56: ton CIF × tarif | C56: ='A1 Asumsi Contoh'!C18*'A1 Asumsi Contoh'!C56*'A1 Asumsi Contoh'!C57*'A1 Asumsi Contoh'!C7/1000000 | D56: ='A1 Asumsi Contoh'!D18*'A1 Asumsi Contoh'!D56*'A1 Asumsi Contoh'!D57*'A1 Asumsi Contoh'!D7/1000000 | E56: =IFERROR((D56-C56)/ABS(C56),"") | F56: =IFERROR(D56/D$13,"")
A57: Komisi agen penjualan | B57: % × ekspor | C57: =C7*'A1 Asumsi Contoh'!C58 | D57: =D7*'A1 Asumsi Contoh'!D58 | E57: =IFERROR((D57-C57)/ABS(C57),"") | F57: =IFERROR(D57/D$13,"")
A58: Surveyor independen & analisa kualitas | B58: ton jual × tarif | C58: ='A1 Asumsi Contoh'!C21*'A1 Asumsi Contoh'!C59*'A1 Asumsi Contoh'!C7/1000000 | D58: ='A1 Asumsi Contoh'!D21*'A1 Asumsi Contoh'!D59*'A1 Asumsi Contoh'!D7/1000000 | E58: =IFERROR((D58-C58)/ABS(C58),"") | F58: =IFERROR(D58/D$13,"")
A59: Demurrage | C59: ='A1 Asumsi Contoh'!C60 | D59: ='A1 Asumsi Contoh'!D60 | E59: =IFERROR((D59-C59)/ABS(C59),"") | F59: =IFERROR(D59/D$13,"")
A60: Dokumen ekspor & pungutan | C60: ='A1 Asumsi Contoh'!C61 | D60: ='A1 Asumsi Contoh'!D61 | E60: =IFERROR((D60-C60)/ABS(C60),"") | F60: =IFERROR(D60/D$13,"")
A61: Pemasaran & promosi | C61: ='A1 Asumsi Contoh'!C62 | D61: ='A1 Asumsi Contoh'!D62 | E61: =IFERROR((D61-C61)/ABS(C61),"") | F61: =IFERROR(D61/D$13,"")
A62: Subtotal beban penjualan | C62: =SUM(C56:C61) | D62: =SUM(D56:D61) | E62: =IFERROR((D62-C62)/ABS(C62),"") | F62: =IFERROR(D62/D$13,"")
A63: Beban umum & administrasi
A64: Gaji & tunjangan kantor pusat | C64: ='A1 Asumsi Contoh'!C64 | D64: ='A1 Asumsi Contoh'!D64 | E64: =IFERROR((D64-C64)/ABS(C64),"") | F64: =IFERROR(D64/D$13,"")
A65: Jasa profesional | C65: ='A1 Asumsi Contoh'!C65 | D65: ='A1 Asumsi Contoh'!D65 | E65: =IFERROR((D65-C65)/ABS(C65),"") | F65: =IFERROR(D65/D$13,"")
A66: Sewa kantor | C66: ='A1 Asumsi Contoh'!C66 | D66: ='A1 Asumsi Contoh'!D66 | E66: =IFERROR((D66-C66)/ABS(C66),"") | F66: =IFERROR(D66/D$13,"")
A67: Perjalanan dinas | C67: ='A1 Asumsi Contoh'!C67 | D67: ='A1 Asumsi Contoh'!D67 | E67: =IFERROR((D67-C67)/ABS(C67),"") | F67: =IFERROR(D67/D$13,"")
A68: Asuransi | C68: ='A1 Asumsi Contoh'!C68 | D68: ='A1 Asumsi Contoh'!D68 | E68: =IFERROR((D68-C68)/ABS(C68),"") | F68: =IFERROR(D68/D$13,"")
A69: Pajak, perizinan & iuran | C69: ='A1 Asumsi Contoh'!C69 | D69: ='A1 Asumsi Contoh'!D69 | E69: =IFERROR((D69-C69)/ABS(C69),"") | F69: =IFERROR(D69/D$13,"")
A70: Teknologi informasi & komunikasi | C70: ='A1 Asumsi Contoh'!C70 | D70: ='A1 Asumsi Contoh'!D70 | E70: =IFERROR((D70-C70)/ABS(C70),"") | F70: =IFERROR(D70/D$13,"")
A71: Penyusutan aset kantor | C71: ='A1 Asumsi Contoh'!C54 | D71: ='A1 Asumsi Contoh'!D54 | E71: =IFERROR((D71-C71)/ABS(C71),"") | F71: =IFERROR(D71/D$13,"")
A72: Beban umum lainnya | C72: ='A1 Asumsi Contoh'!C71 | D72: ='A1 Asumsi Contoh'!D71 | E72: =IFERROR((D72-C72)/ABS(C72),"") | F72: =IFERROR(D72/D$13,"")
A73: Subtotal beban umum & administrasi | C73: =SUM(C64:C72) | D73: =SUM(D64:D72) | E73: =IFERROR((D73-C73)/ABS(C73),"") | F73: =IFERROR(D73/D$13,"")
A74: TOTAL BEBAN USAHA | C74: =C62+C73 | D74: =D62+D73 | E74: =IFERROR((D74-C74)/ABS(C74),"") | F74: =IFERROR(D74/D$13,"")
A76: LABA USAHA | C76: =C51-C74 | D76: =D51-D74 | E76: =IFERROR((D76-C76)/ABS(C76),"") | F76: =IFERROR(D76/D$13,"")
A77: Marjin laba usaha | C77: =IFERROR(C76/C13,0) | D77: =IFERROR(D76/D13,0)
A79: PENDAPATAN (BEBAN) LAIN-LAIN
A80: Pendapatan bunga | B80: kas awal × bunga | C80: ='A3 Neraca Contoh'!C8*'A1 Asumsi Contoh'!C74 | D80: ='A3 Neraca Contoh'!D8*'A1 Asumsi Contoh'!D74 | E80: =IFERROR((D80-C80)/ABS(C80),"") | F80: =IFERROR(D80/D$13,"")
A81: Beban keuangan (bunga pinjaman) | B81: saldo rata-rata × bunga | C81: =-((('A3 Neraca Contoh'!C35+'A3 Neraca Contoh'!C38+'A3 Neraca Contoh'!D35+'A3 Neraca Contoh'!D38)/2)+(('A3 Neraca Contoh'!C34+'A3 Neraca Contoh'!D34)/2))*'A1 Asumsi Contoh'!C84 | D81: =-((('A3 Neraca Contoh'!D35+'A3 Neraca Contoh'!D38+'A3 Neraca Contoh'!E35+'A3 Neraca Contoh'!E38)/2)+(('A3 Neraca Contoh'!D34+'A3 Neraca Contoh'!E34)/2))*'A1 Asumsi Contoh'!D84 | E81: =IFERROR((D81-C81)/ABS(C81),"") | F81: =IFERROR(D81/D$13,"")
A82: Laba (rugi) selisih kurs | C82: ='A1 Asumsi Contoh'!C75 | D82: ='A1 Asumsi Contoh'!D75 | E82: =IFERROR((D82-C82)/ABS(C82),"") | F82: =IFERROR(D82/D$13,"")
A83: Bagian laba entitas asosiasi | C83: ='A1 Asumsi Contoh'!C76 | D83: ='A1 Asumsi Contoh'!D76 | E83: =IFERROR((D83-C83)/ABS(C83),"") | F83: =IFERROR(D83/D$13,"")
A84: Lain-lain – neto | C84: ='A1 Asumsi Contoh'!C77 | D84: ='A1 Asumsi Contoh'!D77 | E84: =IFERROR((D84-C84)/ABS(C84),"") | F84: =IFERROR(D84/D$13,"")
A85: Jumlah pendapatan (beban) lain-lain | C85: =SUM(C80:C84) | D85: =SUM(D80:D84) | E85: =IFERROR((D85-C85)/ABS(C85),"") | F85: =IFERROR(D85/D$13,"")
A87: LABA SEBELUM PAJAK | C87: =C76+C85 | D87: =D76+D85 | E87: =IFERROR((D87-C87)/ABS(C87),"") | F87: =IFERROR(D87/D$13,"")
A88: Beban pajak penghasilan | B88: LSP × tarif (disederhanakan) | C88: =MAX(0,C87)*'A1 Asumsi Contoh'!C85 | D88: =MAX(0,D87)*'A1 Asumsi Contoh'!D85 | E88: =IFERROR((D88-C88)/ABS(C88),"") | F88: =IFERROR(D88/D$13,"")
A89: LABA BERSIH TAHUN BERJALAN | C89: =C87-C88 | D89: =D87-D88 | E89: =IFERROR((D89-C89)/ABS(C89),"") | F89: =IFERROR(D89/D$13,"")
A90: Marjin laba bersih | C90: =IFERROR(C89/C13,0) | D90: =IFERROR(D89/D13,0)
A92: MEMO
A93: EBITDA (laba usaha + penyusutan & amortisasi) | C93: =C76+C46+C71 | D93: =D76+D46+D71 | E93: =IFERROR((D93-C93)/ABS(C93),"") | F93: =IFERROR(D93/D$13,"")
A94: Marjin EBITDA | C94: =IFERROR(C93/C13,0) | D94: =IFERROR(D93/D13,0)
A95: Biaya produksi per ton untuk valuasi persediaan | B95: Rp/ton | C95: =(C25+C27+C28+C41+C46)*1000000/'A1 Asumsi Contoh'!C14 | D95: =(D25+D27+D28+D41+D46)*1000000/'A1 Asumsi Contoh'!D14

Sheet A3 Neraca Contoh
A1: PT Batubara Contoh Tbk (fiktif) – Laporan Posisi Keuangan (Neraca) Konsolidasian
A2: Per 31 Desember | dalam Rp juta | kolom 2023 = saldo awal (input); 2024–2025 dihitung dari driver & arus kas
A5: Uraian | B5: Basis | C5: 31 Des 2023 | D5: 31 Des 2024 | E5: 31 Des 2025
A6: ASET
A7: Aset lancar
A8: Kas dan setara kas | C8: 1450000 | D8: ='A4 Arus Kas Contoh'!C46 | E8: ='A4 Arus Kas Contoh'!D46
A9: Piutang usaha | B9: DSO | C9: 850000 | D9: ='A2 Laba Rugi Contoh'!C13*'A1 Asumsi Contoh'!C95/365 | E9: ='A2 Laba Rugi Contoh'!D13*'A1 Asumsi Contoh'!D95/365
A10: Piutang lain-lain | C10: 55000 | D10: ='A1 Asumsi Contoh'!C98 | E10: ='A1 Asumsi Contoh'!D98
A11: Persediaan batubara | B11: stok × biaya/ton | C11: 243000 | D11: ='A1 Asumsi Contoh'!C24*'A2 Laba Rugi Contoh'!C95/1000000 | E11: ='A1 Asumsi Contoh'!D24*'A2 Laba Rugi Contoh'!D95/1000000
A12: Persediaan suku cadang & BBM | C12: 195000 | D12: ='A1 Asumsi Contoh'!C97 | E12: ='A1 Asumsi Contoh'!D97
A13: Uang muka & biaya dibayar dimuka | C13: 90000 | D13: ='A1 Asumsi Contoh'!C99 | E13: ='A1 Asumsi Contoh'!D99
A14: Pajak dibayar dimuka | C14: 130000 | D14: ='A1 Asumsi Contoh'!C100 | E14: ='A1 Asumsi Contoh'!D100
A15: Jumlah aset lancar | C15: =SUM(C8:C14) | D15: =SUM(D8:D14) | E15: =SUM(E8:E14)
A16: Aset tidak lancar
A17: Aset tetap – neto (termasuk aset hak guna) | C17: 2650000 | D17: =C17+'A1 Asumsi Contoh'!C90-'A1 Asumsi Contoh'!C51-'A1 Asumsi Contoh'!C54 | E17: =D17+'A1 Asumsi Contoh'!D90-'A1 Asumsi Contoh'!D51-'A1 Asumsi Contoh'!D54
A18: Properti pertambangan – neto | C18: 1450000 | D18: =C18+'A1 Asumsi Contoh'!C91-'A1 Asumsi Contoh'!C52 | E18: =D18+'A1 Asumsi Contoh'!D91-'A1 Asumsi Contoh'!D52
A19: Aset eksplorasi & evaluasi | C19: 80000 | D19: =C19+'A1 Asumsi Contoh'!C93 | E19: =D19+'A1 Asumsi Contoh'!D93
A20: Biaya pengupasan tangguhan – neto | C20: 420000 | D20: =C20+'A1 Asumsi Contoh'!C92-'A1 Asumsi Contoh'!C53 | E20: =D20+'A1 Asumsi Contoh'!D92-'A1 Asumsi Contoh'!D53
A21: Investasi pada entitas asosiasi | C21: 180000 | D21: =C21+'A2 Laba Rugi Contoh'!C83 | E21: =D21+'A2 Laba Rugi Contoh'!D83
A22: Dana jaminan reklamasi (dibatasi) | C22: 110000 | D22: ='A1 Asumsi Contoh'!C106 | E22: ='A1 Asumsi Contoh'!D106
A23: Aset pajak tangguhan | C23: 55000 | D23: =C23 | E23: =D23
A24: Aset tidak lancar lainnya | C24: 38000 | D24: ='A1 Asumsi Contoh'!C107 | E24: ='A1 Asumsi Contoh'!D107
A25: Jumlah aset tidak lancar | C25: =SUM(C17:C24) | D25: =SUM(D17:D24) | E25: =SUM(E17:E24)
A26: JUMLAH ASET | C26: =C15+C25 | D26: =D15+D25 | E26: =E15+E25
A28: LIABILITAS
A29: Liabilitas jangka pendek
A30: Utang usaha (kontraktor & pemasok) | B30: DPO | C30: 620000 | D30: =('A2 Laba Rugi Contoh'!C25+'A2 Laba Rugi Contoh'!C31+'A2 Laba Rugi Contoh'!C41-'A2 Laba Rugi Contoh'!C38)*'A1 Asumsi Contoh'!C96/365 | E30: =('A2 Laba Rugi Contoh'!D25+'A2 Laba Rugi Contoh'!D31+'A2 Laba Rugi Contoh'!D41-'A2 Laba Rugi Contoh'!D38)*'A1 Asumsi Contoh'!D96/365
A31: Utang royalti | C31: 70000 | D31: ='A2 Laba Rugi Contoh'!C33/12*'A1 Asumsi Contoh'!C102 | E31: ='A2 Laba Rugi Contoh'!D33/12*'A1 Asumsi Contoh'!D102
A32: Beban akrual | C32: 140000 | D32: ='A1 Asumsi Contoh'!C101 | E32: ='A1 Asumsi Contoh'!D101
A33: Utang pajak | C33: 150000 | D33: ='A2 Laba Rugi Contoh'!C88*'A1 Asumsi Contoh'!C103 | E33: ='A2 Laba Rugi Contoh'!D88*'A1 Asumsi Contoh'!D103
A34: Pinjaman bank jangka pendek | C34: 100000 | D34: ='A1 Asumsi Contoh'!C83 | E34: ='A1 Asumsi Contoh'!D83
A35: Bagian lancar pinjaman bank jangka panjang | C35: 350000 | D35: ='A1 Asumsi Contoh'!C81 | E35: ='A1 Asumsi Contoh'!D81
A36: Jumlah liabilitas jangka pendek | C36: =SUM(C30:C35) | D36: =SUM(D30:D35) | E36: =SUM(E30:E35)
A37: Liabilitas jangka panjang
A38: Pinjaman bank jangka panjang – setelah bagian lancar | C38: 1550000 | D38: ='A1 Asumsi Contoh'!C82-D35 | E38: ='A1 Asumsi Contoh'!D82-E35
A39: Provisi reklamasi & penutupan tambang | C39: 380000 | D39: =C39+'A2 Laba Rugi Contoh'!C38-'A1 Asumsi Contoh'!C104 | E39: =D39+'A2 Laba Rugi Contoh'!D38-'A1 Asumsi Contoh'!D104
A40: Liabilitas imbalan kerja | C40: 170000 | D40: ='A1 Asumsi Contoh'!C105 | E40: ='A1 Asumsi Contoh'!D105
A41: Liabilitas pajak tangguhan | C41: 120000 | D41: =C41 | E41: =D41
A42: Jumlah liabilitas jangka panjang | C42: =SUM(C38:C41) | D42: =SUM(D38:D41) | E42: =SUM(E38:E41)
A43: JUMLAH LIABILITAS | C43: =C36+C42 | D43: =D36+D42 | E43: =E36+E42
A45: EKUITAS
A46: Modal saham | C46: 1150000 | D46: =C46 | E46: =D46
A47: Tambahan modal disetor | C47: 350000 | D47: =C47 | E47: =D47
A48: Saldo laba | B48: awal + laba – dividen | C48: 2671000 | D48: =C48+'A2 Laba Rugi Contoh'!C89-'A1 Asumsi Contoh'!C88 | E48: =D48+'A2 Laba Rugi Contoh'!D89-'A1 Asumsi Contoh'!D88
A49: Penghasilan komprehensif lain | C49: 25000 | D49: =C49 | E49: =D49
A50: Kepentingan nonpengendali | C50: 150000 | D50: =C50 | E50: =D50
A51: JUMLAH EKUITAS | C51: =SUM(C46:C50) | D51: =SUM(D46:D50) | E51: =SUM(E46:E50)
A53: JUMLAH LIABILITAS DAN EKUITAS | C53: =C43+C51 | D53: =D43+D51 | E53: =E43+E51
A54: Cek keseimbangan (harus 0) | C54: =ROUND(C26-C53,0) | D54: =ROUND(D26-D53,0) | E54: =ROUND(E26-E53,0)

Sheet A4 Arus Kas Contoh
A1: PT Batubara Contoh Tbk (fiktif) – Laporan Arus Kas Konsolidasian
A2: Untuk tahun yang berakhir 31 Desember | dalam Rp juta | metode tidak langsung + rekonsiliasi metode langsung
A5: Uraian | B5: Basis | C5: FY2024 | D5: FY2025
A6: ARUS KAS DARI AKTIVITAS OPERASI (metode tidak langsung)
A7: Laba bersih tahun berjalan | C7: ='A2 Laba Rugi Contoh'!C89 | D7: ='A2 Laba Rugi Contoh'!D89
A8: Penyesuaian pos non-kas
A9: Penyusutan & amortisasi | C9: ='A2 Laba Rugi Contoh'!C46+'A2 Laba Rugi Contoh'!C71 | D9: ='A2 Laba Rugi Contoh'!D46+'A2 Laba Rugi Contoh'!D71
A10: Bagian laba entitas asosiasi | C10: =-'A2 Laba Rugi Contoh'!C83 | D10: =-'A2 Laba Rugi Contoh'!D83
A11: Kenaikan provisi reklamasi – neto | C11: =('A3 Neraca Contoh'!D39-'A3 Neraca Contoh'!C39) | D11: =('A3 Neraca Contoh'!E39-'A3 Neraca Contoh'!D39)
A12: Kenaikan liabilitas imbalan kerja | C12: =('A3 Neraca Contoh'!D40-'A3 Neraca Contoh'!C40) | D12: =('A3 Neraca Contoh'!E40-'A3 Neraca Contoh'!D40)
A13: Perubahan pajak tangguhan | C13: =-('A3 Neraca Contoh'!D23-'A3 Neraca Contoh'!C23)+('A3 Neraca Contoh'!D41-'A3 Neraca Contoh'!C41) | D13: =-('A3 Neraca Contoh'!E23-'A3 Neraca Contoh'!D23)+('A3 Neraca Contoh'!E41-'A3 Neraca Contoh'!D41)
A14: Perubahan modal kerja
A15: Piutang usaha | C15: =-('A3 Neraca Contoh'!D9-'A3 Neraca Contoh'!C9) | D15: =-('A3 Neraca Contoh'!E9-'A3 Neraca Contoh'!D9)
A16: Piutang lain-lain | C16: =-('A3 Neraca Contoh'!D10-'A3 Neraca Contoh'!C10) | D16: =-('A3 Neraca Contoh'!E10-'A3 Neraca Contoh'!D10)
A17: Persediaan batubara | C17: =-('A3 Neraca Contoh'!D11-'A3 Neraca Contoh'!C11) | D17: =-('A3 Neraca Contoh'!E11-'A3 Neraca Contoh'!D11)
A18: Persediaan suku cadang & BBM | C18: =-('A3 Neraca Contoh'!D12-'A3 Neraca Contoh'!C12) | D18: =-('A3 Neraca Contoh'!E12-'A3 Neraca Contoh'!D12)
A19: Uang muka & biaya dibayar dimuka | C19: =-('A3 Neraca Contoh'!D13-'A3 Neraca Contoh'!C13) | D19: =-('A3 Neraca Contoh'!E13-'A3 Neraca Contoh'!D13)
A20: Pajak dibayar dimuka | C20: =-('A3 Neraca Contoh'!D14-'A3 Neraca Contoh'!C14) | D20: =-('A3 Neraca Contoh'!E14-'A3 Neraca Contoh'!D14)
A21: Utang usaha | C21: =('A3 Neraca Contoh'!D30-'A3 Neraca Contoh'!C30) | D21: =('A3 Neraca Contoh'!E30-'A3 Neraca Contoh'!D30)
A22: Utang royalti | C22: =('A3 Neraca Contoh'!D31-'A3 Neraca Contoh'!C31) | D22: =('A3 Neraca Contoh'!E31-'A3 Neraca Contoh'!D31)
A23: Beban akrual | C23: =('A3 Neraca Contoh'!D32-'A3 Neraca Contoh'!C32) | D23: =('A3 Neraca Contoh'!E32-'A3 Neraca Contoh'!D32)
A24: Utang pajak | C24: =('A3 Neraca Contoh'!D33-'A3 Neraca Contoh'!C33) | D24: =('A3 Neraca Contoh'!E33-'A3 Neraca Contoh'!D33)
A25: Kas bersih dari aktivitas operasi | C25: =SUM(C7:C24) | D25: =SUM(D7:D24)
A27: ARUS KAS DARI AKTIVITAS INVESTASI
A28: Perolehan aset tetap | C28: =-(('A3 Neraca Contoh'!D17-'A3 Neraca Contoh'!C17)+'A2 Laba Rugi Contoh'!C43+'A2 Laba Rugi Contoh'!C71) | D28: =-(('A3 Neraca Contoh'!E17-'A3 Neraca Contoh'!D17)+'A2 Laba Rugi Contoh'!D43+'A2 Laba Rugi Contoh'!D71)
A29: Penambahan properti pertambangan | C29: =-(('A3 Neraca Contoh'!D18-'A3 Neraca Contoh'!C18)+'A2 Laba Rugi Contoh'!C44) | D29: =-(('A3 Neraca Contoh'!E18-'A3 Neraca Contoh'!D18)+'A2 Laba Rugi Contoh'!D44)
A30: Biaya pengupasan tangguhan | C30: =-(('A3 Neraca Contoh'!D20-'A3 Neraca Contoh'!C20)+'A2 Laba Rugi Contoh'!C45) | D30: =-(('A3 Neraca Contoh'!E20-'A3 Neraca Contoh'!D20)+'A2 Laba Rugi Contoh'!D45)
A31: Pengeluaran eksplorasi & evaluasi | C31: =-('A3 Neraca Contoh'!D19-'A3 Neraca Contoh'!C19) | D31: =-('A3 Neraca Contoh'!E19-'A3 Neraca Contoh'!D19)
A32: Penempatan dana jaminan reklamasi | C32: =-('A3 Neraca Contoh'!D22-'A3 Neraca Contoh'!C22) | D32: =-('A3 Neraca Contoh'!E22-'A3 Neraca Contoh'!D22)
A33: Aset tidak lancar lainnya | C33: =-('A3 Neraca Contoh'!D24-'A3 Neraca Contoh'!C24) | D33: =-('A3 Neraca Contoh'!E24-'A3 Neraca Contoh'!D24)
A34: Kas bersih untuk aktivitas investasi | C34: =SUM(C28:C33) | D34: =SUM(D28:D33)
A36: ARUS KAS DARI AKTIVITAS PENDANAAN
A37: Penerimaan (pembayaran) pinjaman jangka pendek – neto | C37: =('A3 Neraca Contoh'!D34-'A3 Neraca Contoh'!C34) | D37: =('A3 Neraca Contoh'!E34-'A3 Neraca Contoh'!D34)
A38: Penerimaan pinjaman bank jangka panjang | C38: ='A1 Asumsi Contoh'!C79 | D38: ='A1 Asumsi Contoh'!D79
A39: Pembayaran pinjaman bank jangka panjang | C39: =-'A1 Asumsi Contoh'!C80 | D39: =-'A1 Asumsi Contoh'!D80
A40: Pembayaran dividen | C40: =-'A1 Asumsi Contoh'!C88 | D40: =-'A1 Asumsi Contoh'!D88
A41: Perubahan ekuitas lainnya | C41: =('A3 Neraca Contoh'!D46-'A3 Neraca Contoh'!C46)+('A3 Neraca Contoh'!D47-'A3 Neraca Contoh'!C47)+('A3 Neraca Contoh'!D49-'A3 Neraca Contoh'!C49)+('A3 Neraca Contoh'!D50-'A3 Neraca Contoh'!C50) | D41: =('A3 Neraca Contoh'!E46-'A3 Neraca Contoh'!D46)+('A3 Neraca Contoh'!E47-'A3 Neraca Contoh'!D47)+('A3 Neraca Contoh'!E49-'A3 Neraca Contoh'!D49)+('A3 Neraca Contoh'!E50-'A3 Neraca Contoh'!D50)
A42: Kas bersih dari (untuk) aktivitas pendanaan | C42: =SUM(C37:C41) | D42: =SUM(D37:D41)
A44: KENAIKAN (PENURUNAN) BERSIH KAS | C44: =C25+C34+C42 | D44: =D25+D34+D42
A45: Kas dan setara kas awal tahun | C45: ='A3 Neraca Contoh'!C8 | D45: ='A3 Neraca Contoh'!D8
A46: KAS DAN SETARA KAS AKHIR TAHUN | C46: =C45+C44 | D46: =D45+D44
A47: Memo: Free cash flow (CFO + CFI) | C47: =C25+C34 | D47: =D25+D34
A49: MEMO: ARUS KAS OPERASI – METODE LANGSUNG (format penyajian emiten Tbk)
A50: Penerimaan kas dari pelanggan | C50: ='A2 Laba Rugi Contoh'!C13+C15 | D50: ='A2 Laba Rugi Contoh'!D13+D15
A51: Penerimaan bunga | C51: ='A2 Laba Rugi Contoh'!C80 | D51: ='A2 Laba Rugi Contoh'!D80
A52: Pembayaran royalti | C52: =-'A2 Laba Rugi Contoh'!C33+C22 | D52: =-'A2 Laba Rugi Contoh'!D33+D22
A53: Pembayaran pajak penghasilan | C53: =-'A2 Laba Rugi Contoh'!C88+C24+C20+C13 | D53: =-'A2 Laba Rugi Contoh'!D88+D24+D20+D13
A54: Pembayaran bunga & beban keuangan | C54: ='A2 Laba Rugi Contoh'!C81 | D54: ='A2 Laba Rugi Contoh'!D81
A55: Pembayaran kepada pemasok, kontraktor & karyawan (selisih) | C55: =C25-C50-C51-C52-C53-C54 | D55: =D25-D50-D51-D52-D53-D54
A56: Kas bersih dari aktivitas operasi | C56: =SUM(C50:C55) | D56: =SUM(D50:D55)

Sheet B1 Struktur Rev-Cost
A1: Struktur Pendapatan & Struktur Biaya – Perusahaan Tambang Batubara (model contoh)
A2: Sumber angka: sheet A1–A2. Dalam Rp juta kecuali disebutkan.
A4: 1. STRUKTUR PENDAPATAN (REVENUE STRUCTURE)
A5: Segmen pendapatan | B5: Volume 2024 (ton) | C5: ASP 2024 (USD/t) | D5: Pendapatan 2024 | E5: Porsi 2024 | F5: Volume 2025 (ton) | G5: ASP 2025 (USD/t) | H5: Pendapatan 2025 | I5: Porsi 2025 | J5: Pertumbuhan
A6: Ekspor | B6: ='A1 Asumsi Contoh'!C18 | C6: ='A1 Asumsi Contoh'!C9 | D6: ='A2 Laba Rugi Contoh'!C7 | E6: =IFERROR(D6/D$11,0) | F6: ='A1 Asumsi Contoh'!D18 | G6: ='A1 Asumsi Contoh'!D9 | H6: ='A2 Laba Rugi Contoh'!D7 | I6: =IFERROR(H6/H$11,0) | J6: =IFERROR((H6-D6)/ABS(D6),"")
A7: Domestik – DMO (kelistrikan) | B7: ='A1 Asumsi Contoh'!C19 | C7: ='A1 Asumsi Contoh'!C10 | D7: ='A2 Laba Rugi Contoh'!C8 | E7: =IFERROR(D7/D$11,0) | F7: ='A1 Asumsi Contoh'!D19 | G7: ='A1 Asumsi Contoh'!D10 | H7: ='A2 Laba Rugi Contoh'!D8 | I7: =IFERROR(H7/H$11,0) | J7: =IFERROR((H7-D7)/ABS(D7),"")
A8: Domestik – non-DMO (industri) | B8: ='A1 Asumsi Contoh'!C20 | C8: ='A1 Asumsi Contoh'!C11 | D8: ='A2 Laba Rugi Contoh'!C9 | E8: =IFERROR(D8/D$11,0) | F8: ='A1 Asumsi Contoh'!D20 | G8: ='A1 Asumsi Contoh'!D11 | H8: ='A2 Laba Rugi Contoh'!D9 | I8: =IFERROR(H8/H$11,0) | J8: =IFERROR((H8-D8)/ABS(D8),"")
A9: Penyesuaian harga / penalti kualitas | D9: ='A2 Laba Rugi Contoh'!C11 | E9: =IFERROR(D9/D$11,0) | H9: ='A2 Laba Rugi Contoh'!D11 | I9: =IFERROR(H9/H$11,0) | J9: =IFERROR((H9-D9)/ABS(D9),"")
A10: Pendapatan jasa pihak ketiga | D10: ='A2 Laba Rugi Contoh'!C12 | E10: =IFERROR(D10/D$11,0) | H10: ='A2 Laba Rugi Contoh'!D12 | I10: =IFERROR(H10/H$11,0) | J10: =IFERROR((H10-D10)/ABS(D10),"")
A11: TOTAL PENDAPATAN BERSIH | B11: =SUM(B6:B10) | C11: =IFERROR(SUM(D6:D8)*1000000/B11/'A1 Asumsi Contoh'!C7,0) | D11: =SUM(D6:D10) | E11: =SUM(E6:E10) | F11: =SUM(F6:F10) | G11: =IFERROR(SUM(H6:H8)*1000000/F11/'A1 Asumsi Contoh'!D7,0) | H11: =SUM(H6:H10) | I11: =SUM(I6:I10) | J11: =IFERROR((H11-D11)/ABS(D11),"")
A12: ASP total = ASP rata-rata tertimbang penjualan batubara (excl. penalti & jasa).
A13: Pemicu pendapatan: Pendapatan batubara = Volume penjualan (ton) × Harga realisasi (USD/t) × Kurs (Rp/USD) ± penyesuaian kualitas.
A14: Harga realisasi dipengaruhi: indeks acuan (HBA / ICI / Newcastle), nilai kalori (GAR/NAR), spesifikasi (TM, ash, sulfur), term FOB vs CIF, dan kontrak DMO (cap harga).
A15: Bauran pasar: ekspor (harga pasar, eksposur USD), DMO (harga dibatasi, kewajiban ≥25%), domestik non-DMO (industri/semen/smelter). Pendapatan jasa = pemanfaatan pelabuhan/jalan hauling oleh pihak ketiga.
A18: 2. STRUKTUR BIAYA (COST STRUCTURE) – total biaya = BPP + beban usaha + beban keuangan
A19: Komponen biaya | B19: FY2024 (Rp juta) | C19: FY2025 (Rp juta) | D19: Porsi thd total biaya 2025 | E19: % thd pendapatan 2025 | F19: USD/t terjual 2025 | G19: Sifat biaya | H19: Pemicu biaya (cost driver) | I19: Dapat dikendalikan | J19: Δ% YoY
A20: Pengupasan OB (kontraktor + BBM + peledakan) | B20: ='A2 Laba Rugi Contoh'!C17+'A2 Laba Rugi Contoh'!C18+'A2 Laba Rugi Contoh'!C19 | C20: ='A2 Laba Rugi Contoh'!D17+'A2 Laba Rugi Contoh'!D18+'A2 Laba Rugi Contoh'!D19 | D20: =IFERROR(C20/C$35,0) | E20: =IFERROR(C20/'A2 Laba Rugi Contoh'!D13,0) | F20: =IFERROR(C20*1000000/'A1 Asumsi Contoh'!D21/'A1 Asumsi Contoh'!D7,0) | G20: Variabel | H20: Volume OB (bcm) = produksi × SR; tarif; harga BBM | I20: Ya | J20: =IFERROR((C20-B20)/ABS(B20),"")
A21: Penggalian batubara (coal getting) | B21: ='A2 Laba Rugi Contoh'!C20 | C21: ='A2 Laba Rugi Contoh'!D20 | D21: =IFERROR(C21/C$35,0) | E21: =IFERROR(C21/'A2 Laba Rugi Contoh'!D13,0) | F21: =IFERROR(C21*1000000/'A1 Asumsi Contoh'!D21/'A1 Asumsi Contoh'!D7,0) | G21: Variabel | H21: Ton produksi × tarif | I21: Ya | J21: =IFERROR((C21-B21)/ABS(B21),"")
A22: Biaya tambang tetap (sewa alat, pemeliharaan, dewatering, survei) | B22: ='A2 Laba Rugi Contoh'!C21+'A2 Laba Rugi Contoh'!C22+'A2 Laba Rugi Contoh'!C23+'A2 Laba Rugi Contoh'!C24 | C22: ='A2 Laba Rugi Contoh'!D21+'A2 Laba Rugi Contoh'!D22+'A2 Laba Rugi Contoh'!D23+'A2 Laba Rugi Contoh'!D24 | D22: =IFERROR(C22/C$35,0) | E22: =IFERROR(C22/'A2 Laba Rugi Contoh'!D13,0) | F22: =IFERROR(C22*1000000/'A1 Asumsi Contoh'!D21/'A1 Asumsi Contoh'!D7,0) | G22: Tetap | H22: Kontrak periodik, curah hujan | I22: Ya | J22: =IFERROR((C22-B22)/ABS(B22),"")
A23: Crushing & pengolahan (CPP) | B23: ='A2 Laba Rugi Contoh'!C27 | C23: ='A2 Laba Rugi Contoh'!D27 | D23: =IFERROR(C23/C$35,0) | E23: =IFERROR(C23/'A2 Laba Rugi Contoh'!D13,0) | F23: =IFERROR(C23*1000000/'A1 Asumsi Contoh'!D21/'A1 Asumsi Contoh'!D7,0) | G23: Variabel | H23: Ton produksi | I23: Ya | J23: =IFERROR((C23-B23)/ABS(B23),"")
A24: Hauling tambang – pelabuhan | B24: ='A2 Laba Rugi Contoh'!C28 | C24: ='A2 Laba Rugi Contoh'!D28 | D24: =IFERROR(C24/C$35,0) | E24: =IFERROR(C24/'A2 Laba Rugi Contoh'!D13,0) | F24: =IFERROR(C24*1000000/'A1 Asumsi Contoh'!D21/'A1 Asumsi Contoh'!D7,0) | G24: Variabel | H24: Ton × jarak (km) × tarif | I24: Ya | J24: =IFERROR((C24-B24)/ABS(B24),"")
A25: Pelabuhan & stockpile | B25: ='A2 Laba Rugi Contoh'!C29 | C25: ='A2 Laba Rugi Contoh'!D29 | D25: =IFERROR(C25/C$35,0) | E25: =IFERROR(C25/'A2 Laba Rugi Contoh'!D13,0) | F25: =IFERROR(C25*1000000/'A1 Asumsi Contoh'!D21/'A1 Asumsi Contoh'!D7,0) | G25: Variabel | H25: Ton penjualan | I25: Ya | J25: =IFERROR((C25-B25)/ABS(B25),"")
A26: Tongkang & transshipment | B26: ='A2 Laba Rugi Contoh'!C30 | C26: ='A2 Laba Rugi Contoh'!D30 | D26: =IFERROR(C26/C$35,0) | E26: =IFERROR(C26/'A2 Laba Rugi Contoh'!D13,0) | F26: =IFERROR(C26*1000000/'A1 Asumsi Contoh'!D21/'A1 Asumsi Contoh'!D7,0) | G26: Variabel | H26: Ton penjualan; tarif pasar tongkang | I26: Sebagian | J26: =IFERROR((C26-B26)/ABS(B26),"")
A27: Royalti / PNBP | B27: ='A2 Laba Rugi Contoh'!C33 | C27: ='A2 Laba Rugi Contoh'!D33 | D27: =IFERROR(C27/C$35,0) | E27: =IFERROR(C27/'A2 Laba Rugi Contoh'!D13,0) | F27: =IFERROR(C27*1000000/'A1 Asumsi Contoh'!D21/'A1 Asumsi Contoh'!D7,0) | G27: Variabel | H27: Harga jual × tarif regulasi | I27: Tidak | J27: =IFERROR((C27-B27)/ABS(B27),"")
A28: Overhead site (gaji, camp, K3, PPM, lahan) | B28: ='A2 Laba Rugi Contoh'!C41-'A2 Laba Rugi Contoh'!C38 | C28: ='A2 Laba Rugi Contoh'!D41-'A2 Laba Rugi Contoh'!D38 | D28: =IFERROR(C28/C$35,0) | E28: =IFERROR(C28/'A2 Laba Rugi Contoh'!D13,0) | F28: =IFERROR(C28*1000000/'A1 Asumsi Contoh'!D21/'A1 Asumsi Contoh'!D7,0) | G28: Tetap | H28: Headcount & periode | I28: Ya | J28: =IFERROR((C28-B28)/ABS(B28),"")
A29: Lingkungan & reklamasi (provisi) | B29: ='A2 Laba Rugi Contoh'!C38 | C29: ='A2 Laba Rugi Contoh'!D38 | D29: =IFERROR(C29/C$35,0) | E29: =IFERROR(C29/'A2 Laba Rugi Contoh'!D13,0) | F29: =IFERROR(C29*1000000/'A1 Asumsi Contoh'!D21/'A1 Asumsi Contoh'!D7,0) | G29: Semi-variabel | H29: Luas bukaan lahan | I29: Sebagian | J29: =IFERROR((C29-B29)/ABS(B29),"")
A30: Penyusutan & amortisasi (BPP) | B30: ='A2 Laba Rugi Contoh'!C46 | C30: ='A2 Laba Rugi Contoh'!D46 | D30: =IFERROR(C30/C$35,0) | E30: =IFERROR(C30/'A2 Laba Rugi Contoh'!D13,0) | F30: =IFERROR(C30*1000000/'A1 Asumsi Contoh'!D21/'A1 Asumsi Contoh'!D7,0) | G30: Tetap | H30: Basis aset / unit produksi | I30: Tidak (jangka pendek) | J30: =IFERROR((C30-B30)/ABS(B30),"")
A31: Perubahan persediaan batubara | B31: ='A2 Laba Rugi Contoh'!C48 | C31: ='A2 Laba Rugi Contoh'!D48 | D31: =IFERROR(C31/C$35,0) | E31: =IFERROR(C31/'A2 Laba Rugi Contoh'!D13,0) | F31: =IFERROR(C31*1000000/'A1 Asumsi Contoh'!D21/'A1 Asumsi Contoh'!D7,0) | G31: Variabel | H31: Selisih produksi vs penjualan | I31: Sebagian | J31: =IFERROR((C31-B31)/ABS(B31),"")
A32: Beban penjualan | B32: ='A2 Laba Rugi Contoh'!C62 | C32: ='A2 Laba Rugi Contoh'!D62 | D32: =IFERROR(C32/C$35,0) | E32: =IFERROR(C32/'A2 Laba Rugi Contoh'!D13,0) | F32: =IFERROR(C32*1000000/'A1 Asumsi Contoh'!D21/'A1 Asumsi Contoh'!D7,0) | G32: Variabel | H32: Volume ekspor, demurrage, komisi | I32: Ya | J32: =IFERROR((C32-B32)/ABS(B32),"")
A33: Beban umum & administrasi | B33: ='A2 Laba Rugi Contoh'!C73 | C33: ='A2 Laba Rugi Contoh'!D73 | D33: =IFERROR(C33/C$35,0) | E33: =IFERROR(C33/'A2 Laba Rugi Contoh'!D13,0) | F33: =IFERROR(C33*1000000/'A1 Asumsi Contoh'!D21/'A1 Asumsi Contoh'!D7,0) | G33: Tetap | H33: Struktur organisasi kantor pusat | I33: Ya | J33: =IFERROR((C33-B33)/ABS(B33),"")
A34: Beban keuangan (bunga) | B34: =-'A2 Laba Rugi Contoh'!C81 | C34: =-'A2 Laba Rugi Contoh'!D81 | D34: =IFERROR(C34/C$35,0) | E34: =IFERROR(C34/'A2 Laba Rugi Contoh'!D13,0) | F34: =IFERROR(C34*1000000/'A1 Asumsi Contoh'!D21/'A1 Asumsi Contoh'!D7,0) | G34: Tetap | H34: Saldo pinjaman × suku bunga | I34: Sebagian | J34: =IFERROR((C34-B34)/ABS(B34),"")
A35: TOTAL BIAYA | B35: =SUM(B20:B34) | C35: =SUM(C20:C34) | D35: =SUM(D20:D34) | E35: =SUM(E20:E34) | F35: =SUM(F20:F34) | J35: =IFERROR((C35-B35)/ABS(B35),"")
A38: 3. BIAYA TETAP vs VARIABEL, MARJIN KONTRIBUSI & TITIK IMPAS (BREAKEVEN)
A39: Uraian | B39: FY2024 | C39: FY2025 | D39: Satuan | E39: Keterangan
A40: Porsi variabel dari biaya semi-variabel | B40: 0.5 | C40: =B40 | D40: % | E40: Asumsi: 50% biaya semi-variabel diperlakukan variabel
A41: Pendapatan bersih | B41: ='A2 Laba Rugi Contoh'!C13 | C41: ='A2 Laba Rugi Contoh'!D13 | D41: Rp juta
A42: Biaya variabel | B42: =SUMIF($G$20:$G$34,"Variabel",B$20:B$34)+B40*SUMIF($G$20:$G$34,"Semi-variabel",B$20:B$34) | C42: =SUMIF($G$20:$G$34,"Variabel",C$20:C$34)+C40*SUMIF($G$20:$G$34,"Semi-variabel",C$20:C$34) | D42: Rp juta | E42: Berubah proporsional dengan volume/harga
A43: Biaya tetap | B43: =SUMIF($G$20:$G$34,"Tetap",B$20:B$34)+(1-B40)*SUMIF($G$20:$G$34,"Semi-variabel",B$20:B$34) | C43: =SUMIF($G$20:$G$34,"Tetap",C$20:C$34)+(1-C40)*SUMIF($G$20:$G$34,"Semi-variabel",C$20:C$34) | D43: Rp juta | E43: Tetap dalam rentang produksi relevan
A44: Marjin kontribusi | B44: =B41-B42 | C44: =C41-C42 | D44: Rp juta | E44: Pendapatan – biaya variabel
A45: Rasio marjin kontribusi | B45: =IFERROR(B44/B41,0) | C45: =IFERROR(C44/C41,0) | D45: %
A46: Porsi biaya tetap thd total biaya | B46: =IFERROR(B43/(B43+B42),0) | C46: =IFERROR(C43/(C43+C42),0) | D46: % | E46: Makin tinggi = leverage operasi makin besar
A47: Pendapatan impas (BEP) | B47: =IFERROR(B43/B45,0) | C47: =IFERROR(C43/C45,0) | D47: Rp juta | E47: Biaya tetap / rasio marjin kontribusi
A48: Volume penjualan impas | B48: =IFERROR(B47/'A2 Laba Rugi Contoh'!C13*'A1 Asumsi Contoh'!C21,0) | C48: =IFERROR(C47/'A2 Laba Rugi Contoh'!D13*'A1 Asumsi Contoh'!D21,0) | D48: ton | E48: Pada bauran & harga tahun berjalan
A49: Harga impas (full cost) | B49: =IFERROR((B42+B43-'A2 Laba Rugi Contoh'!C12)*1000000/'A1 Asumsi Contoh'!C21/'A1 Asumsi Contoh'!C7,0) | C49: =IFERROR((C42+C43-'A2 Laba Rugi Contoh'!D12)*1000000/'A1 Asumsi Contoh'!D21/'A1 Asumsi Contoh'!D7,0) | D49: USD/t | E49: Total biaya (neto pendapatan jasa) per ton terjual
A50: Margin of safety | B50: =IFERROR((B41-B47)/B41,0) | C50: =IFERROR((C41-C47)/C41,0) | D50: % | E50: Seberapa jauh pendapatan boleh turun sebelum rugi

Sheet B2 COP dan KPI
A1: Cost of Production (COP) per Unit & Penilaian KPI – model contoh
A2: USD/unit = Biaya (Rp juta) × 1.000.000 ÷ volume basis ÷ kurs rata-rata tahun berjalan
A4: 1. BIAYA PRODUKSI PER UNIT (UNIT COST) | M4: Skala penilaian KPI
A5: Komponen | B5: Basis | C5: Biaya 2024 (Rp juta) | D5: Biaya 2025 (Rp juta) | E5: Volume basis 2024 | F5: Volume basis 2025 | G5: USD/unit 2024 | H5: USD/unit 2025 | I5: Δ USD/unit | J5: Δ% | K5: Penilaian | M5: Skor 5 jika pencapaian ≥ | N5: 1.05
A6: Jasa kontraktor OB | B6: per bcm OB | C6: ='A2 Laba Rugi Contoh'!C17 | D6: ='A2 Laba Rugi Contoh'!D17 | E6: ='A1 Asumsi Contoh'!C16 | F6: ='A1 Asumsi Contoh'!D16 | G6: =IFERROR(C6*1000000/E6/'A1 Asumsi Contoh'!C7,0) | H6: =IFERROR(D6*1000000/F6/'A1 Asumsi Contoh'!D7,0) | I6: =H6-G6 | J6: =IFERROR(I6/ABS(G6),"") | K6: =IF(I6<=0,"Efisien","Naik – review") | M6: Skor 4 jika ≥ | N6: 1
A7: BBM | B7: per bcm OB | C7: ='A2 Laba Rugi Contoh'!C18 | D7: ='A2 Laba Rugi Contoh'!D18 | E7: ='A1 Asumsi Contoh'!C16 | F7: ='A1 Asumsi Contoh'!D16 | G7: =IFERROR(C7*1000000/E7/'A1 Asumsi Contoh'!C7,0) | H7: =IFERROR(D7*1000000/F7/'A1 Asumsi Contoh'!D7,0) | I7: =H7-G7 | J7: =IFERROR(I7/ABS(G7),"") | K7: =IF(I7<=0,"Efisien","Naik – review") | M7: Skor 3 jika ≥ | N7: 0.95
A8: Peledakan | B8: per bcm OB | C8: ='A2 Laba Rugi Contoh'!C19 | D8: ='A2 Laba Rugi Contoh'!D19 | E8: ='A1 Asumsi Contoh'!C16 | F8: ='A1 Asumsi Contoh'!D16 | G8: =IFERROR(C8*1000000/E8/'A1 Asumsi Contoh'!C7,0) | H8: =IFERROR(D8*1000000/F8/'A1 Asumsi Contoh'!D7,0) | I8: =H8-G8 | J8: =IFERROR(I8/ABS(G8),"") | K8: =IF(I8<=0,"Efisien","Naik – review") | M8: Skor 2 jika ≥ | N8: 0.9
A9: Total biaya pengupasan OB per bcm | B9: per bcm OB | C9: ='A2 Laba Rugi Contoh'!C17+'A2 Laba Rugi Contoh'!C18+'A2 Laba Rugi Contoh'!C19 | D9: ='A2 Laba Rugi Contoh'!D17+'A2 Laba Rugi Contoh'!D18+'A2 Laba Rugi Contoh'!D19 | E9: ='A1 Asumsi Contoh'!C16 | F9: ='A1 Asumsi Contoh'!D16 | G9: =IFERROR(C9*1000000/E9/'A1 Asumsi Contoh'!C7,0) | H9: =IFERROR(D9*1000000/F9/'A1 Asumsi Contoh'!D7,0) | I9: =H9-G9 | J9: =IFERROR(I9/ABS(G9),"") | K9: =IF(I9<=0,"Efisien","Naik – review") | M9: Status Hijau jika ≥ | N9: 1
A10: Biaya OB per ton batubara (efek SR) | B10: per ton produksi | C10: ='A2 Laba Rugi Contoh'!C17+'A2 Laba Rugi Contoh'!C18+'A2 Laba Rugi Contoh'!C19 | D10: ='A2 Laba Rugi Contoh'!D17+'A2 Laba Rugi Contoh'!D18+'A2 Laba Rugi Contoh'!D19 | E10: ='A1 Asumsi Contoh'!C14 | F10: ='A1 Asumsi Contoh'!D14 | G10: =IFERROR(C10*1000000/E10/'A1 Asumsi Contoh'!C7,0) | H10: =IFERROR(D10*1000000/F10/'A1 Asumsi Contoh'!D7,0) | I10: =H10-G10 | J10: =IFERROR(I10/ABS(G10),"") | K10: =IF(I10<=0,"Efisien","Naik – review") | M10: Status Kuning jika ≥ | N10: 0.95
A11: Coal getting | B11: per ton produksi | C11: ='A2 Laba Rugi Contoh'!C20 | D11: ='A2 Laba Rugi Contoh'!D20 | E11: ='A1 Asumsi Contoh'!C14 | F11: ='A1 Asumsi Contoh'!D14 | G11: =IFERROR(C11*1000000/E11/'A1 Asumsi Contoh'!C7,0) | H11: =IFERROR(D11*1000000/F11/'A1 Asumsi Contoh'!D7,0) | I11: =H11-G11 | J11: =IFERROR(I11/ABS(G11),"") | K11: =IF(I11<=0,"Efisien","Naik – review") | M11: Batas atas pencapaian | N11: 1.2
A12: Biaya tambang tetap | B12: per ton produksi | C12: ='A2 Laba Rugi Contoh'!C21+'A2 Laba Rugi Contoh'!C22+'A2 Laba Rugi Contoh'!C23+'A2 Laba Rugi Contoh'!C24 | D12: ='A2 Laba Rugi Contoh'!D21+'A2 Laba Rugi Contoh'!D22+'A2 Laba Rugi Contoh'!D23+'A2 Laba Rugi Contoh'!D24 | E12: ='A1 Asumsi Contoh'!C14 | F12: ='A1 Asumsi Contoh'!D14 | G12: =IFERROR(C12*1000000/E12/'A1 Asumsi Contoh'!C7,0) | H12: =IFERROR(D12*1000000/F12/'A1 Asumsi Contoh'!D7,0) | I12: =H12-G12 | J12: =IFERROR(I12/ABS(G12),"") | K12: =IF(I12<=0,"Efisien","Naik – review") | M12: Skor 1 jika < skor 2. Merah jika < Kuning.
A13: TOTAL BIAYA PENAMBANGAN (mining cost) | B13: per ton produksi | C13: ='A2 Laba Rugi Contoh'!C25 | D13: ='A2 Laba Rugi Contoh'!D25 | E13: ='A1 Asumsi Contoh'!C14 | F13: ='A1 Asumsi Contoh'!D14 | G13: =IFERROR(C13*1000000/E13/'A1 Asumsi Contoh'!C7,0) | H13: =IFERROR(D13*1000000/F13/'A1 Asumsi Contoh'!D7,0) | I13: =H13-G13 | J13: =IFERROR(I13/ABS(G13),"") | K13: =IF(I13<=0,"Efisien","Naik – review") | M13: Polaritas Lower: pencapaian = target ÷ aktual
A14: Crushing & pengolahan | B14: per ton produksi | C14: ='A2 Laba Rugi Contoh'!C27 | D14: ='A2 Laba Rugi Contoh'!D27 | E14: ='A1 Asumsi Contoh'!C14 | F14: ='A1 Asumsi Contoh'!D14 | G14: =IFERROR(C14*1000000/E14/'A1 Asumsi Contoh'!C7,0) | H14: =IFERROR(D14*1000000/F14/'A1 Asumsi Contoh'!D7,0) | I14: =H14-G14 | J14: =IFERROR(I14/ABS(G14),"") | K14: =IF(I14<=0,"Efisien","Naik – review") | M14: Polaritas Higher: pencapaian = aktual ÷ target
A15: Hauling (per ton) | B15: per ton produksi | C15: ='A2 Laba Rugi Contoh'!C28 | D15: ='A2 Laba Rugi Contoh'!D28 | E15: ='A1 Asumsi Contoh'!C14 | F15: ='A1 Asumsi Contoh'!D14 | G15: =IFERROR(C15*1000000/E15/'A1 Asumsi Contoh'!C7,0) | H15: =IFERROR(D15*1000000/F15/'A1 Asumsi Contoh'!D7,0) | I15: =H15-G15 | J15: =IFERROR(I15/ABS(G15),"") | K15: =IF(I15<=0,"Efisien","Naik – review")
A16: Hauling (per ton-km) | B16: per ton-km | C16: ='A2 Laba Rugi Contoh'!C28 | D16: ='A2 Laba Rugi Contoh'!D28 | E16: ='A1 Asumsi Contoh'!C14*'A1 Asumsi Contoh'!C17 | F16: ='A1 Asumsi Contoh'!D14*'A1 Asumsi Contoh'!D17 | G16: =IFERROR(C16*1000000/E16/'A1 Asumsi Contoh'!C7,0) | H16: =IFERROR(D16*1000000/F16/'A1 Asumsi Contoh'!D7,0) | I16: =H16-G16 | J16: =IFERROR(I16/ABS(G16),"") | K16: =IF(I16<=0,"Efisien","Naik – review")
A17: Pelabuhan & stockpile | B17: per ton penjualan | C17: ='A2 Laba Rugi Contoh'!C29 | D17: ='A2 Laba Rugi Contoh'!D29 | E17: ='A1 Asumsi Contoh'!C21 | F17: ='A1 Asumsi Contoh'!D21 | G17: =IFERROR(C17*1000000/E17/'A1 Asumsi Contoh'!C7,0) | H17: =IFERROR(D17*1000000/F17/'A1 Asumsi Contoh'!D7,0) | I17: =H17-G17 | J17: =IFERROR(I17/ABS(G17),"") | K17: =IF(I17<=0,"Efisien","Naik – review")
A18: Tongkang & transshipment | B18: per ton penjualan | C18: ='A2 Laba Rugi Contoh'!C30 | D18: ='A2 Laba Rugi Contoh'!D30 | E18: ='A1 Asumsi Contoh'!C21 | F18: ='A1 Asumsi Contoh'!D21 | G18: =IFERROR(C18*1000000/E18/'A1 Asumsi Contoh'!C7,0) | H18: =IFERROR(D18*1000000/F18/'A1 Asumsi Contoh'!D7,0) | I18: =H18-G18 | J18: =IFERROR(I18/ABS(G18),"") | K18: =IF(I18<=0,"Efisien","Naik – review")
A19: Overhead site (termasuk reklamasi) | B19: per ton produksi | C19: ='A2 Laba Rugi Contoh'!C41 | D19: ='A2 Laba Rugi Contoh'!D41 | E19: ='A1 Asumsi Contoh'!C14 | F19: ='A1 Asumsi Contoh'!D14 | G19: =IFERROR(C19*1000000/E19/'A1 Asumsi Contoh'!C7,0) | H19: =IFERROR(D19*1000000/F19/'A1 Asumsi Contoh'!D7,0) | I19: =H19-G19 | J19: =IFERROR(I19/ABS(G19),"") | K19: =IF(I19<=0,"Efisien","Naik – review")
A20: CASH COST FOB (excl. royalti) | B20: per ton penjualan | C20: ='A2 Laba Rugi Contoh'!C25+'A2 Laba Rugi Contoh'!C31+'A2 Laba Rugi Contoh'!C41 | D20: ='A2 Laba Rugi Contoh'!D25+'A2 Laba Rugi Contoh'!D31+'A2 Laba Rugi Contoh'!D41 | E20: ='A1 Asumsi Contoh'!C21 | F20: ='A1 Asumsi Contoh'!D21 | G20: =IFERROR(C20*1000000/E20/'A1 Asumsi Contoh'!C7,0) | H20: =IFERROR(D20*1000000/F20/'A1 Asumsi Contoh'!D7,0) | I20: =H20-G20 | J20: =IFERROR(I20/ABS(G20),"") | K20: =IF(I20<=0,"Efisien","Naik – review")
A21: Royalti | B21: per ton penjualan | C21: ='A2 Laba Rugi Contoh'!C33 | D21: ='A2 Laba Rugi Contoh'!D33 | E21: ='A1 Asumsi Contoh'!C21 | F21: ='A1 Asumsi Contoh'!D21 | G21: =IFERROR(C21*1000000/E21/'A1 Asumsi Contoh'!C7,0) | H21: =IFERROR(D21*1000000/F21/'A1 Asumsi Contoh'!D7,0) | I21: =H21-G21 | J21: =IFERROR(I21/ABS(G21),"") | K21: =IF(I21<=0,"Efisien","Naik – review")
A22: CASH COST FOB (incl. royalti) | B22: per ton penjualan | C22: ='A2 Laba Rugi Contoh'!C25+'A2 Laba Rugi Contoh'!C31+'A2 Laba Rugi Contoh'!C41+'A2 Laba Rugi Contoh'!C33 | D22: ='A2 Laba Rugi Contoh'!D25+'A2 Laba Rugi Contoh'!D31+'A2 Laba Rugi Contoh'!D41+'A2 Laba Rugi Contoh'!D33 | E22: ='A1 Asumsi Contoh'!C21 | F22: ='A1 Asumsi Contoh'!D21 | G22: =IFERROR(C22*1000000/E22/'A1 Asumsi Contoh'!C7,0) | H22: =IFERROR(D22*1000000/F22/'A1 Asumsi Contoh'!D7,0) | I22: =H22-G22 | J22: =IFERROR(I22/ABS(G22),"") | K22: =IF(I22<=0,"Efisien","Naik – review")
A23: Beban penjualan | B23: per ton penjualan | C23: ='A2 Laba Rugi Contoh'!C62 | D23: ='A2 Laba Rugi Contoh'!D62 | E23: ='A1 Asumsi Contoh'!C21 | F23: ='A1 Asumsi Contoh'!D21 | G23: =IFERROR(C23*1000000/E23/'A1 Asumsi Contoh'!C7,0) | H23: =IFERROR(D23*1000000/F23/'A1 Asumsi Contoh'!D7,0) | I23: =H23-G23 | J23: =IFERROR(I23/ABS(G23),"") | K23: =IF(I23<=0,"Efisien","Naik – review")
A24: Beban umum & administrasi (excl. penyusutan) | B24: per ton penjualan | C24: ='A2 Laba Rugi Contoh'!C73-'A2 Laba Rugi Contoh'!C71 | D24: ='A2 Laba Rugi Contoh'!D73-'A2 Laba Rugi Contoh'!D71 | E24: ='A1 Asumsi Contoh'!C21 | F24: ='A1 Asumsi Contoh'!D21 | G24: =IFERROR(C24*1000000/E24/'A1 Asumsi Contoh'!C7,0) | H24: =IFERROR(D24*1000000/F24/'A1 Asumsi Contoh'!D7,0) | I24: =H24-G24 | J24: =IFERROR(I24/ABS(G24),"") | K24: =IF(I24<=0,"Efisien","Naik – review")
A25: TOTAL CASH COST | B25: per ton penjualan | C25: ='A2 Laba Rugi Contoh'!C25+'A2 Laba Rugi Contoh'!C31+'A2 Laba Rugi Contoh'!C41+'A2 Laba Rugi Contoh'!C33+'A2 Laba Rugi Contoh'!C62+'A2 Laba Rugi Contoh'!C73-'A2 Laba Rugi Contoh'!C71 | D25: ='A2 Laba Rugi Contoh'!D25+'A2 Laba Rugi Contoh'!D31+'A2 Laba Rugi Contoh'!D41+'A2 Laba Rugi Contoh'!D33+'A2 Laba Rugi Contoh'!D62+'A2 Laba Rugi Contoh'!D73-'A2 Laba Rugi Contoh'!D71 | E25: ='A1 Asumsi Contoh'!C21 | F25: ='A1 Asumsi Contoh'!D21 | G25: =IFERROR(C25*1000000/E25/'A1 Asumsi Contoh'!C7,0) | H25: =IFERROR(D25*1000000/F25/'A1 Asumsi Contoh'!D7,0) | I25: =H25-G25 | J25: =IFERROR(I25/ABS(G25),"") | K25: =IF(I25<=0,"Efisien","Naik – review")
A26: Penyusutan & amortisasi | B26: per ton penjualan | C26: ='A2 Laba Rugi Contoh'!C46+'A2 Laba Rugi Contoh'!C71 | D26: ='A2 Laba Rugi Contoh'!D46+'A2 Laba Rugi Contoh'!D71 | E26: ='A1 Asumsi Contoh'!C21 | F26: ='A1 Asumsi Contoh'!D21 | G26: =IFERROR(C26*1000000/E26/'A1 Asumsi Contoh'!C7,0) | H26: =IFERROR(D26*1000000/F26/'A1 Asumsi Contoh'!D7,0) | I26: =H26-G26 | J26: =IFERROR(I26/ABS(G26),"") | K26: =IF(I26<=0,"Efisien","Naik – review")
A27: Capex berkelanjutan (aset tetap + pengupasan tangguhan) | B27: per ton penjualan | C27: ='A1 Asumsi Contoh'!C90+'A1 Asumsi Contoh'!C92 | D27: ='A1 Asumsi Contoh'!D90+'A1 Asumsi Contoh'!D92 | E27: ='A1 Asumsi Contoh'!C21 | F27: ='A1 Asumsi Contoh'!D21 | G27: =IFERROR(C27*1000000/E27/'A1 Asumsi Contoh'!C7,0) | H27: =IFERROR(D27*1000000/F27/'A1 Asumsi Contoh'!D7,0) | I27: =H27-G27 | J27: =IFERROR(I27/ABS(G27),"") | K27: =IF(I27<=0,"Efisien","Naik – review")
A28: ALL-IN SUSTAINING COST (AISC) | B28: per ton penjualan | C28: ='A2 Laba Rugi Contoh'!C25+'A2 Laba Rugi Contoh'!C31+'A2 Laba Rugi Contoh'!C41+'A2 Laba Rugi Contoh'!C33+'A2 Laba Rugi Contoh'!C62+'A2 Laba Rugi Contoh'!C73-'A2 Laba Rugi Contoh'!C71+'A1 Asumsi Contoh'!C90+'A1 Asumsi Contoh'!C92 | D28: ='A2 Laba Rugi Contoh'!D25+'A2 Laba Rugi Contoh'!D31+'A2 Laba Rugi Contoh'!D41+'A2 Laba Rugi Contoh'!D33+'A2 Laba Rugi Contoh'!D62+'A2 Laba Rugi Contoh'!D73-'A2 Laba Rugi Contoh'!D71+'A1 Asumsi Contoh'!D90+'A1 Asumsi Contoh'!D92 | E28: ='A1 Asumsi Contoh'!C21 | F28: ='A1 Asumsi Contoh'!D21 | G28: =IFERROR(C28*1000000/E28/'A1 Asumsi Contoh'!C7,0) | H28: =IFERROR(D28*1000000/F28/'A1 Asumsi Contoh'!D7,0) | I28: =H28-G28 | J28: =IFERROR(I28/ABS(G28),"") | K28: =IF(I28<=0,"Efisien","Naik – review")
A29: Harga jual rata-rata (ASP) blended, neto penalti | B29: per ton penjualan | C29: ='A2 Laba Rugi Contoh'!C10+'A2 Laba Rugi Contoh'!C11 | D29: ='A2 Laba Rugi Contoh'!D10+'A2 Laba Rugi Contoh'!D11 | E29: ='A1 Asumsi Contoh'!C21 | F29: ='A1 Asumsi Contoh'!D21 | G29: =IFERROR(C29*1000000/E29/'A1 Asumsi Contoh'!C7,0) | H29: =IFERROR(D29*1000000/F29/'A1 Asumsi Contoh'!D7,0) | I29: =H29-G29 | J29: =IFERROR(I29/ABS(G29),"") | K29: =IF(I29>=0,"Membaik","Menurun – review")
A30: MARJIN KAS PER TON (ASP – total cash cost) | B30: per ton penjualan | C30: =C29-C25 | D30: =D29-D25 | E30: ='A1 Asumsi Contoh'!C21 | F30: ='A1 Asumsi Contoh'!D21 | G30: =IFERROR(C30*1000000/E30/'A1 Asumsi Contoh'!C7,0) | H30: =IFERROR(D30*1000000/F30/'A1 Asumsi Contoh'!D7,0) | I30: =H30-G30 | J30: =IFERROR(I30/ABS(G30),"") | K30: =IF(I30>=0,"Membaik","Menurun – review")
A31: MARJIN AISC PER TON (ASP – AISC) | B31: per ton penjualan | C31: =C29-C28 | D31: =D29-D28 | E31: ='A1 Asumsi Contoh'!C21 | F31: ='A1 Asumsi Contoh'!D21 | G31: =IFERROR(C31*1000000/E31/'A1 Asumsi Contoh'!C7,0) | H31: =IFERROR(D31*1000000/F31/'A1 Asumsi Contoh'!D7,0) | I31: =H31-G31 | J31: =IFERROR(I31/ABS(G31),"") | K31: =IF(I31>=0,"Membaik","Menurun – review")
A32: Catatan: cash cost memakai basis ton penjualan; mining cost memakai basis ton produksi; biaya OB memakai basis bcm. AISC = total cash cost + capex berkelanjutan.
A34: 2. PENILAIAN KPI COST OF PRODUCTION – FY2025
A35: KPI Cost of Production | B35: Satuan | C35: Aktual FY2024 | D35: Aktual FY2025 | E35: Target FY2025 | F35: Polaritas | G35: Pencapaian | H35: Skor (1–5) | I35: Status | J35: Catatan manajemen
A36: Stripping ratio | B36: bcm/t | C36: ='A1 Asumsi Contoh'!C15 | D36: ='A1 Asumsi Contoh'!D15 | E36: 7.5 | F36: Lower | G36: =MIN('B2 COP dan KPI'!$N$11,IF(F36="Lower",IF(D36<=0,'B2 COP dan KPI'!$N$11,E36/D36),IFERROR(D36/E36,0))) | H36: =IF(G36>='B2 COP dan KPI'!$N$5,5,IF(G36>='B2 COP dan KPI'!$N$6,4,IF(G36>='B2 COP dan KPI'!$N$7,3,IF(G36>='B2 COP dan KPI'!$N$8,2,1)))) | I36: =IF(G36>='B2 COP dan KPI'!$N$9,"Hijau",IF(G36>='B2 COP dan KPI'!$N$10,"Kuning","Merah")) | J36: Deviasi dari rencana tambang; SR terlalu rendah bisa tanda high-grading
A37: Biaya pengupasan OB | B37: USD/bcm | C37: =G9 | D37: =H9 | E37: 2.75 | F37: Lower | G37: =MIN('B2 COP dan KPI'!$N$11,IF(F37="Lower",IF(D37<=0,'B2 COP dan KPI'!$N$11,E37/D37),IFERROR(D37/E37,0))) | H37: =IF(G37>='B2 COP dan KPI'!$N$5,5,IF(G37>='B2 COP dan KPI'!$N$6,4,IF(G37>='B2 COP dan KPI'!$N$7,3,IF(G37>='B2 COP dan KPI'!$N$8,2,1)))) | I37: =IF(G37>='B2 COP dan KPI'!$N$9,"Hijau",IF(G37>='B2 COP dan KPI'!$N$10,"Kuning","Merah")) | J37: Tarif kontraktor + BBM + peledakan
A38: Fuel ratio | B38: L/bcm | C38: ='A1 Asumsi Contoh'!C29 | D38: ='A1 Asumsi Contoh'!D29 | E38: 0.92 | F38: Lower | G38: =MIN('B2 COP dan KPI'!$N$11,IF(F38="Lower",IF(D38<=0,'B2 COP dan KPI'!$N$11,E38/D38),IFERROR(D38/E38,0))) | H38: =IF(G38>='B2 COP dan KPI'!$N$5,5,IF(G38>='B2 COP dan KPI'!$N$6,4,IF(G38>='B2 COP dan KPI'!$N$7,3,IF(G38>='B2 COP dan KPI'!$N$8,2,1)))) | I38: =IF(G38>='B2 COP dan KPI'!$N$9,"Hijau",IF(G38>='B2 COP dan KPI'!$N$10,"Kuning","Merah")) | J38: Indikator efisiensi armada & jarak angkut OB
A39: Mining cost per ton produksi | B39: USD/t | C39: =G13 | D39: =H13 | E39: 22 | F39: Lower | G39: =MIN('B2 COP dan KPI'!$N$11,IF(F39="Lower",IF(D39<=0,'B2 COP dan KPI'!$N$11,E39/D39),IFERROR(D39/E39,0))) | H39: =IF(G39>='B2 COP dan KPI'!$N$5,5,IF(G39>='B2 COP dan KPI'!$N$6,4,IF(G39>='B2 COP dan KPI'!$N$7,3,IF(G39>='B2 COP dan KPI'!$N$8,2,1)))) | I39: =IF(G39>='B2 COP dan KPI'!$N$9,"Hijau",IF(G39>='B2 COP dan KPI'!$N$10,"Kuning","Merah")) | J39: Dipengaruhi SR, tarif, BBM, biaya tetap tambang
A40: Hauling cost per ton-km | B40: USD/t-km | C40: =G16 | D40: =H16 | E40: 0.1 | F40: Lower | G40: =MIN('B2 COP dan KPI'!$N$11,IF(F40="Lower",IF(D40<=0,'B2 COP dan KPI'!$N$11,E40/D40),IFERROR(D40/E40,0))) | H40: =IF(G40>='B2 COP dan KPI'!$N$5,5,IF(G40>='B2 COP dan KPI'!$N$6,4,IF(G40>='B2 COP dan KPI'!$N$7,3,IF(G40>='B2 COP dan KPI'!$N$8,2,1)))) | I40: =IF(G40>='B2 COP dan KPI'!$N$9,"Hijau",IF(G40>='B2 COP dan KPI'!$N$10,"Kuning","Merah")) | J40: Kondisi jalan, payload, cycle time
A41: Barging cost per ton | B41: USD/t | C41: =G18 | D41: =H18 | E41: 3.9 | F41: Lower | G41: =MIN('B2 COP dan KPI'!$N$11,IF(F41="Lower",IF(D41<=0,'B2 COP dan KPI'!$N$11,E41/D41),IFERROR(D41/E41,0))) | H41: =IF(G41>='B2 COP dan KPI'!$N$5,5,IF(G41>='B2 COP dan KPI'!$N$6,4,IF(G41>='B2 COP dan KPI'!$N$7,3,IF(G41>='B2 COP dan KPI'!$N$8,2,1)))) | I41: =IF(G41>='B2 COP dan KPI'!$N$9,"Hijau",IF(G41>='B2 COP dan KPI'!$N$10,"Kuning","Merah")) | J41: Tarif tongkang, waktu tunggu, draft sungai
A42: Cash cost FOB excl. royalti | B42: USD/t | C42: =G20 | D42: =H20 | E42: 34 | F42: Lower | G42: =MIN('B2 COP dan KPI'!$N$11,IF(F42="Lower",IF(D42<=0,'B2 COP dan KPI'!$N$11,E42/D42),IFERROR(D42/E42,0))) | H42: =IF(G42>='B2 COP dan KPI'!$N$5,5,IF(G42>='B2 COP dan KPI'!$N$6,4,IF(G42>='B2 COP dan KPI'!$N$7,3,IF(G42>='B2 COP dan KPI'!$N$8,2,1)))) | I42: =IF(G42>='B2 COP dan KPI'!$N$9,"Hijau",IF(G42>='B2 COP dan KPI'!$N$10,"Kuning","Merah")) | J42: KPI utama biaya produksi yang dapat dikendalikan
A43: Cash cost FOB incl. royalti | B43: USD/t | C43: =G22 | D43: =H22 | E43: 38 | F43: Lower | G43: =MIN('B2 COP dan KPI'!$N$11,IF(F43="Lower",IF(D43<=0,'B2 COP dan KPI'!$N$11,E43/D43),IFERROR(D43/E43,0))) | H43: =IF(G43>='B2 COP dan KPI'!$N$5,5,IF(G43>='B2 COP dan KPI'!$N$6,4,IF(G43>='B2 COP dan KPI'!$N$7,3,IF(G43>='B2 COP dan KPI'!$N$8,2,1)))) | I43: =IF(G43>='B2 COP dan KPI'!$N$9,"Hijau",IF(G43>='B2 COP dan KPI'!$N$10,"Kuning","Merah")) | J43: Royalti mengikuti harga – pisahkan dari kinerja biaya
A44: All-in sustaining cost (AISC) | B44: USD/t | C44: =G28 | D44: =H28 | E44: 46 | F44: Lower | G44: =MIN('B2 COP dan KPI'!$N$11,IF(F44="Lower",IF(D44<=0,'B2 COP dan KPI'!$N$11,E44/D44),IFERROR(D44/E44,0))) | H44: =IF(G44>='B2 COP dan KPI'!$N$5,5,IF(G44>='B2 COP dan KPI'!$N$6,4,IF(G44>='B2 COP dan KPI'!$N$7,3,IF(G44>='B2 COP dan KPI'!$N$8,2,1)))) | I44: =IF(G44>='B2 COP dan KPI'!$N$9,"Hijau",IF(G44>='B2 COP dan KPI'!$N$10,"Kuning","Merah")) | J44: Termasuk capex berkelanjutan
A45: Marjin kas per ton | B45: USD/t | C45: =G30 | D45: =H30 | E45: 15 | F45: Higher | G45: =MIN('B2 COP dan KPI'!$N$11,IF(F45="Lower",IF(D45<=0,'B2 COP dan KPI'!$N$11,E45/D45),IFERROR(D45/E45,0))) | H45: =IF(G45>='B2 COP dan KPI'!$N$5,5,IF(G45>='B2 COP dan KPI'!$N$6,4,IF(G45>='B2 COP dan KPI'!$N$7,3,IF(G45>='B2 COP dan KPI'!$N$8,2,1)))) | I45: =IF(G45>='B2 COP dan KPI'!$N$9,"Hijau",IF(G45>='B2 COP dan KPI'!$N$10,"Kuning","Merah")) | J45: ASP – total cash cost
A46: Rata-rata skor KPI COP | H46: =AVERAGE(H36:H45)
A47: Target diisi manajemen (sel kuning) – contoh: dari RKAP/budget atau benchmark. Sumber target contoh: asumsi penyusun.

Sheet B3 KPI Cost vs Revenue
A1: Analisa KPI Cost vs Revenue – untuk Penilaian Manajemen (model contoh)
A2: Sumber: A2 Laba Rugi, A3 Neraca, A4 Arus Kas, B2 COP. Target/acuan = input manajemen (sel kuning).
A4: No | B4: KPI | C4: Rumus | D4: Satuan | E4: FY2024 | F4: FY2025 | G4: Polaritas | H4: Acuan / Target | I4: Penilaian FY2025 | J4: Interpretasi untuk manajemen
A5: A. PERTUMBUHAN & "JAWS"
A6: 1 | B6: Pertumbuhan pendapatan | C6: Pendapatan t ÷ t-1 – 1 | D6: % | E6: n/a | F6: ='A2 Laba Rugi Contoh'!D13/'A2 Laba Rugi Contoh'!C13-1 | G6: Higher | H6: 0.02 | I6: =IF(G6="Info","Informasi",IF(G6="Higher",IF(F6>=H6,"Baik","Perlu perbaikan"),IF(F6<=H6,"Baik","Perlu perbaikan"))) | J6: Pisahkan efek volume, harga, kurs (lihat B4).
A7: 2 | B7: Pertumbuhan total biaya | C7: Total biaya t ÷ t-1 – 1 | D7: % | E7: n/a | F7: =('A2 Laba Rugi Contoh'!D49+'A2 Laba Rugi Contoh'!D74-'A2 Laba Rugi Contoh'!D81)/('A2 Laba Rugi Contoh'!C49+'A2 Laba Rugi Contoh'!C74-'A2 Laba Rugi Contoh'!C81)-1 | G7: Lower | H7: =F6 | I7: =IF(G7="Info","Informasi",IF(G7="Higher",IF(F7>=H7,"Baik","Perlu perbaikan"),IF(F7<=H7,"Baik","Perlu perbaikan"))) | J7: Target: biaya tumbuh lebih lambat dari pendapatan.
A8: 3 | B8: Jaws ratio | C8: Growth pendapatan – growth biaya | D8: pp | E8: n/a | F8: =F6-F7 | G8: Higher | H8: 0 | I8: =IF(G8="Info","Informasi",IF(G8="Higher",IF(F8>=H8,"Baik","Perlu perbaikan"),IF(F8<=H8,"Baik","Perlu perbaikan"))) | J8: Positif = pendapatan tumbuh lebih cepat dari biaya (leverage operasi sehat).
A9: B. RASIO BIAYA TERHADAP PENDAPATAN
A10: 4 | B10: Rasio total biaya thd pendapatan | C10: (BPP + beban usaha + bunga) ÷ pendapatan | D10: % | E10: =('A2 Laba Rugi Contoh'!C49+'A2 Laba Rugi Contoh'!C74-'A2 Laba Rugi Contoh'!C81)/'A2 Laba Rugi Contoh'!C13 | F10: =('A2 Laba Rugi Contoh'!D49+'A2 Laba Rugi Contoh'!D74-'A2 Laba Rugi Contoh'!D81)/'A2 Laba Rugi Contoh'!D13 | G10: Lower | H10: 0.8 | I10: =IF(G10="Info","Informasi",IF(G10="Higher",IF(F10>=H10,"Baik","Perlu perbaikan"),IF(F10<=H10,"Baik","Perlu perbaikan"))) | J10: Setiap Rp100 pendapatan menyerap Rp x biaya.
A11: 5 | B11: Rasio BPP thd pendapatan | C11: BPP ÷ pendapatan | D11: % | E11: ='A2 Laba Rugi Contoh'!C49/'A2 Laba Rugi Contoh'!C13 | F11: ='A2 Laba Rugi Contoh'!D49/'A2 Laba Rugi Contoh'!D13 | G11: Lower | H11: 0.72 | I11: =IF(G11="Info","Informasi",IF(G11="Higher",IF(F11>=H11,"Baik","Perlu perbaikan"),IF(F11<=H11,"Baik","Perlu perbaikan"))) | J11: Kebalikan dari marjin laba kotor.
A12: 6 | B12: Rasio beban usaha thd pendapatan | C12: (Penjualan + G&A) ÷ pendapatan | D12: % | E12: ='A2 Laba Rugi Contoh'!C74/'A2 Laba Rugi Contoh'!C13 | F12: ='A2 Laba Rugi Contoh'!D74/'A2 Laba Rugi Contoh'!D13 | G12: Lower | H12: 0.07 | I12: =IF(G12="Info","Informasi",IF(G12="Higher",IF(F12>=H12,"Baik","Perlu perbaikan"),IF(F12<=H12,"Baik","Perlu perbaikan"))) | J12: Efisiensi overhead non-produksi.
A13: 7 | B13: Royalti thd pendapatan | C13: Royalti ÷ pendapatan | D13: % | E13: ='A2 Laba Rugi Contoh'!C33/'A2 Laba Rugi Contoh'!C13 | F13: ='A2 Laba Rugi Contoh'!D33/'A2 Laba Rugi Contoh'!D13 | G13: Lower | H13: 0.07 | I13: =IF(G13="Info","Informasi",IF(G13="Higher",IF(F13>=H13,"Baik","Perlu perbaikan"),IF(F13<=H13,"Baik","Perlu perbaikan"))) | J13: Tidak dapat dikendalikan – mengikuti harga & regulasi.
A14: C. PROFITABILITAS
A15: 8 | B15: Marjin laba kotor | C15: Laba kotor ÷ pendapatan | D15: % | E15: ='A2 Laba Rugi Contoh'!C52 | F15: ='A2 Laba Rugi Contoh'!D52 | G15: Higher | H15: 0.28 | I15: =IF(G15="Info","Informasi",IF(G15="Higher",IF(F15>=H15,"Baik","Perlu perbaikan"),IF(F15<=H15,"Baik","Perlu perbaikan")))
A16: 9 | B16: EBITDA | C16: Laba usaha + D&A | D16: Rp juta | E16: ='A2 Laba Rugi Contoh'!C93 | F16: ='A2 Laba Rugi Contoh'!D93 | G16: Higher | H16: 3000000 | I16: =IF(G16="Info","Informasi",IF(G16="Higher",IF(F16>=H16,"Baik","Perlu perbaikan"),IF(F16<=H16,"Baik","Perlu perbaikan"))) | J16: Ukuran kas operasi sebelum modal kerja, pajak & bunga.
A17: 10 | B17: Marjin EBITDA | C17: EBITDA ÷ pendapatan | D17: % | E17: ='A2 Laba Rugi Contoh'!C94 | F17: ='A2 Laba Rugi Contoh'!D94 | G17: Higher | H17: 0.28 | I17: =IF(G17="Info","Informasi",IF(G17="Higher",IF(F17>=H17,"Baik","Perlu perbaikan"),IF(F17<=H17,"Baik","Perlu perbaikan")))
A18: 11 | B18: EBITDA per ton | C18: EBITDA ÷ ton jual ÷ kurs | D18: USD/t | E18: ='A2 Laba Rugi Contoh'!C93*1000000/'A1 Asumsi Contoh'!C21/'A1 Asumsi Contoh'!C7 | F18: ='A2 Laba Rugi Contoh'!D93*1000000/'A1 Asumsi Contoh'!D21/'A1 Asumsi Contoh'!D7 | G18: Higher | H18: 16 | I18: =IF(G18="Info","Informasi",IF(G18="Higher",IF(F18>=H18,"Baik","Perlu perbaikan"),IF(F18<=H18,"Baik","Perlu perbaikan"))) | J18: Pembanding antar-perusahaan yang netral skala.
A19: 12 | B19: Marjin laba usaha | C19: Laba usaha ÷ pendapatan | D19: % | E19: ='A2 Laba Rugi Contoh'!C77 | F19: ='A2 Laba Rugi Contoh'!D77 | G19: Higher | H19: 0.22 | I19: =IF(G19="Info","Informasi",IF(G19="Higher",IF(F19>=H19,"Baik","Perlu perbaikan"),IF(F19<=H19,"Baik","Perlu perbaikan")))
A20: 13 | B20: Marjin laba bersih | C20: Laba bersih ÷ pendapatan | D20: % | E20: ='A2 Laba Rugi Contoh'!C90 | F20: ='A2 Laba Rugi Contoh'!D90 | G20: Higher | H20: 0.16 | I20: =IF(G20="Info","Informasi",IF(G20="Higher",IF(F20>=H20,"Baik","Perlu perbaikan"),IF(F20<=H20,"Baik","Perlu perbaikan")))
A21: D. HARGA vs BIAYA PER TON
A22: 14 | B22: ASP blended | C22: Penjualan batubara neto ÷ ton | D22: USD/t | E22: ='B2 COP dan KPI'!G29 | F22: ='B2 COP dan KPI'!H29 | G22: Higher | H22: 58 | I22: =IF(G22="Info","Informasi",IF(G22="Higher",IF(F22>=H22,"Baik","Perlu perbaikan"),IF(F22<=H22,"Baik","Perlu perbaikan")))
A23: 15 | B23: Realisasi harga ekspor vs indeks | C23: ASP ekspor ÷ indeks acuan | D23: % | E23: ='A1 Asumsi Contoh'!C9/'A1 Asumsi Contoh'!C8 | F23: ='A1 Asumsi Contoh'!D9/'A1 Asumsi Contoh'!D8 | G23: Higher | H23: 0.95 | I23: =IF(G23="Info","Informasi",IF(G23="Higher",IF(F23>=H23,"Baik","Perlu perbaikan"),IF(F23<=H23,"Baik","Perlu perbaikan"))) | J23: Mengukur kualitas pemasaran & spesifikasi produk.
A24: 16 | B24: Total cash cost | C24: Lihat B2 | D24: USD/t | E24: ='B2 COP dan KPI'!G25 | F24: ='B2 COP dan KPI'!H25 | G24: Lower | H24: 43 | I24: =IF(G24="Info","Informasi",IF(G24="Higher",IF(F24>=H24,"Baik","Perlu perbaikan"),IF(F24<=H24,"Baik","Perlu perbaikan")))
A25: 17 | B25: Marjin kas per ton | C25: ASP – total cash cost | D25: USD/t | E25: ='B2 COP dan KPI'!G30 | F25: ='B2 COP dan KPI'!H30 | G25: Higher | H25: 15 | I25: =IF(G25="Info","Informasi",IF(G25="Higher",IF(F25>=H25,"Baik","Perlu perbaikan"),IF(F25<=H25,"Baik","Perlu perbaikan")))
A26: 18 | B26: Harga impas kas (cash breakeven) | C26: (Total cash cost + bunga) per ton | D26: USD/t | E26: ='B2 COP dan KPI'!G25-'A2 Laba Rugi Contoh'!C81*1000000/'A1 Asumsi Contoh'!C21/'A1 Asumsi Contoh'!C7 | F26: ='B2 COP dan KPI'!H25-'A2 Laba Rugi Contoh'!D81*1000000/'A1 Asumsi Contoh'!D21/'A1 Asumsi Contoh'!D7 | G26: Lower | H26: 45 | I26: =IF(G26="Info","Informasi",IF(G26="Higher",IF(F26>=H26,"Baik","Perlu perbaikan"),IF(F26<=H26,"Baik","Perlu perbaikan"))) | J26: Harga minimum agar kas operasi tidak negatif.
A27: 19 | B27: Margin of safety harga | C27: (ASP – harga impas) ÷ ASP | D27: % | E27: =IFERROR(('B2 COP dan KPI'!G29-E26)/'B2 COP dan KPI'!G29,0) | F27: =IFERROR(('B2 COP dan KPI'!H29-F26)/'B2 COP dan KPI'!H29,0) | G27: Higher | H27: 0.2 | I27: =IF(G27="Info","Informasi",IF(G27="Higher",IF(F27>=H27,"Baik","Perlu perbaikan"),IF(F27<=H27,"Baik","Perlu perbaikan"))) | J27: Ketahanan terhadap penurunan harga batubara.
A28: 20 | B28: Degree of operating leverage (DOL) | C28: %Δ laba usaha ÷ %Δ pendapatan | D28: x | E28: n/a | F28: =IFERROR(('A2 Laba Rugi Contoh'!D76/'A2 Laba Rugi Contoh'!C76-1)/F6,0) | G28: Info | I28: =IF(G28="Info","Informasi",IF(G28="Higher",IF(F28>=H28,"Baik","Perlu perbaikan"),IF(F28<=H28,"Baik","Perlu perbaikan"))) | J28: DOL tinggi = laba sangat sensitif thd perubahan pendapatan.
A29: E. KAS, LEVERAGE & IMBAL HASIL
A30: 21 | B30: Interest coverage | C30: EBITDA ÷ beban bunga | D30: x | E30: =IFERROR('A2 Laba Rugi Contoh'!C93/-'A2 Laba Rugi Contoh'!C81,0) | F30: =IFERROR('A2 Laba Rugi Contoh'!D93/-'A2 Laba Rugi Contoh'!D81,0) | G30: Higher | H30: 5 | I30: =IF(G30="Info","Informasi",IF(G30="Higher",IF(F30>=H30,"Baik","Perlu perbaikan"),IF(F30<=H30,"Baik","Perlu perbaikan")))
A31: 22 | B31: Konversi kas (cash conversion) | C31: CFO ÷ EBITDA | D31: % | E31: ='A4 Arus Kas Contoh'!C25/'A2 Laba Rugi Contoh'!C93 | F31: ='A4 Arus Kas Contoh'!D25/'A2 Laba Rugi Contoh'!D93 | G31: Higher | H31: 0.8 | I31: =IF(G31="Info","Informasi",IF(G31="Higher",IF(F31>=H31,"Baik","Perlu perbaikan"),IF(F31<=H31,"Baik","Perlu perbaikan"))) | J31: Kualitas laba – seberapa banyak EBITDA menjadi kas.
A32: 23 | B32: ROE | C32: Laba bersih ÷ ekuitas rata-rata | D32: % | E32: ='A2 Laba Rugi Contoh'!C89/(('A3 Neraca Contoh'!D51+'A3 Neraca Contoh'!C51)/2) | F32: ='A2 Laba Rugi Contoh'!D89/(('A3 Neraca Contoh'!E51+'A3 Neraca Contoh'!D51)/2) | G32: Higher | H32: 0.2 | I32: =IF(G32="Info","Informasi",IF(G32="Higher",IF(F32>=H32,"Baik","Perlu perbaikan"),IF(F32<=H32,"Baik","Perlu perbaikan")))
A33: 24 | B33: ROA | C33: Laba bersih ÷ aset rata-rata | D33: % | E33: ='A2 Laba Rugi Contoh'!C89/(('A3 Neraca Contoh'!D26+'A3 Neraca Contoh'!C26)/2) | F33: ='A2 Laba Rugi Contoh'!D89/(('A3 Neraca Contoh'!E26+'A3 Neraca Contoh'!D26)/2) | G33: Higher | H33: 0.12 | I33: =IF(G33="Info","Informasi",IF(G33="Higher",IF(F33>=H33,"Baik","Perlu perbaikan"),IF(F33<=H33,"Baik","Perlu perbaikan")))
A34: 25 | B34: Debt to equity (DER) | C34: Pinjaman ÷ ekuitas | D34: x | E34: =('A3 Neraca Contoh'!D34+'A3 Neraca Contoh'!D35+'A3 Neraca Contoh'!D38)/'A3 Neraca Contoh'!D51 | F34: =('A3 Neraca Contoh'!E34+'A3 Neraca Contoh'!E35+'A3 Neraca Contoh'!E38)/'A3 Neraca Contoh'!E51 | G34: Lower | H34: 0.5 | I34: =IF(G34="Info","Informasi",IF(G34="Higher",IF(F34>=H34,"Baik","Perlu perbaikan"),IF(F34<=H34,"Baik","Perlu perbaikan")))
A35: 26 | B35: Net debt ÷ EBITDA | C35: (Pinjaman – kas) ÷ EBITDA | D35: x | E35: =(('A3 Neraca Contoh'!D34+'A3 Neraca Contoh'!D35+'A3 Neraca Contoh'!D38)-'A3 Neraca Contoh'!D8)/'A2 Laba Rugi Contoh'!C93 | F35: =(('A3 Neraca Contoh'!E34+'A3 Neraca Contoh'!E35+'A3 Neraca Contoh'!E38)-'A3 Neraca Contoh'!E8)/'A2 Laba Rugi Contoh'!D93 | G35: Lower | H35: 1 | I35: =IF(G35="Info","Informasi",IF(G35="Higher",IF(F35>=H35,"Baik","Perlu perbaikan"),IF(F35<=H35,"Baik","Perlu perbaikan"))) | J35: Negatif = posisi kas neto.
A36: 27 | B36: Current ratio | C36: Aset lancar ÷ liabilitas lancar | D36: x | E36: ='A3 Neraca Contoh'!D15/'A3 Neraca Contoh'!D36 | F36: ='A3 Neraca Contoh'!E15/'A3 Neraca Contoh'!E36 | G36: Higher | H36: 1.5 | I36: =IF(G36="Info","Informasi",IF(G36="Higher",IF(F36>=H36,"Baik","Perlu perbaikan"),IF(F36<=H36,"Baik","Perlu perbaikan")))
A38: RINGKASAN PENILAIAN MANAJEMEN
B39: Jumlah KPI "Baik" | F39: =COUNTIF(I5:I36,"Baik")
B40: Jumlah KPI "Perlu perbaikan" | F40: =COUNTIF(I5:I36,"Perlu perbaikan")
B41: Persentase KPI tercapai | F41: =IFERROR(F39/(F39+F40),0)
B42: Kesimpulan otomatis | F42: =IF(F41>=0.8,"Kinerja manajemen BAIK – pertahankan disiplin biaya",IF(F41>=0.6,"Kinerja CUKUP – fokus pada KPI merah","Kinerja KURANG – perlu rencana perbaikan biaya & harga"))
B44: Cara membaca: nilai kinerja manajemen dari KPI yang dapat dikendalikan (cash cost excl. royalti, fuel ratio, USD/bcm, beban usaha/pendapatan),
B45: bukan dari KPI yang digerakkan pasar (harga indeks, kurs, royalti). Gunakan jembatan EBITDA di B4 untuk memisahkan efek pasar vs efek manajemen.

Sheet B4 Efisiensi Biaya
A1: Analisa Efisiensi Biaya – Efek Volume vs Efek Tarif/Efisiensi & Jembatan EBITDA (FY2025 vs FY2024)
A2: Efek volume = biaya/unit 2024 × Δvolume; efek tarif = Δbiaya/unit × volume 2025; efek kurs = porsi efek tarif akibat perubahan Rp/USD (item berbasis USD).
A4: 1. ANALISA VARIANS BIAYA PER KOMPONEN (Rp juta)
A5: Komponen biaya | B5: Pemicu volume | C5: Mata uang tarif | D5: Volume 2024 | E5: Volume 2025 | F5: Biaya 2024 | G5: Biaya 2025 | H5: Biaya/unit 2024 (Rp) | I5: Biaya/unit 2025 (Rp) | J5: Δ Total | K5: Efek volume | L5: Efek tarif / efisiensi | M5: Efek kurs (bagian dari efek tarif) | N5: Efisiensi riil (excl. kurs) | O5: Penilaian
A6: Jasa kontraktor OB | B6: per bcm OB | C6: USD | D6: ='A1 Asumsi Contoh'!C16 | E6: ='A1 Asumsi Contoh'!D16 | F6: ='A2 Laba Rugi Contoh'!C17 | G6: ='A2 Laba Rugi Contoh'!D17 | H6: =IFERROR(F6*1000000/D6,0) | I6: =IFERROR(G6*1000000/E6,0) | J6: =G6-F6 | K6: =H6*(E6-D6)/1000000 | L6: =(I6-H6)*E6/1000000 | M6: =IF(C6="USD",G6*(1-'A1 Asumsi Contoh'!C7/'A1 Asumsi Contoh'!D7),0) | N6: =L6-M6 | O6: =IF(N6<=0,"Efisien","Tidak efisien")
A7: BBM | B7: per bcm OB | C7: Rp | D7: ='A1 Asumsi Contoh'!C16 | E7: ='A1 Asumsi Contoh'!D16 | F7: ='A2 Laba Rugi Contoh'!C18 | G7: ='A2 Laba Rugi Contoh'!D18 | H7: =IFERROR(F7*1000000/D7,0) | I7: =IFERROR(G7*1000000/E7,0) | J7: =G7-F7 | K7: =H7*(E7-D7)/1000000 | L7: =(I7-H7)*E7/1000000 | M7: =IF(C7="USD",G7*(1-'A1 Asumsi Contoh'!C7/'A1 Asumsi Contoh'!D7),0) | N7: =L7-M7 | O7: =IF(N7<=0,"Efisien","Tidak efisien")
A8: Peledakan | B8: per bcm OB | C8: USD | D8: ='A1 Asumsi Contoh'!C16 | E8: ='A1 Asumsi Contoh'!D16 | F8: ='A2 Laba Rugi Contoh'!C19 | G8: ='A2 Laba Rugi Contoh'!D19 | H8: =IFERROR(F8*1000000/D8,0) | I8: =IFERROR(G8*1000000/E8,0) | J8: =G8-F8 | K8: =H8*(E8-D8)/1000000 | L8: =(I8-H8)*E8/1000000 | M8: =IF(C8="USD",G8*(1-'A1 Asumsi Contoh'!C7/'A1 Asumsi Contoh'!D7),0) | N8: =L8-M8 | O8: =IF(N8<=0,"Efisien","Tidak efisien")
A9: Coal getting | B9: per ton produksi | C9: USD | D9: ='A1 Asumsi Contoh'!C14 | E9: ='A1 Asumsi Contoh'!D14 | F9: ='A2 Laba Rugi Contoh'!C20 | G9: ='A2 Laba Rugi Contoh'!D20 | H9: =IFERROR(F9*1000000/D9,0) | I9: =IFERROR(G9*1000000/E9,0) | J9: =G9-F9 | K9: =H9*(E9-D9)/1000000 | L9: =(I9-H9)*E9/1000000 | M9: =IF(C9="USD",G9*(1-'A1 Asumsi Contoh'!C7/'A1 Asumsi Contoh'!D7),0) | N9: =L9-M9 | O9: =IF(N9<=0,"Efisien","Tidak efisien")
A10: Biaya tambang tetap (sewa, pemeliharaan, dewatering, survei) | B10: per ton produksi | C10: Rp | D10: ='A1 Asumsi Contoh'!C14 | E10: ='A1 Asumsi Contoh'!D14 | F10: ='A2 Laba Rugi Contoh'!C21+'A2 Laba Rugi Contoh'!C22+'A2 Laba Rugi Contoh'!C23+'A2 Laba Rugi Contoh'!C24 | G10: ='A2 Laba Rugi Contoh'!D21+'A2 Laba Rugi Contoh'!D22+'A2 Laba Rugi Contoh'!D23+'A2 Laba Rugi Contoh'!D24 | H10: =IFERROR(F10*1000000/D10,0) | I10: =IFERROR(G10*1000000/E10,0) | J10: =G10-F10 | K10: =H10*(E10-D10)/1000000 | L10: =(I10-H10)*E10/1000000 | M10: =IF(C10="USD",G10*(1-'A1 Asumsi Contoh'!C7/'A1 Asumsi Contoh'!D7),0) | N10: =L10-M10 | O10: =IF(N10<=0,"Efisien","Tidak efisien")
A11: Crushing & pengolahan | B11: per ton produksi | C11: USD | D11: ='A1 Asumsi Contoh'!C14 | E11: ='A1 Asumsi Contoh'!D14 | F11: ='A2 Laba Rugi Contoh'!C27 | G11: ='A2 Laba Rugi Contoh'!D27 | H11: =IFERROR(F11*1000000/D11,0) | I11: =IFERROR(G11*1000000/E11,0) | J11: =G11-F11 | K11: =H11*(E11-D11)/1000000 | L11: =(I11-H11)*E11/1000000 | M11: =IF(C11="USD",G11*(1-'A1 Asumsi Contoh'!C7/'A1 Asumsi Contoh'!D7),0) | N11: =L11-M11 | O11: =IF(N11<=0,"Efisien","Tidak efisien")
A12: Hauling | B12: per ton-km | C12: USD | D12: ='A1 Asumsi Contoh'!C14*'A1 Asumsi Contoh'!C17 | E12: ='A1 Asumsi Contoh'!D14*'A1 Asumsi Contoh'!D17 | F12: ='A2 Laba Rugi Contoh'!C28 | G12: ='A2 Laba Rugi Contoh'!D28 | H12: =IFERROR(F12*1000000/D12,0) | I12: =IFERROR(G12*1000000/E12,0) | J12: =G12-F12 | K12: =H12*(E12-D12)/1000000 | L12: =(I12-H12)*E12/1000000 | M12: =IF(C12="USD",G12*(1-'A1 Asumsi Contoh'!C7/'A1 Asumsi Contoh'!D7),0) | N12: =L12-M12 | O12: =IF(N12<=0,"Efisien","Tidak efisien")
A13: Pelabuhan & stockpile | B13: per ton penjualan | C13: USD | D13: ='A1 Asumsi Contoh'!C21 | E13: ='A1 Asumsi Contoh'!D21 | F13: ='A2 Laba Rugi Contoh'!C29 | G13: ='A2 Laba Rugi Contoh'!D29 | H13: =IFERROR(F13*1000000/D13,0) | I13: =IFERROR(G13*1000000/E13,0) | J13: =G13-F13 | K13: =H13*(E13-D13)/1000000 | L13: =(I13-H13)*E13/1000000 | M13: =IF(C13="USD",G13*(1-'A1 Asumsi Contoh'!C7/'A1 Asumsi Contoh'!D7),0) | N13: =L13-M13 | O13: =IF(N13<=0,"Efisien","Tidak efisien")
A14: Tongkang & transshipment | B14: per ton penjualan | C14: USD | D14: ='A1 Asumsi Contoh'!C21 | E14: ='A1 Asumsi Contoh'!D21 | F14: ='A2 Laba Rugi Contoh'!C30 | G14: ='A2 Laba Rugi Contoh'!D30 | H14: =IFERROR(F14*1000000/D14,0) | I14: =IFERROR(G14*1000000/E14,0) | J14: =G14-F14 | K14: =H14*(E14-D14)/1000000 | L14: =(I14-H14)*E14/1000000 | M14: =IF(C14="USD",G14*(1-'A1 Asumsi Contoh'!C7/'A1 Asumsi Contoh'!D7),0) | N14: =L14-M14 | O14: =IF(N14<=0,"Efisien","Tidak efisien")
A15: Royalti | B15: per Rp pendapatan | C15: Rp | D15: ='A2 Laba Rugi Contoh'!C10+'A2 Laba Rugi Contoh'!C11 | E15: ='A2 Laba Rugi Contoh'!D10+'A2 Laba Rugi Contoh'!D11 | F15: ='A2 Laba Rugi Contoh'!C33 | G15: ='A2 Laba Rugi Contoh'!D33 | H15: =IFERROR(F15/D15,0) | I15: =IFERROR(G15/E15,0) | J15: =G15-F15 | K15: =H15*(E15-D15) | L15: =(I15-H15)*E15 | M15: =IF(C15="USD",G15*(1-'A1 Asumsi Contoh'!C7/'A1 Asumsi Contoh'!D7),0) | N15: =L15-M15 | O15: =IF(N15<=0,"Efisien","Tidak efisien")
A16: Overhead site | B16: per ton produksi | C16: Rp | D16: ='A1 Asumsi Contoh'!C14 | E16: ='A1 Asumsi Contoh'!D14 | F16: ='A2 Laba Rugi Contoh'!C41 | G16: ='A2 Laba Rugi Contoh'!D41 | H16: =IFERROR(F16*1000000/D16,0) | I16: =IFERROR(G16*1000000/E16,0) | J16: =G16-F16 | K16: =H16*(E16-D16)/1000000 | L16: =(I16-H16)*E16/1000000 | M16: =IF(C16="USD",G16*(1-'A1 Asumsi Contoh'!C7/'A1 Asumsi Contoh'!D7),0) | N16: =L16-M16 | O16: =IF(N16<=0,"Efisien","Tidak efisien")
A17: Perubahan persediaan | B17: n/a | C17: Rp | F17: ='A2 Laba Rugi Contoh'!C48 | G17: ='A2 Laba Rugi Contoh'!D48 | J17: =G17-F17 | K17: =J17 | L17: 0 | M17: =IF(C17="USD",G17*(1-'A1 Asumsi Contoh'!C7/'A1 Asumsi Contoh'!D7),0) | N17: =L17-M17 | O17: =IF(N17<=0,"Efisien","Tidak efisien")
A18: Beban penjualan | B18: per ton penjualan | C18: Rp | D18: ='A1 Asumsi Contoh'!C21 | E18: ='A1 Asumsi Contoh'!D21 | F18: ='A2 Laba Rugi Contoh'!C62 | G18: ='A2 Laba Rugi Contoh'!D62 | H18: =IFERROR(F18*1000000/D18,0) | I18: =IFERROR(G18*1000000/E18,0) | J18: =G18-F18 | K18: =H18*(E18-D18)/1000000 | L18: =(I18-H18)*E18/1000000 | M18: =IF(C18="USD",G18*(1-'A1 Asumsi Contoh'!C7/'A1 Asumsi Contoh'!D7),0) | N18: =L18-M18 | O18: =IF(N18<=0,"Efisien","Tidak efisien")
A19: Beban umum & administrasi (excl. penyusutan) | B19: per ton penjualan | C19: Rp | D19: ='A1 Asumsi Contoh'!C21 | E19: ='A1 Asumsi Contoh'!D21 | F19: ='A2 Laba Rugi Contoh'!C73-'A2 Laba Rugi Contoh'!C71 | G19: ='A2 Laba Rugi Contoh'!D73-'A2 Laba Rugi Contoh'!D71 | H19: =IFERROR(F19*1000000/D19,0) | I19: =IFERROR(G19*1000000/E19,0) | J19: =G19-F19 | K19: =H19*(E19-D19)/1000000 | L19: =(I19-H19)*E19/1000000 | M19: =IF(C19="USD",G19*(1-'A1 Asumsi Contoh'!C7/'A1 Asumsi Contoh'!D7),0) | N19: =L19-M19 | O19: =IF(N19<=0,"Efisien","Tidak efisien")
A20: TOTAL BIAYA KAS (BPP excl. D&A + beban usaha excl. penyusutan) | F20: =SUM(F6:F19) | G20: =SUM(G6:G19) | J20: =SUM(J6:J19) | K20: =SUM(K6:K19) | L20: =SUM(L6:L19) | M20: =SUM(M6:M19) | N20: =SUM(N6:N19) | O20: =IF(N20<=0,"Efisien","Tidak efisien")
A21: Cek: Δ total = efek volume + efek tarif (harus 0) | J21: =ROUND(J20-K20-L20,0)
A22: Royalti memakai pemicu pendapatan: "biaya/unit" = tarif efektif royalti; efek volume = tarif 2024 × Δpendapatan.
A24: 2. JEMBATAN PENDAPATAN BATUBARA (Rp juta)
A25: Uraian | B25: Nilai | C25: Rumus
A26: Pendapatan batubara 2024 | B26: ='A2 Laba Rugi Contoh'!C10 | C26: Dari A2
A27: Efek volume | B27: =('A1 Asumsi Contoh'!D21-'A1 Asumsi Contoh'!C21)*('A2 Laba Rugi Contoh'!C10*1000000/'A1 Asumsi Contoh'!C21/'A1 Asumsi Contoh'!C7)*'A1 Asumsi Contoh'!C7/1000000 | C27: ΔVolume × ASP 2024 × kurs 2024
A28: Efek harga (USD) | B28: ='A1 Asumsi Contoh'!D21*(('A2 Laba Rugi Contoh'!D10*1000000/'A1 Asumsi Contoh'!D21/'A1 Asumsi Contoh'!D7)-('A2 Laba Rugi Contoh'!C10*1000000/'A1 Asumsi Contoh'!C21/'A1 Asumsi Contoh'!C7))*'A1 Asumsi Contoh'!C7/1000000 | C28: Volume 2025 × ΔASP × kurs 2024
A29: Efek kurs | B29: ='A1 Asumsi Contoh'!D21*('A2 Laba Rugi Contoh'!D10*1000000/'A1 Asumsi Contoh'!D21/'A1 Asumsi Contoh'!D7)*('A1 Asumsi Contoh'!D7-'A1 Asumsi Contoh'!C7)/1000000 | C29: Volume 2025 × ASP 2025 × Δkurs
A30: Pendapatan batubara 2025 | B30: =SUM(B26:B29) | C30: Harus sama dengan A2
A31: Cek vs A2 (harus 0) | B31: =ROUND(B30-'A2 Laba Rugi Contoh'!D10,0)
A34: 3. JEMBATAN EBITDA FY2024 → FY2025: memisahkan efek PASAR vs efek MANAJEMEN (Rp juta)
A35: Uraian | B35: Nilai | C35: Kategori | D35: Penjelasan
A36: EBITDA FY2024 | B36: ='A2 Laba Rugi Contoh'!C93 | D36: Titik awal
A37: + Efek volume penjualan | B37: =B27 | C37: Operasional | D37: Tambahan ton terjual
A38: + Efek harga jual (USD) | B38: =B28 | C38: Pasar | D38: Perubahan harga indeks & realisasi
A39: + Efek kurs atas pendapatan | B39: =B29 | C39: Pasar | D39: Pelemahan/penguatan Rupiah
A40: + Perubahan penalti kualitas & pendapatan jasa | B40: =('A2 Laba Rugi Contoh'!D11+'A2 Laba Rugi Contoh'!D12)-('A2 Laba Rugi Contoh'!C11+'A2 Laba Rugi Contoh'!C12) | C40: Manajemen | D40: Kualitas produk & utilisasi aset
A41: – Efek volume atas biaya | B41: =-K20 | C41: Operasional | D41: Biaya tambahan karena volume naik
A42: – Efek kurs atas biaya (USD) | B42: =-M20 | C42: Pasar | D42: Tarif USD dikonversi ke Rupiah
A43: – Efisiensi riil biaya (excl. kurs) | B43: =-N20 | C43: Manajemen | D43: Tarif, produktivitas, SR, BBM, overhead; negatif = boros
A44: EBITDA FY2025 (hasil jembatan) | B44: =SUM(B36:B43)
A45: Cek vs A2 (harus 0) | B45: =ROUND(B44-'A2 Laba Rugi Contoh'!D93,0)
A47: Total efek PASAR (harga, kurs, royalti via harga) | B47: =SUMIF(C36:C43,"Pasar",B36:B43) | D47: Catatan: efek royalti akibat harga termasuk di efisiensi royalti (tarif efektif); untuk presisi lebih, pisahkan tarif royalti per tier HBA.
A48: Total efek OPERASIONAL (volume) | B48: =SUMIF(C36:C43,"Operasional",B36:B43)
A49: Total efek MANAJEMEN (efisiensi & kualitas) | B49: =SUMIF(C36:C43,"Manajemen",B36:B43) | C49: =IF(B49>=0,"Manajemen menambah nilai","Manajemen menggerus nilai")
A52: 4. INISIATIF EFISIENSI BIAYA & POTENSI PENGHEMATAN (berbasis data FY2025)
A53: Inisiatif | B53: Tuas (lever) | C53: Asumsi perbaikan | D53: Satuan asumsi | E53: Potensi penghematan (Rp juta/tahun) | F53: Setara USD/t terjual | G53: % thd EBITDA 2025 | H53: KPI pemantau | I53: PIC | J53: Timeline
A54: Program penghematan BBM (idle time, payload, fuel monitoring) | B54: Fuel ratio | C54: 0.05 | D54: L/bcm | E54: ='A1 Asumsi Contoh'!D16*C54*'A1 Asumsi Contoh'!D30/1000000 | F54: =E54*1000000/'A1 Asumsi Contoh'!D21/'A1 Asumsi Contoh'!D7 | G54: =E54/'A2 Laba Rugi Contoh'!D93 | H54: Fuel ratio L/bcm | I54: Mining Ops | J54: Q1–Q2
A55: Negosiasi ulang tarif kontraktor OB (rise & fall, benchmark) | B55: Tarif USD/bcm | C55: 0.03 | D55: % tarif | E55: ='A2 Laba Rugi Contoh'!D17*C55 | F55: =E55*1000000/'A1 Asumsi Contoh'!D21/'A1 Asumsi Contoh'!D7 | G55: =E55/'A2 Laba Rugi Contoh'!D93 | H55: USD/bcm OB | I55: Procurement | J55: Q1
A56: Optimasi desain pit & sekuens (turunkan SR) | B56: Stripping ratio | C56: 0.2 | D56: bcm/t | E56: ='A1 Asumsi Contoh'!D14*C56*'B2 COP dan KPI'!D9*1000000/'B2 COP dan KPI'!F9/1000000 | F56: =E56*1000000/'A1 Asumsi Contoh'!D21/'A1 Asumsi Contoh'!D7 | G56: =E56/'A2 Laba Rugi Contoh'!D93 | H56: SR aktual vs plan | I56: Mine Planning | J56: Q2–Q4
A57: Perbaikan jalan hauling & dispatch (cycle time) | B57: Tarif hauling | C57: 0.05 | D57: % biaya | E57: ='A2 Laba Rugi Contoh'!D28*C57 | F57: =E57*1000000/'A1 Asumsi Contoh'!D21/'A1 Asumsi Contoh'!D7 | G57: =E57/'A2 Laba Rugi Contoh'!D93 | H57: USD/t-km | I57: Logistik | J57: Q2
A58: Kontrak tongkang jangka panjang & optimasi load-out | B58: Tarif barging | C58: 0.03 | D58: % biaya | E58: ='A2 Laba Rugi Contoh'!D30*C58 | F58: =E58*1000000/'A1 Asumsi Contoh'!D21/'A1 Asumsi Contoh'!D7 | G58: =E58/'A2 Laba Rugi Contoh'!D93 | H58: USD/t barging | I58: Logistik | J58: Q1–Q2
A59: Pengendalian demurrage (laycan planning) | B59: Demurrage | C59: 0.5 | D59: % biaya | E59: ='A2 Laba Rugi Contoh'!D59*C59 | F59: =E59*1000000/'A1 Asumsi Contoh'!D21/'A1 Asumsi Contoh'!D7 | G59: =E59/'A2 Laba Rugi Contoh'!D93 | H59: Hari demurrage | I59: Marketing | J59: Q1
A60: Quality control & blending (kurangi penalti) | B60: Penalti kualitas | C60: 0.5 | D60: % penalti | E60: =-'A2 Laba Rugi Contoh'!D11*C60 | F60: =E60*1000000/'A1 Asumsi Contoh'!D21/'A1 Asumsi Contoh'!D7 | G60: =E60/'A2 Laba Rugi Contoh'!D93 | H60: Penalti % pendapatan | I60: QC / Marketing | J60: Q1–Q2
A61: Sentralisasi pengadaan & rasionalisasi overhead | B61: Overhead + G&A | C61: 0.05 | D61: % biaya | E61: =('A2 Laba Rugi Contoh'!D41-'A2 Laba Rugi Contoh'!D38+'A2 Laba Rugi Contoh'!D73-'A2 Laba Rugi Contoh'!D71)*C61 | F61: =E61*1000000/'A1 Asumsi Contoh'!D21/'A1 Asumsi Contoh'!D7 | G61: =E61/'A2 Laba Rugi Contoh'!D93 | H61: Overhead USD/t | I61: Finance / HR | J61: Q1–Q3
A62: Peningkatan realisasi harga ekspor (marketing & spesifikasi) | B62: Harga realisasi | C62: 1 | D62: USD/t ekspor | E62: ='A1 Asumsi Contoh'!D18*C62*'A1 Asumsi Contoh'!D7/1000000 | F62: =E62*1000000/'A1 Asumsi Contoh'!D21/'A1 Asumsi Contoh'!D7 | G62: =E62/'A2 Laba Rugi Contoh'!D93 | H62: ASP vs indeks | I62: Marketing | J62: Q1–Q4
A63: TOTAL POTENSI | E63: =SUM(E54:E62) | F63: =SUM(F54:F62) | G63: =SUM(G54:G62)
A64: Asumsi perbaikan (sel kuning) adalah contoh penyusun – sesuaikan dengan hasil kajian lapangan GEG.

Sheet B5 Benchmark Emiten
A1: Referensi Emiten Batubara di BEI & Kisaran KPI Industri (indikatif)
A2: Gunakan untuk membandingkan format & KPI. Angka kisaran bersifat indikatif – WAJIB divalidasi dengan laporan tahunan/keuangan terbaru.
A4: 1. EMITEN BATUBARA TBK SEBAGAI ACUAN FORMAT LAPORAN
A5: Kode | B5: Emiten | C5: Mata uang penyajian | D5: Karakteristik yang relevan | E5: Hal yang dapat dipelajari
A6: PTBA | B6: PT Bukit Asam Tbk | C6: Rupiah | D6: BUMN (MIND ID); tambang sendiri + kontraktor; angkutan kereta api | E6: Format LK dalam Rupiah – paling mirip kebutuhan GEG; rincian BPP per jenis biaya
A7: ITMG | B7: PT Indo Tambangraya Megah Tbk | C7: USD | D7: Grup Banpu; beberapa konsesi di Kaltim/Kalsel | E7: Rincian BPP (kontraktor, BBM, royalti), KPI SR & cash cost di laporan tahunan
A8: AADI | B8: PT Adaro Andalan Indonesia Tbk | C8: USD | D8: Pemisahan bisnis batubara termal grup Adaro (2024); integrasi tambang–logistik | E8: Contoh integrasi hauling, barging, pelabuhan; pelaporan segmen
A9: BUMI | B9: PT Bumi Resources Tbk | C9: USD | D9: Pemegang KPC & Arutmin (IUPK) | E9: Struktur royalti IUPK; laporan entitas asosiasi
A10: BYAN | B10: PT Bayan Resources Tbk | C10: USD | D10: Biaya produksi rendah, SR rendah, logistik sungai | E10: Benchmark efisiensi biaya & SR
A11: INDY | B11: PT Indika Energy Tbk | C11: USD | D11: Grup energi terdiversifikasi (Kideco) | E11: Pelaporan segmen & diversifikasi
A12: GEMS | B12: PT Golden Energy Mines Tbk | C12: USD | D12: Produsen batubara kalori menengah–rendah | E12: Profil produk CV rendah mirip banyak tambang IUP
A13: HRUM | B13: PT Harum Energy Tbk | C13: USD | D13: Batubara + diversifikasi nikel | E13: Pelaporan segmen lintas komoditas
A15: Sumber unduhan: www.idx.co.id → Perusahaan Tercatat → Laporan Keuangan & Tahunan; situs Investor Relations masing-masing emiten; MODI/MinerbaOne (Kementerian ESDM) untuk data produksi & HBA.
A16: Di catatan atas laporan keuangan (CALK), cari catatan: "Pendapatan" (per pelanggan/pasar), "Beban Pokok Pendapatan" (rincian per jenis biaya), "Beban Usaha", "Informasi Segmen", "Provisi Reklamasi".
A18: 2. KISARAN KPI INDUSTRI BATUBARA TERMAL INDONESIA (INDIKATIF – validasi sebelum dipakai sebagai target)
A19: KPI | B19: Satuan | C19: Kisaran indikatif | D19: Faktor penentu | E19: Catatan
A20: Stripping ratio | B20: bcm/t | C20: 3 – 12 | D20: Geologi, kedalaman seam, desain pit | E20: Tambang SR rendah (<5) umumnya berbiaya rendah
A21: Tarif kontraktor OB (excl. BBM) | B21: USD/bcm | C21: ± 1,5 – 3,0 | D21: Jarak angkut OB, fleet, kontrak rise & fall | E21: Sangat bergantung kontrak
A22: Fuel ratio | B22: L/bcm | C22: ± 0,8 – 1,2 | D22: Jarak & grade jalan, umur armada
A23: Tarif hauling batubara | B23: USD/t-km | C23: ± 0,08 – 0,15 | D23: Kondisi jalan, kapasitas truk
A24: Tarif barging | B24: USD/t | C24: ± 3 – 8 | D24: Jarak sungai/laut, musim, pasar tongkang
A25: Cash cost FOB excl. royalti | B25: USD/t | C25: ± 25 – 50 | D25: SR, logistik, skala | E25: Bandingkan pada CV setara
A26: Royalti | B26: % harga | C26: IUP: bertingkat (PP 26/2022); IUPK: 14%–28% (PP 15/2022) | D26: CV, HBA, jenis izin | E26: Cek regulasi terbaru
A27: Physical availability (PA) | B27: % | C27: ± 85 – 92 | D27: Program perawatan
A28: Use of availability (UA) | B28: % | C28: ± 70 – 85 | D28: Hujan, slippery, manajemen dispatch
A29: Marjin EBITDA | B29: % | C29: sangat siklikal: ± 15 – 45 | D29: Harga batubara, biaya | E29: Bandingkan dalam tahun yang sama
A30: Kewajiban DMO | B30: % penjualan | C30: ≥ 25 | D30: Kepmen ESDM | E30: Kompensasi/denda bila tidak terpenuhi
A32: Disclaimer: kisaran di atas adalah perkiraan umum penyusun untuk orientasi, bukan kutipan dari laporan emiten tertentu.

Sheet C0 GEG Petunjuk
A1: GEG – Petunjuk Penggunaan Template Pelaporan Bulanan
A2: Global Energy Group | FP&A monthly management reporting pack
A4: A. STRUKTUR TEMPLATE
A5: C1 GEG Setting | B5: Pilih bulan laporan, skala penilaian KPI, predikat. Satu sel (C6) menggerakkan seluruh laporan.
A6: C2 / C3 Ops Budget & Aktual | B6: Data operasional bulanan: OB, produksi, SR, hauling, barging, penjualan per pasar, harga, kurs, BBM, PA/UA, K3, reklamasi.
A7: C4 / C5 LR Budget & Aktual | B7: Laba rugi bulanan per kode akun MIS – OTOMATIS dari C19 GL Trial Balance (SUMIFS berdasarkan Tag MIS). Tidak perlu diketik ulang.
A8: C6 Neraca Aktual | B8: Saldo neraca akhir bulan + saldo awal tahun. Baris cek harus 0.
A9: C7 Arus Kas | B9: Otomatis (metode tidak langsung) dari C5 & C6, termasuk rekonsiliasi kas & free cash flow.
A10: C8 Lap LR | B10: Laba rugi bulan berjalan & YTD: aktual vs budget, varians, F/U.
A11: C9 Lap Ops | B11: Kinerja operasional bulan berjalan & YTD vs budget dengan status tercapai.
A12: C10 COP | B12: Cost of production per unit (USD/bcm, USD/t, USD/t-km), cash cost, total cost, marjin kas.
A13: C12 Dashboard | B13: Tile KPI, grafik kinerja bulanan & tabel KPI Scored.
A14: C13 – C17 (format AAT) | B14: Financial Highlight MoM/budget/YTD, analisa biaya & unit cost, tren volume vs tahun lalu, pit & pembeli, arus kas langsung + DSCR. Kolom catatan varians diisi FP&A.
A15: C11 KPI Scorecard | B15: 28 KPI dalam 5 perspektif, bobot 100%, skor 1–5, status Hijau/Kuning/Merah, predikat kinerja.
A16: B. KODE WARNA
A17: Teks biru + sel kuning muda | B17: Sel input – diisi dari GL / laporan produksi. Data contoh sudah terisi: GANTI dengan data GEG.
A18: Teks hitam | B18: Rumus – jangan ditimpa.
A19: Teks hijau | B19: Tautan dari sheet lain.
A20: Sel kuning terang | B20: Parameter kunci (bulan laporan, skor total).
A21: C. LANGKAH PENUTUPAN BULANAN (MONTHLY CLOSING)
A22: H+3 | B22: Operasi menyerahkan data produksi final (rekonsiliasi survei bulanan OB & stok, bukan hanya truck count).
A23: H+5 | B23: Akuntansi menutup buku; mapping GL → kode akun template (4xxx pendapatan, 5xxx BPP, 6xxx beban usaha, 7xxx lain-lain, 8xxx pajak).
A24: H+6 | B24: FP&A tempel trial balance ke C19 (beri Tag MIS untuk akun baru), input C3 & C6 → buka C22 Kontrol Data: semua status harus OK (SIAP KIRIM).
A25: H+7 | B25: FP&A menulis komentar varians > ±5% atau > Rp 1 miliar di C8/C10; review KPI merah bersama PIC.
A26: H+8 | B26: Paket laporan ke Direksi: C8, C9, C10, C11 (+ grafik bila perlu).
A27: D. ATURAN PENTING
A28: Konsistensi basis | B28: Mining cost per ton PRODUKSI; logistik, royalti, penjualan & cash cost per ton PENJUALAN; OB per BCM.
A29: Tanda (sign) | B29: Beban diisi positif. Penalti kualitas & beban keuangan diisi negatif. Perubahan persediaan: positif bila stok turun.
A30: Budget | B30: Budget/RKAP dikunci setelah disetujui; revisi disimpan sebagai versi terpisah (mis. Forecast Q2).
A31: Rekonsiliasi | B31: Volume penjualan C3 harus cocok dengan invoice & B/L; produksi harus cocok dengan laporan RKAB/MODI.
A32: Menambah akun | B32: Sisipkan baris DI ATAS baris subtotal agar rumus SUM otomatis mencakup; periksa ulang C8 & C10.

Sheet C1 GEG Setting
A1: GEG – Pengaturan Laporan & Parameter KPI
A2: Ubah BULAN LAPORAN (sel kuning terang) untuk menggeser seluruh laporan bulanan & scorecard.
F3: No | G3: Bulan
A4: Nama perusahaan | C4: PT Global Energy Group | F4: 1 | G4: Jan
A5: Tahun anggaran | C5: 2026 | F5: 2 | G5: Feb
A6: Bulan laporan (1–12) | C6: 8 | F6: 3 | G6: Mar
A7: Nama bulan laporan | C7: =INDEX($G$4:$G$15,C6) | F7: 4 | G7: Apr
A8: Satuan uang | C8: Rp juta | F8: 5 | G8: Mei
A9: Kurs budget (informasi) | C9: 16400 | F9: 6 | G9: Jun
F10: 7 | G10: Jul
A11: SKALA PENILAIAN KPI | F11: 8 | G11: Agu
A12: Skor 5 jika pencapaian ≥ | C12: 1.05 | F12: 9 | G12: Sep
A13: Skor 4 jika pencapaian ≥ | C13: 1 | F13: 10 | G13: Okt
A14: Skor 3 jika pencapaian ≥ | C14: 0.95 | F14: 11 | G14: Nov
A15: Skor 2 jika pencapaian ≥ | C15: 0.9 | F15: 12 | G15: Des
A16: Status HIJAU jika pencapaian ≥ | C16: 1
A17: Status KUNING jika pencapaian ≥ | C17: 0.95
A18: Batas atas pencapaian (cap) | C18: 1.2
A19: Skor 1 bila di bawah ambang skor 2; status MERAH bila di bawah ambang kuning.
A21: PREDIKAT SKOR TERTIMBANG
A22: Skor minimum | C22: Predikat
A23: 4.5 | C23: Sangat Baik
A24: 3.5 | C24: Baik
A25: 2.5 | C25: Cukup
A26: 1.5 | C26: Kurang
A27: 0 | C27: Buruk

Sheet C2 GEG Ops Budget
A1: GEG – Data Operasional BUDGET / RKAP Bulanan
A2: Isi sel kuning (teks biru) per bulan. Baris hitam = rumus otomatis. Kolom P = total/rata-rata tahun.
D5: 1 | E5: 2 | F5: 3 | G5: 4 | H5: 5 | I5: 6 | J5: 7 | K5: 8 | L5: 9 | M5: 10 | N5: 11 | O5: 12
A6: No | B6: Parameter | C6: Satuan | D6: Jan | E6: Feb | F6: Mar | G6: Apr | H6: Mei | I6: Jun | J6: Jul | K6: Agu | L6: Sep | M6: Okt | N6: Nov | O6: Des | P6: FY / YTD
A7: PRODUKSI & OPERASI TAMBANG
A8: 1 | B8: OB removal | C8: bcm | D8: 1677000 | E8: 1638000 | F8: 1813500 | G8: 1950000 | H8: 2047500 | I8: 2086500 | J8: 2145000 | K8: 2145000 | L8: 2067000 | M8: 1989000 | N8: 1891500 | O8: 1794000 | P8: =SUM(D8:O8)
A9: 2 | B9: Produksi batubara (coal getting / ROM) | C9: ton | D9: 215000 | E9: 210000 | F9: 232500 | G9: 250000 | H9: 262500 | I9: 267500 | J9: 275000 | K9: 275000 | L9: 265000 | M9: 255000 | N9: 242500 | O9: 230000 | P9: =SUM(D9:O9)
A10: 3 | B10: Stripping ratio | C10: bcm/t | D10: =IFERROR(D8/D9,0) | E10: =IFERROR(E8/E9,0) | F10: =IFERROR(F8/F9,0) | G10: =IFERROR(G8/G9,0) | H10: =IFERROR(H8/H9,0) | I10: =IFERROR(I8/I9,0) | J10: =IFERROR(J8/J9,0) | K10: =IFERROR(K8/K9,0) | ... P10: =IFERROR(P8/P9,0)
A11: 4 | B11: Hauling batubara ke pelabuhan | C11: ton | D11: 212850 | E11: 207900 | F11: 230175 | G11: 247500 | H11: 259875 | I11: 264825 | J11: 272250 | K11: 272250 | L11: 262350 | M11: 252450 | N11: 240075 | O11: 227700 | P11: =SUM(D11:O11)
A12: 5 | B12: Jarak hauling rata-rata | C12: km | D12: 30 | E12: 30 | F12: 30 | G12: 30 | H12: 30 | I12: 30 | J12: 30 | K12: 30 | L12: 30 | M12: 30 | N12: 30 | O12: 30 | P12: =IFERROR(SUMPRODUCT(D12:O12,D11:O11)/SUM(D11:O11),0)
A13: 6 | B13: Barging / pemuatan tongkang | C13: ton | D13: 210700 | E13: 205800 | F13: 227850 | G13: 245000 | H13: 257250 | I13: 262150 | J13: 269500 | K13: 269500 | L13: 259700 | M13: 249900 | N13: 237650 | O13: 225400 | P13: =SUM(D13:O13)
A14: 7 | B14: Stok batubara akhir bulan (ROM + pelabuhan) | C14: ton | D14: 184300 | E14: 188500 | F14: 193150 | G14: 198150 | H14: 203400 | I14: 208750 | J14: 214250 | K14: 219750 | L14: 225050 | M14: 230150 | N14: 235000 | O14: 239600 | P14: =IFERROR(INDEX(D14:O14,COUNT(D14:O14)),0)
A15: PENJUALAN & HARGA
A16: 8 | B16: Penjualan – Ekspor | C16: ton | D16: 126420 | E16: 123480 | F16: 136710 | G16: 147000 | H16: 154350 | I16: 157290 | J16: 161700 | K16: 161700 | L16: 155820 | M16: 149940 | N16: 142590 | O16: 135240 | P16: =SUM(D16:O16)
A17: 9 | B17: Penjualan – Domestik DMO | C17: ton | D17: 58996 | E17: 57624 | F17: 63798 | G17: 68600 | H17: 72030 | I17: 73402 | J17: 75460 | K17: 75460 | L17: 72716 | M17: 69972 | N17: 66542 | O17: 63112 | P17: =SUM(D17:O17)
A18: 10 | B18: Penjualan – Domestik non-DMO | C18: ton | D18: 25284 | E18: 24696 | F18: 27342 | G18: 29400 | H18: 30870 | I18: 31458 | J18: 32340 | K18: 32340 | L18: 31164 | M18: 29988 | N18: 28518 | O18: 27048 | P18: =SUM(D18:O18)
A19: 11 | B19: Total penjualan | C19: ton | D19: =D16+D17+D18 | E19: =E16+E17+E18 | F19: =F16+F17+F18 | G19: =G16+G17+G18 | H19: =H16+H17+H18 | I19: =I16+I17+I18 | J19: =J16+J17+J18 | K19: =K16+K17+K18 | ... P19: =P16+P17+P18
A20: 12 | B20: ASP – Ekspor | C20: USD/t | D20: 62 | E20: 62 | F20: 62 | G20: 62 | H20: 62 | I20: 62 | J20: 62 | K20: 62 | L20: 62 | M20: 62 | N20: 62 | O20: 62 | P20: =IFERROR(SUMPRODUCT(D20:O20,D16:O16)/SUM(D16:O16),0)
A21: 13 | B21: ASP – Domestik DMO | C21: USD/t | D21: 42 | E21: 42 | F21: 42 | G21: 42 | H21: 42 | I21: 42 | J21: 42 | K21: 42 | L21: 42 | M21: 42 | N21: 42 | O21: 42 | P21: =IFERROR(SUMPRODUCT(D21:O21,D17:O17)/SUM(D17:O17),0)
A22: 14 | B22: ASP – Domestik non-DMO | C22: USD/t | D22: 50 | E22: 50 | F22: 50 | G22: 50 | H22: 50 | I22: 50 | J22: 50 | K22: 50 | L22: 50 | M22: 50 | N22: 50 | O22: 50 | P22: =IFERROR(SUMPRODUCT(D22:O22,D18:O18)/SUM(D18:O18),0)
A23: 15 | B23: Harga indeks acuan (HBA/ICI setara CV) | C23: USD/t | D23: 66 | E23: 66 | F23: 66 | G23: 66 | H23: 66 | I23: 66 | J23: 66 | K23: 66 | L23: 66 | M23: 66 | N23: 66 | O23: 66 | P23: =IFERROR(AVERAGE(D23:O23),0)
A24: 16 | B24: Nilai kalori realisasi | C24: kcal/kg GAR | D24: 4300 | E24: 4300 | F24: 4300 | G24: 4300 | H24: 4300 | I24: 4300 | J24: 4300 | K24: 4300 | L24: 4300 | M24: 4300 | N24: 4300 | O24: 4300 | P24: =IFERROR(SUMPRODUCT(D24:O24,D19:O19)/SUM(D19:O19),0)
A25: 17 | B25: Kurs rata-rata | C25: Rp/USD | D25: 16400 | E25: 16400 | F25: 16400 | G25: 16400 | H25: 16400 | I25: 16400 | J25: 16400 | K25: 16400 | L25: 16400 | M25: 16400 | N25: 16400 | O25: 16400 | P25: =IFERROR(AVERAGE(D25:O25),0)
A26: SARANA, BBM & CUACA
A27: 18 | B27: Konsumsi BBM | C27: liter | D27: 1593150 | E27: 1556100 | F27: 1722825 | G27: 1852500 | H27: 1945125 | I27: 1982175 | J27: 2037750 | K27: 2037750 | L27: 1963650 | M27: 1889550 | N27: 1796925 | O27: 1704300 | P27: =SUM(D27:O27)
A28: 19 | B28: Fuel ratio | C28: L/bcm | D28: =IFERROR(D27/D8,0) | E28: =IFERROR(E27/E8,0) | F28: =IFERROR(F27/F8,0) | G28: =IFERROR(G27/G8,0) | H28: =IFERROR(H27/H8,0) | I28: =IFERROR(I27/I8,0) | J28: =IFERROR(J27/J8,0) | K28: =IFERROR(K27/K8,0) | ... P28: =IFERROR(P27/P8,0)
A29: 20 | B29: Jam hujan + slippery | C29: jam | D29: 180 | E29: 170 | F29: 160 | G29: 120 | H29: 100 | I29: 80 | J29: 60 | K29: 60 | L29: 70 | M29: 110 | N29: 150 | O29: 170 | P29: =SUM(D29:O29)
A30: 21 | B30: Physical availability (PA) armada utama | C30: % | D30: 0.88 | E30: 0.88 | F30: 0.88 | G30: 0.88 | H30: 0.88 | I30: 0.88 | J30: 0.88 | K30: 0.88 | L30: 0.88 | M30: 0.88 | N30: 0.88 | O30: 0.88 | P30: =IFERROR(AVERAGE(D30:O30),0)
A31: 22 | B31: Use of availability (UA) armada utama | C31: % | D31: 0.75 | E31: 0.75 | F31: 0.75 | G31: 0.75 | H31: 0.75 | I31: 0.75 | J31: 0.75 | K31: 0.75 | L31: 0.75 | M31: 0.75 | N31: 0.75 | O31: 0.75 | P31: =IFERROR(AVERAGE(D31:O31),0)
A32: SDM, K3 & LINGKUNGAN
A33: 23 | B33: Jumlah tenaga kerja (organik + kontraktor) | C33: orang | D33: 1450 | E33: 1450 | F33: 1450 | G33: 1450 | H33: 1450 | I33: 1450 | J33: 1450 | K33: 1450 | L33: 1450 | M33: 1450 | N33: 1450 | O33: 1450 | P33: =IFERROR(INDEX(D33:O33,COUNT(D33:O33)),0)
A34: 24 | B34: Jam kerja orang (man-hours) | C34: jam | D34: 362500 | E34: 362500 | F34: 362500 | G34: 362500 | H34: 362500 | I34: 362500 | J34: 362500 | K34: 362500 | L34: 362500 | M34: 362500 | N34: 362500 | O34: 362500 | P34: =SUM(D34:O34)
A35: 25 | B35: Kecelakaan hilang waktu kerja (LTI) | C35: kasus | D35: 0 | E35: 0 | F35: 0 | G35: 0 | H35: 0 | I35: 0 | J35: 0 | K35: 0 | L35: 0 | M35: 0 | N35: 0 | O35: 0 | P35: =SUM(D35:O35)
A36: 26 | B36: LTIFR | C36: per 1 juta jam | D36: =IFERROR(D35*1000000/D34,0) | E36: =IFERROR(E35*1000000/E34,0) | F36: =IFERROR(F35*1000000/F34,0) | G36: =IFERROR(G35*1000000/G34,0) | H36: =IFERROR(H35*1000000/H34,0) | I36: =IFERROR(I35*1000000/I34,0) | J36: =IFERROR(J35*1000000/J34,0) | K36: =IFERROR(K35*1000000/K34,0) | ... P36: =IFERROR(P35*1000000/P34,0)
A37: 27 | B37: Bukaan lahan | C37: ha | D37: 12 | E37: 12 | F37: 12 | G37: 12 | H37: 12 | I37: 12 | J37: 12 | K37: 12 | L37: 12 | M37: 12 | N37: 12 | O37: 12 | P37: =SUM(D37:O37)
A38: 28 | B38: Reklamasi & revegetasi | C38: ha | D38: 8 | E38: 8 | F38: 8 | G38: 8 | H38: 8 | I38: 8 | J38: 8 | K38: 8 | L38: 8 | M38: 8 | N38: 8 | O38: 8 | P38: =SUM(D38:O38)

Sheet C3 GEG Ops Aktual
A1: GEG – Data Operasional AKTUAL Bulanan
A2: Isi sel kuning (teks biru) per bulan. Baris hitam = rumus otomatis. Kolom P = total/rata-rata tahun.
D5: 1 | E5: 2 | F5: 3 | G5: 4 | H5: 5 | I5: 6 | J5: 7 | K5: 8 | L5: 9 | M5: 10 | N5: 11 | O5: 12
A6: No | B6: Parameter | C6: Satuan | D6: Jan | E6: Feb | F6: Mar | G6: Apr | H6: Mei | I6: Jun | J6: Jul | K6: Agu | L6: Sep | M6: Okt | N6: Nov | O6: Des | P6: FY / YTD
A7: PRODUKSI & OPERASI TAMBANG
A8: 1 | B8: OB removal | C8: bcm | D8: 1558766 | E8: 1726600 | F8: 1750198 | G8: 2095849 | H8: 1934365 | I8: 1883049 | J8: 2195899 | K8: 2218568 | P8: =SUM(D8:O8)
A9: 2 | B9: Produksi batubara (coal getting / ROM) | C9: ton | D9: 193042 | E9: 212866 | F9: 209826 | G9: 255864 | H9: 237723 | I9: 239194 | J9: 274042 | K9: 283132 | P9: =SUM(D9:O9)
A10: 3 | B10: Stripping ratio | C10: bcm/t | D10: =IFERROR(D8/D9,0) | E10: =IFERROR(E8/E9,0) | F10: =IFERROR(F8/F9,0) | G10: =IFERROR(G8/G9,0) | H10: =IFERROR(H8/H9,0) | I10: =IFERROR(I8/I9,0) | J10: =IFERROR(J8/J9,0) | K10: =IFERROR(K8/K9,0) | ... P10: =IFERROR(P8/P9,0)
A11: 4 | B11: Hauling batubara ke pelabuhan | C11: ton | D11: 191111 | E11: 210737 | F11: 207728 | G11: 253305 | H11: 235345 | I11: 236803 | J11: 271302 | K11: 280301 | P11: =SUM(D11:O11)
A12: 5 | B12: Jarak hauling rata-rata | C12: km | D12: 30.77 | E12: 31.3 | F12: 31.44 | G12: 30.95 | H12: 30.31 | I12: 30.01 | J12: 30.02 | K12: 30.18 | P12: =IFERROR(SUMPRODUCT(D12:O12,D11:O11)/SUM(D11:O11),0)
A13: 6 | B13: Barging / pemuatan tongkang | C13: ton | D13: 191690 | E13: 206750 | F13: 207765 | G13: 245050 | H13: 233246 | I13: 228348 | J13: 261662 | K13: 269504 | P13: =SUM(D13:O13)
A14: 7 | B14: Stok batubara akhir bulan (ROM + pelabuhan) | C14: ton | D14: 181351 | E14: 187466 | F14: 189527 | G14: 200341 | H14: 204818 | I14: 215664 | J14: 228044 | K14: 241673 | P14: =IFERROR(INDEX(D14:O14,COUNT(D14:O14)),0)
A15: PENJUALAN & HARGA
A16: 8 | B16: Penjualan – Ekspor | C16: ton | D16: 106807 | E16: 125328 | F16: 127752 | G16: 140154 | H16: 135776 | I16: 132850 | J16: 144335 | K16: 158086 | P16: =SUM(D16:O16)
A17: 9 | B17: Penjualan – Domestik DMO | C17: ton | D17: 51552 | E17: 60923 | F17: 57010 | G17: 69428 | H17: 62821 | I17: 62389 | J17: 69320 | K17: 76506 | P17: =SUM(D17:O17)
A18: 10 | B18: Penjualan – Domestik non-DMO | C18: ton | D18: 33332 | E18: 20500 | F18: 23003 | G18: 35468 | H18: 34649 | I18: 33109 | J18: 48007 | K18: 34912 | P18: =SUM(D18:O18)
A19: 11 | B19: Total penjualan | C19: ton | D19: =D16+D17+D18 | E19: =E16+E17+E18 | F19: =F16+F17+F18 | G19: =G16+G17+G18 | H19: =H16+H17+H18 | I19: =I16+I17+I18 | J19: =J16+J17+J18 | K19: =K16+K17+K18 | ... P19: =P16+P17+P18
A20: 12 | B20: ASP – Ekspor | C20: USD/t | D20: 61.01 | E20: 62.54 | F20: 58.78 | G20: 61.95 | H20: 61.63 | I20: 60.7 | J20: 61.49 | K20: 63.09 | P20: =IFERROR(SUMPRODUCT(D20:O20,D16:O16)/SUM(D16:O16),0)
A21: 13 | B21: ASP – Domestik DMO | C21: USD/t | D21: 42 | E21: 42 | F21: 42 | G21: 42 | H21: 42 | I21: 42 | J21: 42 | K21: 42 | P21: =IFERROR(SUMPRODUCT(D21:O21,D17:O17)/SUM(D17:O17),0)
A22: 14 | B22: ASP – Domestik non-DMO | C22: USD/t | D22: 49.45 | E22: 48.89 | F22: 49.92 | G22: 50.82 | H22: 49.42 | I22: 50.42 | J22: 49.52 | K22: 48.56 | P22: =IFERROR(SUMPRODUCT(D22:O22,D18:O18)/SUM(D18:O18),0)
A23: 15 | B23: Harga indeks acuan (HBA/ICI setara CV) | C23: USD/t | D23: 67.12 | E23: 66.1 | F23: 65.87 | G23: 65.97 | H23: 64.16 | I23: 67.37 | J23: 67.73 | K23: 65.7 | P23: =IFERROR(AVERAGE(D23:O23),0)
A24: 16 | B24: Nilai kalori realisasi | C24: kcal/kg GAR | D24: 4288 | E24: 4318 | F24: 4241 | G24: 4211 | H24: 4271 | I24: 4299 | J24: 4265 | K24: 4233 | P24: =IFERROR(SUMPRODUCT(D24:O24,D19:O19)/SUM(D19:O19),0)
A25: 17 | B25: Kurs rata-rata | C25: Rp/USD | D25: 16492 | E25: 16596 | F25: 16568 | G25: 16552 | H25: 16527 | I25: 16364 | J25: 16423 | K25: 16344 | P25: =IFERROR(AVERAGE(D25:O25),0)
A26: SARANA, BBM & CUACA
A27: 18 | B27: Konsumsi BBM | C27: liter | D27: 1556554 | E27: 1705028 | F27: 1720551 | G27: 2009854 | H27: 1859947 | I27: 1792301 | J27: 2199970 | K27: 2168910 | P27: =SUM(D27:O27)
A28: 19 | B28: Fuel ratio | C28: L/bcm | D28: =IFERROR(D27/D8,0) | E28: =IFERROR(E27/E8,0) | F28: =IFERROR(F27/F8,0) | G28: =IFERROR(G27/G8,0) | H28: =IFERROR(H27/H8,0) | I28: =IFERROR(I27/I8,0) | J28: =IFERROR(J27/J8,0) | K28: =IFERROR(K27/K8,0) | ... P28: =IFERROR(P27/P8,0)
A29: 20 | B29: Jam hujan + slippery | C29: jam | D29: 216 | E29: 188 | F29: 186 | G29: 136 | H29: 127 | I29: 83 | J29: 70 | K29: 73 | P29: =SUM(D29:O29)
A30: 21 | B30: Physical availability (PA) armada utama | C30: % | D30: 0.867 | E30: 0.884 | F30: 0.823 | G30: 0.897 | H30: 0.824 | I30: 0.875 | J30: 0.869 | K30: 0.873 | P30: =IFERROR(AVERAGE(D30:O30),0)
A31: 22 | B31: Use of availability (UA) armada utama | C31: % | D31: 0.704 | E31: 0.738 | F31: 0.709 | G31: 0.768 | H31: 0.767 | I31: 0.759 | J31: 0.772 | K31: 0.757 | P31: =IFERROR(AVERAGE(D31:O31),0)
A32: SDM, K3 & LINGKUNGAN
A33: 23 | B33: Jumlah tenaga kerja (organik + kontraktor) | C33: orang | D33: 1469 | E33: 1438 | F33: 1459 | G33: 1462 | H33: 1442 | I33: 1443 | J33: 1450 | K33: 1441 | P33: =IFERROR(INDEX(D33:O33,COUNT(D33:O33)),0)
A34: 24 | B34: Jam kerja orang (man-hours) | C34: jam | D34: 351776 | E34: 367999 | F34: 370170 | G34: 356395 | H34: 360644 | I34: 352413 | J34: 363371 | K34: 361944 | P34: =SUM(D34:O34)
A35: 25 | B35: Kecelakaan hilang waktu kerja (LTI) | C35: kasus | D35: 0 | E35: 0 | F35: 1 | G35: 0 | H35: 0 | I35: 1 | J35: 0 | K35: 0 | P35: =SUM(D35:O35)
A36: 26 | B36: LTIFR | C36: per 1 juta jam | D36: =IFERROR(D35*1000000/D34,0) | E36: =IFERROR(E35*1000000/E34,0) | F36: =IFERROR(F35*1000000/F34,0) | G36: =IFERROR(G35*1000000/G34,0) | H36: =IFERROR(H35*1000000/H34,0) | I36: =IFERROR(I35*1000000/I34,0) | J36: =IFERROR(J35*1000000/J34,0) | K36: =IFERROR(K35*1000000/K34,0) | ... P36: =IFERROR(P35*1000000/P34,0)
A37: 27 | B37: Bukaan lahan | C37: ha | D37: 12 | E37: 12 | F37: 12 | G37: 12 | H37: 12 | I37: 12 | J37: 12 | K37: 12 | P37: =SUM(D37:O37)
A38: 28 | B38: Reklamasi & revegetasi | C38: ha | D38: 5.1 | E38: 7.9 | F38: 4.4 | G38: 5.7 | H38: 6.7 | I38: 6.9 | J38: 6.4 | K38: 6.6 | P38: =SUM(D38:O38)

Sheet C4 GEG LR Budget
A1: GEG – Laba Rugi BUDGET / RKAP Bulanan (Rp juta)
A2: OTOMATIS dari sheet C19 GL Trial Balance (SUMIFS per kode akun MIS) – tidak perlu input di sini. Beban positif; penalti & beban keuangan negatif.
D5: 1 | E5: 2 | F5: 3 | G5: 4 | H5: 5 | I5: 6 | J5: 7 | K5: 8 | L5: 9 | M5: 10 | N5: 11 | O5: 12
A6: Kode akun | B6: Uraian | C6: Catatan | D6: Jan | E6: Feb | F6: Mar | G6: Apr | H6: Mei | I6: Jun | J6: Jul | K6: Agu | L6: Sep | M6: Okt | N6: Nov | O6: Des | P6: FY / YTD
A7: PENDAPATAN
A8: 4101 | B8: Penjualan batubara – Ekspor | D8: =SUMIFS('C19 GEG GL Trial Balance'!$S$10:$S$400,'C19 GEG GL Trial Balance'!$A$10:$A$400,$A8,'C19 GEG GL Trial Balance'!$D$10:$D$400,"Posting") | E8: =SUMIFS('C19 GEG GL Trial Balance'!$T$10:$T$400,'C19 GEG GL Trial Balance'!$A$10:$A$400,$A8,'C19 GEG GL Trial Balance'!$D$10:$D$400,"Posting") | F8: =SUMIFS('C19 GEG GL Trial Balance'!$U$10:$U$400,'C19 GEG GL Trial Balance'!$A$10:$A$400,$A8,'C19 GEG GL Trial Balance'!$D$10:$D$400,"Posting") | G8: =SUMIFS('C19 GEG GL Trial Balance'!$V$10:$V$400,'C19 GEG GL Trial Balance'!$A$10:$A$400,$A8,'C19 GEG GL Trial Balance'!$D$10:$D$400,"Posting") | H8: =SUMIFS('C19 GEG GL Trial Balance'!$W$10:$W$400,'C19 GEG GL Trial Balance'!$A$10:$A$400,$A8,'C19 GEG GL Trial Balance'!$D$10:$D$400,"Posting") | I8: =SUMIFS('C19 GEG GL Trial Balance'!$X$10:$X$400,'C19 GEG GL Trial Balance'!$A$10:$A$400,$A8,'C19 GEG GL Trial Balance'!$D$10:$D$400,"Posting") | J8: =SUMIFS('C19 GEG GL Trial Balance'!$Y$10:$Y$400,'C19 GEG GL Trial Balance'!$A$10:$A$400,$A8,'C19 GEG GL Trial Balance'!$D$10:$D$400,"Posting") | K8: =SUMIFS('C19 GEG GL Trial Balance'!$Z$10:$Z$400,'C19 GEG GL Trial Balance'!$A$10:$A$400,$A8,'C19 GEG GL Trial Balance'!$D$10:$D$400,"Posting") | L8: =SUMIFS('C19 GEG GL Trial Balance'!$AA$10:$AA$400,'C19 GEG GL Trial Balance'!$A$10:$A$400,$A8,'C19 GEG GL Trial Balance'!$D$10:$D$400,"Posting") | M8: =SUMIFS('C19 GEG GL Trial Balance'!$AB$10:$AB$400,'C19 GEG GL Trial Balance'!$A$10:$A$400,$A8,'C19 GEG GL Trial Balance'!$D$10:$D$400,"Posting") | N8: =SUMIFS('C19 GEG GL Trial Balance'!$AC$10:$AC$400,'C19 GEG GL Trial Balance'!$A$10:$A$400,$A8,'C19 GEG GL Trial Balance'!$D$10:$D$400,"Posting") | O8: =SUMIFS('C19 GEG GL Trial Balance'!$AD$10:$AD$400,'C19 GEG GL Trial Balance'!$A$10:$A$400,$A8,'C19 GEG GL Trial Balance'!$D$10:$D$400,"Posting") | P8: =SUM(D8:O8)
A9: 4102 | B9: Penjualan batubara – Domestik DMO | D9: =SUMIFS('C19 GEG GL Trial Balance'!$S$10:$S$400,'C19 GEG GL Trial Balance'!$A$10:$A$400,$A9,'C19 GEG GL Trial Balance'!$D$10:$D$400,"Posting") | E9: =SUMIFS('C19 GEG GL Trial Balance'!$T$10:$T$400,'C19 GEG GL Trial Balance'!$A$10:$A$400,$A9,'C19 GEG GL Trial Balance'!$D$10:$D$400,"Posting") | F9: =SUMIFS('C19 GEG GL Trial Balance'!$U$10:$U$400,'C19 GEG GL Trial Balance'!$A$10:$A$400,$A9,'C19 GEG GL Trial Balance'!$D$10:$D$400,"Posting") | G9: =SUMIFS('C19 GEG GL Trial Balance'!$V$10:$V$400,'C19 GEG GL Trial Balance'!$A$10:$A$400,$A9,'C19 GEG GL Trial Balance'!$D$10:$D$400,"Posting") | H9: =SUMIFS('C19 GEG GL Trial Balance'!$W$10:$W$400,'C19 GEG GL Trial Balance'!$A$10:$A$400,$A9,'C19 GEG GL Trial Balance'!$D$10:$D$400,"Posting") | I9: =SUMIFS('C19 GEG GL Trial Balance'!$X$10:$X$400,'C19 GEG GL Trial Balance'!$A$10:$A$400,$A9,'C19 GEG GL Trial Balance'!$D$10:$D$400,"Posting") | J9: =SUMIFS('C19 GEG GL Trial Balance'!$Y$10:$Y$400,'C19 GEG GL Trial Balance'!$A$10:$A$400,$A9,'C19 GEG GL Trial Balance'!$D$10:$D$400,"Posting") | K9: =SUMIFS('C19 GEG GL Trial Balance'!$Z$10:$Z$400,'C19 GEG GL Trial Balance'!$A$10:$A$400,$A9,'C19 GEG GL Trial Balance'!$D$10:$D$400,"Posting") | L9: =SUMIFS('C19 GEG GL Trial Balance'!$AA$10:$AA$400,'C19 GEG GL Trial Balance'!$A$10:$A$400,$A9,'C19 GEG GL Trial Balance'!$D$10:$D$400,"Posting") | M9: =SUMIFS('C19 GEG GL Trial Balance'!$AB$10:$AB$400,'C19 GEG GL Trial Balance'!$A$10:$A$400,$A9,'C19 GEG GL Trial Balance'!$D$10:$D$400,"Posting") | N9: =SUMIFS('C19 GEG GL Trial Balance'!$AC$10:$AC$400,'C19 GEG GL Trial Balance'!$A$10:$A$400,$A9,'C19 GEG GL Trial Balance'!$D$10:$D$400,"Posting") | O9: =SUMIFS('C19 GEG GL Trial Balance'!$AD$10:$AD$400,'C19 GEG GL Trial Balance'!$A$10:$A$400,$A9,'C19 GEG GL Trial Balance'!$D$10:$D$400,"Posting") | P9: =SUM(D9:O9)
A10: 4103 | B10: Penjualan batubara – Domestik non-DMO | D10: =SUMIFS('C19 GEG GL Trial Balance'!$S$10:$S$400,'C19 GEG GL Trial Balance'!$A$10:$A$400,$A10,'C19 GEG GL Trial Balance'!$D$10:$D$400,"Posting") | E10: =SUMIFS('C19 GEG GL Trial Balance'!$T$10:$T$400,'C19 GEG GL Trial Balance'!$A$10:$A$400,$A10,'C19 GEG GL Trial Balance'!$D$10:$D$400,"Posting") | F10: =SUMIFS('C19 GEG GL Trial Balance'!$U$10:$U$400,'C19 GEG GL Trial Balance'!$A$10:$A$400,$A10,'C19 GEG GL Trial Balance'!$D$10:$D$400,"Posting") | G10: =SUMIFS('C19 GEG GL Trial Balance'!$V$10:$V$400,'C19 GEG GL Trial Balance'!$A$10:$A$400,$A10,'C19 GEG GL Trial Balance'!$D$10:$D$400,"Posting") | H10: =SUMIFS('C19 GEG GL Trial Balance'!$W$10:$W$400,'C19 GEG GL Trial Balance'!$A$10:$A$400,$A10,'C19 GEG GL Trial Balance'!$D$10:$D$400,"Posting") | I10: =SUMIFS('C19 GEG GL Trial Balance'!$X$10:$X$400,'C19 GEG GL Trial Balance'!$A$10:$A$400,$A10,'C19 GEG GL Trial Balance'!$D$10:$D$400,"Posting") | J10: =SUMIFS('C19 GEG GL Trial Balance'!$Y$10:$Y$400,'C19 GEG GL Trial Balance'!$A$10:$A$400,$A10,'C19 GEG GL Trial Balance'!$D$10:$D$400,"Posting") | K10: =SUMIFS('C19 GEG GL Trial Balance'!$Z$10:$Z$400,'C19 GEG GL Trial Balance'!$A$10:$A$400,$A10,'C19 GEG GL Trial Balance'!$D$10:$D$400,"Posting") | L10: =SUMIFS('C19 GEG GL Trial Balance'!$AA$10:$AA$400,'C19 GEG GL Trial Balance'!$A$10:$A$400,$A10,'C19 GEG GL Trial Balance'!$D$10:$D$400,"Posting") | M10: =SUMIFS('C19 GEG GL Trial Balance'!$AB$10:$AB$400,'C19 GEG GL Trial Balance'!$A$10:$A$400,$A10,'C19 GEG GL Trial Balance'!$D$10:$D$400,"Posting") | N10: =SUMIFS('C19 GEG GL Trial Balance'!$AC$10:$AC$400,'C19 GEG GL Trial Balance'!$A$10:$A$400,$A10,'C19 GEG GL Trial Balance'!$D$10:$D$400,"Posting") | O10: =SUMIFS('C19 GEG GL Trial Balance'!$AD$10:$AD$400,'C19 GEG GL Trial Balance'!$A$10:$A$400,$A10,'C19 GEG GL Trial Balance'!$D$10:$D$400,"Posting") | P10: =SUM(D10:O10)
B11: Subtotal penjualan batubara | D11: =D8+D9+D10 | E11: =E8+E9+E10 | F11: =F8+F9+F10 | G11: =G8+G9+G10 | H11: =H8+H9+H10 | I11: =I8+I9+I10 | J11: =J8+J9+J10 | K11: =K8+K9+K10 | ... P11: =P8+P9+P10
A12: 4104 | B12: Penyesuaian harga / penalti kualitas (isi negatif) | D12: =SUMIFS('C19 GEG GL Trial Balance'!$S$10:$S$400,'C19 GEG GL Trial Balance'!$A$10:$A$400,$A12,'C19 GEG GL Trial Balance'!$D$10:$D$400,"Posting") | E12: =SUMIFS('C19 GEG GL Trial Balance'!$T$10:$T$400,'C19 GEG GL Trial Balance'!$A$10:$A$400,$A12,'C19 GEG GL Trial Balance'!$D$10:$D$400,"Posting") | F12: =SUMIFS('C19 GEG GL Trial Balance'!$U$10:$U$400,'C19 GEG GL Trial Balance'!$A$10:$A$400,$A12,'C19 GEG GL Trial Balance'!$D$10:$D$400,"Posting") | G12: =SUMIFS('C19 GEG GL Trial Balance'!$V$10:$V$400,'C19 GEG GL Trial Balance'!$A$10:$A$400,$A12,'C19 GEG GL Trial Balance'!$D$10:$D$400,"Posting") | H12: =SUMIFS('C19 GEG GL Trial Balance'!$W$10:$W$400,'C19 GEG GL Trial Balance'!$A$10:$A$400,$A12,'C19 GEG GL Trial Balance'!$D$10:$D$400,"Posting") | I12: =SUMIFS('C19 GEG GL Trial Balance'!$X$10:$X$400,'C19 GEG GL Trial Balance'!$A$10:$A$400,$A12,'C19 GEG GL Trial Balance'!$D$10:$D$400,"Posting") | J12: =SUMIFS('C19 GEG GL Trial Balance'!$Y$10:$Y$400,'C19 GEG GL Trial Balance'!$A$10:$A$400,$A12,'C19 GEG GL Trial Balance'!$D$10:$D$400,"Posting") | K12: =SUMIFS('C19 GEG GL Trial Balance'!$Z$10:$Z$400,'C19 GEG GL Trial Balance'!$A$10:$A$400,$A12,'C19 GEG GL Trial Balance'!$D$10:$D$400,"Posting") | L12: =SUMIFS('C19 GEG GL Trial Balance'!$AA$10:$AA$400,'C19 GEG GL Trial Balance'!$A$10:$A$400,$A12,'C19 GEG GL Trial Balance'!$D$10:$D$400,"Posting") | M12: =SUMIFS('C19 GEG GL Trial Balance'!$AB$10:$AB$400,'C19 GEG GL Trial Balance'!$A$10:$A$400,$A12,'C19 GEG GL Trial Balance'!$D$10:$D$400,"Posting") | N12: =SUMIFS('C19 GEG GL Trial Balance'!$AC$10:$AC$400,'C19 GEG GL Trial Balance'!$A$10:$A$400,$A12,'C19 GEG GL Trial Balance'!$D$10:$D$400,"Posting") | O12: =SUMIFS('C19 GEG GL Trial Balance'!$AD$10:$AD$400,'C19 GEG GL Trial Balance'!$A$10:$A$400,$A12,'C19 GEG GL Trial Balance'!$D$10:$D$400,"Posting") | P12: =SUM(D12:O12)
A13: 4201 | B13: Pendapatan jasa & usaha lainnya | D13: =SUMIFS('C19 GEG GL Trial Balance'!$S$10:$S$400,'C19 GEG GL Trial Balance'!$A$10:$A$400,$A13,'C19 GEG GL Trial Balance'!$D$10:$D$400,"Posting") | E13: =SUMIFS('C19 GEG GL Trial Balance'!$T$10:$T$400,'C19 GEG GL Trial Balance'!$A$10:$A$400,$A13,'C19 GEG GL Trial Balance'!$D$10:$D$400,"Posting") | F13: =SUMIFS('C19 GEG GL Trial Balance'!$U$10:$U$400,'C19 GEG GL Trial Balance'!$A$10:$A$400,$A13,'C19 GEG GL Trial Balance'!$D$10:$D$400,"Posting") | G13: =SUMIFS('C19 GEG GL Trial Balance'!$V$10:$V$400,'C19 GEG GL Trial Balance'!$A$10:$A$400,$A13,'C19 GEG GL Trial Balance'!$D$10:$D$400,"Posting") | H13: =SUMIFS('C19 GEG GL Trial Balance'!$W$10:$W$400,'C19 GEG GL Trial Balance'!$A$10:$A$400,$A13,'C19 GEG GL Trial Balance'!$D$10:$D$400,"Posting") | I13: =SUMIFS('C19 GEG GL Trial Balance'!$X$10:$X$400,'C19 GEG GL Trial Balance'!$A$10:$A$400,$A13,'C19 GEG GL Trial Balance'!$D$10:$D$400,"Posting") | J13: =SUMIFS('C19 GEG GL Trial Balance'!$Y$10:$Y$400,'C19 GEG GL Trial Balance'!$A$10:$A$400,$A13,'C19 GEG GL Trial Balance'!$D$10:$D$400,"Posting") | K13: =SUMIFS('C19 GEG GL Trial Balance'!$Z$10:$Z$400,'C19 GEG GL Trial Balance'!$A$10:$A$400,$A13,'C19 GEG GL Trial Balance'!$D$10:$D$400,"Posting") | L13: =SUMIFS('C19 GEG GL Trial Balance'!$AA$10:$AA$400,'C19 GEG GL Trial Balance'!$A$10:$A$400,$A13,'C19 GEG GL Trial Balance'!$D$10:$D$400,"Posting") | M13: =SUMIFS('C19 GEG GL Trial Balance'!$AB$10:$AB$400,'C19 GEG GL Trial Balance'!$A$10:$A$400,$A13,'C19 GEG GL Trial Balance'!$D$10:$D$400,"Posting") | N13: =SUMIFS('C19 GEG GL Trial Balance'!$AC$10:$AC$400,'C19 GEG GL Trial Balance'!$A$10:$A$400,$A13,'C19 GEG GL Trial Balance'!$D$10:$D$400,"Posting") | O13: =SUMIFS('C19 GEG GL Trial Balance'!$AD$10:$AD$400,'C19 GEG GL Trial Balance'!$A$10:$A$400,$A13,'C19 GEG GL Trial Balance'!$D$10:$D$400,"Posting") | P13: =SUM(D13:O13)
B14: PENDAPATAN BERSIH | D14: =D11+D12+D13 | E14: =E11+E12+E13 | F14: =F11+F12+F13 | G14: =G11+G12+G13 | H14: =H11+H12+H13 | I14: =I11+I12+I13 | J14: =J11+J12+J13 | K14: =K11+K12+K13 | ... P14: =P11+P12+P13
A15: BEBAN POKOK PENDAPATAN
B16: A. Biaya penambangan
A17: 5101 | B17: Jasa kontraktor OB removal | D17: =SUMIFS('C19 GEG GL Trial Balance'!$S$10:$S$400,'C19 GEG GL Trial Balance'!$A$10:$A$400,$A17,'C19 GEG GL Trial Balance'!$D$10:$D$400,"Posting") | E17: =SUMIFS('C19 GEG GL Trial Balance'!$T$10:$T$400,'C19 GEG GL Trial Balance'!$A$10:$A$400,$A17,'C19 GEG GL Trial Balance'!$D$10:$D$400,"Posting") | F17: =SUMIFS('C19 GEG GL Trial Balance'!$U$10:$U$400,'C19 GEG GL Trial Balance'!$A$10:$A$400,$A17,'C19 GEG GL Trial Balance'!$D$10:$D$400,"Posting") | G17: =SUMIFS('C19 GEG GL Trial Balance'!$V$10:$V$400,'C19 GEG GL Trial Balance'!$A$10:$A$400,$A17,'C19 GEG GL Trial Balance'!$D$10:$D$400,"Posting") | H17: =SUMIFS('C19 GEG GL Trial Balance'!$W$10:$W$400,'C19 GEG GL Trial Balance'!$A$10:$A$400,$A17,'C19 GEG GL Trial Balance'!$D$10:$D$400,"Posting") | I17: =SUMIFS('C19 GEG GL Trial Balance'!$X$10:$X$400,'C19 GEG GL Trial Balance'!$A$10:$A$400,$A17,'C19 GEG GL Trial Balance'!$D$10:$D$400,"Posting") | J17: =SUMIFS('C19 GEG GL Trial Balance'!$Y$10:$Y$400,'C19 GEG GL Trial Balance'!$A$10:$A$400,$A17,'C19 GEG GL Trial Balance'!$D$10:$D$400,"Posting") | K17: =SUMIFS('C19 GEG GL Trial Balance'!$Z$10:$Z$400,'C19 GEG GL Trial Balance'!$A$10:$A$400,$A17,'C19 GEG GL Trial Balance'!$D$10:$D$400,"Posting") | L17: =SUMIFS('C19 GEG GL Trial Balance'!$AA$10:$AA$400,'C19 GEG GL Trial Balance'!$A$10:$A$400,$A17,'C19 GEG GL Trial Balance'!$D$10:$D$400,"Posting") | M17: =SUMIFS('C19 GEG GL Trial Balance'!$AB$10:$AB$400,'C19 GEG GL Trial Balance'!$A$10:$A$400,$A17,'C19 GEG GL Trial Balance'!$D$10:$D$400,"Posting") | N17: =SUMIFS('C19 GEG GL Trial Balance'!$AC$10:$AC$400,'C19 GEG GL Trial Balance'!$A$10:$A$400,$A17,'C19 GEG GL Trial Balance'!$D$10:$D$400,"Posting") | O17: =SUMIFS('C19 GEG GL Trial Balance'!$AD$10:$AD$400,'C19 GEG GL Trial Balance'!$A$10:$A$400,$A17,'C19 GEG GL Trial Balance'!$D$10:$D$400,"Posting") | P17: =SUM(D17:O17)
A18: 5102 | B18: Bahan bakar (BBM) | D18: =SUMIFS('C19 GEG GL Trial Balance'!$S$10:$S$400,'C19 GEG GL Trial Balance'!$A$10:$A$400,$A18,'C19 GEG GL Trial Balance'!$D$10:$D$400,"Posting") | E18: =SUMIFS('C19 GEG GL Trial Balance'!$T$10:$T$400,'C19 GEG GL Trial Balance'!$A$10:$A$400,$A18,'C19 GEG GL Trial Balance'!$D$10:$D$400,"Posting") | F18: =SUMIFS('C19 GEG GL Trial Balance'!$U$10:$U$400,'C19 GEG GL Trial Balance'!$A$10:$A$400,$A18,'C19 GEG GL Trial Balance'!$D$10:$D$400,"Posting") | G18: =SUMIFS('C19 GEG GL Trial Balance'!$V$10:$V$400,'C19 GEG GL Trial Balance'!$A$10:$A$400,$A18,'C19 GEG GL Trial Balance'!$D$10:$D$400,"Posting") | H18: =SUMIFS('C19 GEG GL Trial Balance'!$W$10:$W$400,'C19 GEG GL Trial Balance'!$A$10:$A$400,$A18,'C19 GEG GL Trial Balance'!$D$10:$D$400,"Posting") | I18: =SUMIFS('C19 GEG GL Trial Balance'!$X$10:$X$400,'C19 GEG GL Trial Balance'!$A$10:$A$400,$A18,'C19 GEG GL Trial Balance'!$D$10:$D$400,"Posting") | J18: =SUMIFS('C19 GEG GL Trial Balance'!$Y$10:$Y$400,'C19 GEG GL Trial Balance'!$A$10:$A$400,$A18,'C19 GEG GL Trial Balance'!$D$10:$D$400,"Posting") | K18: =SUMIFS('C19 GEG GL Trial Balance'!$Z$10:$Z$400,'C19 GEG GL Trial Balance'!$A$10:$A$400,$A18,'C19 GEG GL Trial Balance'!$D$10:$D$400,"Posting") | L18: =SUMIFS('C19 GEG GL Trial Balance'!$AA$10:$AA$400,'C19 GEG GL Trial Balance'!$A$10:$A$400,$A18,'C19 GEG GL Trial Balance'!$D$10:$D$400,"Posting") | M18: =SUMIFS('C19 GEG GL Trial Balance'!$AB$10:$AB$400,'C19 GEG GL Trial Balance'!$A$10:$A$400,$A18,'C19 GEG GL Trial Balance'!$D$10:$D$400,"Posting") | N18: =SUMIFS('C19 GEG GL Trial Balance'!$AC$10:$AC$400,'C19 GEG GL Trial Balance'!$A$10:$A$400,$A18,'C19 GEG GL Trial Balance'!$D$10:$D$400,"Posting") | O18: =SUMIFS('C19 GEG GL Trial Balance'!$AD$10:$AD$400,'C19 GEG GL Trial Balance'!$A$10:$A$400,$A18,'C19 GEG GL Trial Balance'!$D$10:$D$400,"Posting") | P18: =SUM(D18:O18)
A19: 5103 | B19: Peledakan (drill & blast) | D19: =SUMIFS('C19 GEG GL Trial Balance'!$S$10:$S$400,'C19 GEG GL Trial Balance'!$A$10:$A$400,$A19,'C19 GEG GL Trial Balance'!$D$10:$D$400,"Posting") | E19: =SUMIFS('C19 GEG GL Trial Balance'!$T$10:$T$400,'C19 GEG GL Trial Balance'!$A$10:$A$400,$A19,'C19 GEG GL Trial Balance'!$D$10:$D$400,"Posting") | F19: =SUMIFS('C19 GEG GL Trial Balance'!$U$10:$U$400,'C19 GEG GL Trial Balance'!$A$10:$A$400,$A19,'C19 GEG GL Trial Balance'!$D$10:$D$400,"Posting") | G19: =SUMIFS('C19 GEG GL Trial Balance'!$V$10:$V$400,'C19 GEG GL Trial Balance'!$A$10:$A$400,$A19,'C19 GEG GL Trial Balance'!$D$10:$D$400,"Posting") | H19: =SUMIFS('C19 GEG GL Trial Balance'!$W$10:$W$400,'C19 GEG GL Trial Balance'!$A$10:$A$400,$A19,'C19 GEG GL Trial Balance'!$D$10:$D$400,"Posting") | I19: =SUMIFS('C19 GEG GL Trial Balance'!$X$10:$X$400,'C19 GEG GL Trial Balance'!$A$10:$A$400,$A19,'C19 GEG GL Trial Balance'!$D$10:$D$400,"Posting") | J19: =SUMIFS('C19 GEG GL Trial Balance'!$Y$10:$Y$400,'C19 GEG GL Trial Balance'!$A$10:$A$400,$A19,'C19 GEG GL Trial Balance'!$D$10:$D$400,"Posting") | K19: =SUMIFS('C19 GEG GL Trial Balance'!$Z$10:$Z$400,'C19 GEG GL Trial Balance'!$A$10:$A$400,$A19,'C19 GEG GL Trial Balance'!$D$10:$D$400,"Posting") | L19: =SUMIFS('C19 GEG GL Trial Balance'!$AA$10:$AA$400,'C19 GEG GL Trial Balance'!$A$10:$A$400,$A19,'C19 GEG GL Trial Balance'!$D$10:$D$400,"Posting") | M19: =SUMIFS('C19 GEG GL Trial Balance'!$AB$10:$AB$400,'C19 GEG GL Trial Balance'!$A$10:$A$400,$A19,'C19 GEG GL Trial Balance'!$D$10:$D$400,"Posting") | N19: =SUMIFS('C19 GEG GL Trial Balance'!$AC$10:$AC$400,'C19 GEG GL Trial Balance'!$A$10:$A$400,$A19,'C19 GEG GL Trial Balance'!$D$10:$D$400,"Posting") | O19: =SUMIFS('C19 GEG GL Trial Balance'!$AD$10:$AD$400,'C19 GEG GL Trial Balance'!$A$10:$A$400,$A19,'C19 GEG GL Trial Balance'!$D$10:$D$400,"Posting") | P19: =SUM(D19:O19)
A20: 5104 | B20: Penggalian batubara (coal getting) | D20: =SUMIFS('C19 GEG GL Trial Balance'!$S$10:$S$400,'C19 GEG GL Trial Balance'!$A$10:$A$400,$A20,'C19 GEG GL Trial Balance'!$D$10:$D$400,"Posting") | E20: =SUMIFS('C19 GEG GL Trial Balance'!$T$10:$T$400,'C19 GEG GL Trial Balance'!$A$10:$A$400,$A20,'C19 GEG GL Trial Balance'!$D$10:$D$400,"Posting") | F20: =SUMIFS('C19 GEG GL Trial Balance'!$U$10:$U$400,'C19 GEG GL Trial Balance'!$A$10:$A$400,$A20,'C19 GEG GL Trial Balance'!$D$10:$D$400,"Posting") | G20: =SUMIFS('C19 GEG GL Trial Balance'!$V$10:$V$400,'C19 GEG GL Trial Balance'!$A$10:$A$400,$A20,'C19 GEG GL Trial Balance'!$D$10:$D$400,"Posting") | H20: =SUMIFS('C19 GEG GL Trial Balance'!$W$10:$W$400,'C19 GEG GL Trial Balance'!$A$10:$A$400,$A20,'C19 GEG GL Trial Balance'!$D$10:$D$400,"Posting") | I20: =SUMIFS('C19 GEG GL Trial Balance'!$X$10:$X$400,'C19 GEG GL Trial Balance'!$A$10:$A$400,$A20,'C19 GEG GL Trial Balance'!$D$10:$D$400,"Posting") | J20: =SUMIFS('C19 GEG GL Trial Balance'!$Y$10:$Y$400,'C19 GEG GL Trial Balance'!$A$10:$A$400,$A20,'C19 GEG GL Trial Balance'!$D$10:$D$400,"Posting") | K20: =SUMIFS('C19 GEG GL Trial Balance'!$Z$10:$Z$400,'C19 GEG GL Trial Balance'!$A$10:$A$400,$A20,'C19 GEG GL Trial Balance'!$D$10:$D$400,"Posting") | L20: =SUMIFS('C19 GEG GL Trial Balance'!$AA$10:$AA$400,'C19 GEG GL Trial Balance'!$A$10:$A$400,$A20,'C19 GEG GL Trial Balance'!$D$10:$D$400,"Posting") | M20: =SUMIFS('C19 GEG GL Trial Balance'!$AB$10:$AB$400,'C19 GEG GL Trial Balance'!$A$10:$A$400,$A20,'C19 GEG GL Trial Balance'!$D$10:$D$400,"Posting") | N20: =SUMIFS('C19 GEG GL Trial Balance'!$AC$10:$AC$400,'C19 GEG GL Trial Balance'!$A$10:$A$400,$A20,'C19 GEG GL Trial Balance'!$D$10:$D$400,"Posting") | O20: =SUMIFS('C19 GEG GL Trial Balance'!$AD$10:$AD$400,'C19 GEG GL Trial Balance'!$A$10:$A$400,$A20,'C19 GEG GL Trial Balance'!$D$10:$D$400,"Posting") | P20: =SUM(D20:O20)
A21: 5105 | B21: Sewa alat berat & sarana penunjang | D21: =SUMIFS('C19 GEG GL Trial Balance'!$S$10:$S$400,'C19 GEG GL Trial Balance'!$A$10:$A$400,$A21,'C19 GEG GL Trial Balance'!$D$10:$D$400,"Posting") | E21: =SUMIFS('C19 GEG GL Trial Balance'!$T$10:$T$400,'C19 GEG GL Trial Balance'!$A$10:$A$400,$A21,'C19 GEG GL Trial Balance'!$D$10:$D$400,"Posting") | F21: =SUMIFS('C19 GEG GL Trial Balance'!$U$10:$U$400,'C19 GEG GL Trial Balance'!$A$10:$A$400,$A21,'C19 GEG GL Trial Balance'!$D$10:$D$400,"Posting") | G21: =SUMIFS('C19 GEG GL Trial Balance'!$V$10:$V$400,'C19 GEG GL Trial Balance'!$A$10:$A$400,$A21,'C19 GEG GL Trial Balance'!$D$10:$D$400,"Posting") | H21: =SUMIFS('C19 GEG GL Trial Balance'!$W$10:$W$400,'C19 GEG GL Trial Balance'!$A$10:$A$400,$A21,'C19 GEG GL Trial Balance'!$D$10:$D$400,"Posting") | I21: =SUMIFS('C19 GEG GL Trial Balance'!$X$10:$X$400,'C19 GEG GL Trial Balance'!$A$10:$A$400,$A21,'C19 GEG GL Trial Balance'!$D$10:$D$400,"Posting") | J21: =SUMIFS('C19 GEG GL Trial Balance'!$Y$10:$Y$400,'C19 GEG GL Trial Balance'!$A$10:$A$400,$A21,'C19 GEG GL Trial Balance'!$D$10:$D$400,"Posting") | K21: =SUMIFS('C19 GEG GL Trial Balance'!$Z$10:$Z$400,'C19 GEG GL Trial Balance'!$A$10:$A$400,$A21,'C19 GEG GL Trial Balance'!$D$10:$D$400,"Posting") | L21: =SUMIFS('C19 GEG GL Trial Balance'!$AA$10:$AA$400,'C19 GEG GL Trial Balance'!$A$10:$A$400,$A21,'C19 GEG GL Trial Balance'!$D$10:$D$400,"Posting") | M21: =SUMIFS('C19 GEG GL Trial Balance'!$AB$10:$AB$400,'C19 GEG GL Trial Balance'!$A$10:$A$400,$A21,'C19 GEG GL Trial Balance'!$D$10:$D$400,"Posting") | N21: =SUMIFS('C19 GEG GL Trial Balance'!$AC$10:$AC$400,'C19 GEG GL Trial Balance'!$A$10:$A$400,$A21,'C19 GEG GL Trial Balance'!$D$10:$D$400,"Posting") | O21: =SUMIFS('C19 GEG GL Trial Balance'!$AD$10:$AD$400,'C19 GEG GL Trial Balance'!$A$10:$A$400,$A21,'C19 GEG GL Trial Balance'!$D$10:$D$400,"Posting") | P21: =SUM(D21:O21)
A22: 5106 | B22: Pemeliharaan jalan tambang & infrastruktur | D22: =SUMIFS('C19 GEG GL Trial Balance'!$S$10:$S$400,'C19 GEG GL Trial Balance'!$A$10:$A$400,$A22,'C19 GEG GL Trial Balance'!$D$10:$D$400,"Posting") | E22: =SUMIFS('C19 GEG GL Trial Balance'!$T$10:$T$400,'C19 GEG GL Trial Balance'!$A$10:$A$400,$A22,'C19 GEG GL Trial Balance'!$D$10:$D$400,"Posting") | F22: =SUMIFS('C19 GEG GL Trial Balance'!$U$10:$U$400,'C19 GEG GL Trial Balance'!$A$10:$A$400,$A22,'C19 GEG GL Trial Balance'!$D$10:$D$400,"Posting") | G22: =SUMIFS('C19 GEG GL Trial Balance'!$V$10:$V$400,'C19 GEG GL Trial Balance'!$A$10:$A$400,$A22,'C19 GEG GL Trial Balance'!$D$10:$D$400,"Posting") | H22: =SUMIFS('C19 GEG GL Trial Balance'!$W$10:$W$400,'C19 GEG GL Trial Balance'!$A$10:$A$400,$A22,'C19 GEG GL Trial Balance'!$D$10:$D$400,"Posting") | I22: =SUMIFS('C19 GEG GL Trial Balance'!$X$10:$X$400,'C19 GEG GL Trial Balance'!$A$10:$A$400,$A22,'C19 GEG GL Trial Balance'!$D$10:$D$400,"Posting") | J22: =SUMIFS('C19 GEG GL Trial Balance'!$Y$10:$Y$400,'C19 GEG GL Trial Balance'!$A$10:$A$400,$A22,'C19 GEG GL Trial Balance'!$D$10:$D$400,"Posting") | K22: =SUMIFS('C19 GEG GL Trial Balance'!$Z$10:$Z$400,'C19 GEG GL Trial Balance'!$A$10:$A$400,$A22,'C19 GEG GL Trial Balance'!$D$10:$D$400,"Posting") | L22: =SUMIFS('C19 GEG GL Trial Balance'!$AA$10:$AA$400,'C19 GEG GL Trial Balance'!$A$10:$A$400,$A22,'C19 GEG GL Trial Balance'!$D$10:$D$400,"Posting") | M22: =SUMIFS('C19 GEG GL Trial Balance'!$AB$10:$AB$400,'C19 GEG GL Trial Balance'!$A$10:$A$400,$A22,'C19 GEG GL Trial Balance'!$D$10:$D$400,"Posting") | N22: =SUMIFS('C19 GEG GL Trial Balance'!$AC$10:$AC$400,'C19 GEG GL Trial Balance'!$A$10:$A$400,$A22,'C19 GEG GL Trial Balance'!$D$10:$D$400,"Posting") | O22: =SUMIFS('C19 GEG GL Trial Balance'!$AD$10:$AD$400,'C19 GEG GL Trial Balance'!$A$10:$A$400,$A22,'C19 GEG GL Trial Balance'!$D$10:$D$400,"Posting") | P22: =SUM(D22:O22)
A23: 5107 | B23: Pengelolaan air tambang (dewatering) | D23: =SUMIFS('C19 GEG GL Trial Balance'!$S$10:$S$400,'C19 GEG GL Trial Balance'!$A$10:$A$400,$A23,'C19 GEG GL Trial Balance'!$D$10:$D$400,"Posting") | E23: =SUMIFS('C19 GEG GL Trial Balance'!$T$10:$T$400,'C19 GEG GL Trial Balance'!$A$10:$A$400,$A23,'C19 GEG GL Trial Balance'!$D$10:$D$400,"Posting") | F23: =SUMIFS('C19 GEG GL Trial Balance'!$U$10:$U$400,'C19 GEG GL Trial Balance'!$A$10:$A$400,$A23,'C19 GEG GL Trial Balance'!$D$10:$D$400,"Posting") | G23: =SUMIFS('C19 GEG GL Trial Balance'!$V$10:$V$400,'C19 GEG GL Trial Balance'!$A$10:$A$400,$A23,'C19 GEG GL Trial Balance'!$D$10:$D$400,"Posting") | H23: =SUMIFS('C19 GEG GL Trial Balance'!$W$10:$W$400,'C19 GEG GL Trial Balance'!$A$10:$A$400,$A23,'C19 GEG GL Trial Balance'!$D$10:$D$400,"Posting") | I23: =SUMIFS('C19 GEG GL Trial Balance'!$X$10:$X$400,'C19 GEG GL Trial Balance'!$A$10:$A$400,$A23,'C19 GEG GL Trial Balance'!$D$10:$D$400,"Posting") | J23: =SUMIFS('C19 GEG GL Trial Balance'!$Y$10:$Y$400,'C19 GEG GL Trial Balance'!$A$10:$A$400,$A23,'C19 GEG GL Trial Balance'!$D$10:$D$400,"Posting") | K23: =SUMIFS('C19 GEG GL Trial Balance'!$Z$10:$Z$400,'C19 GEG GL Trial Balance'!$A$10:$A$400,$A23,'C19 GEG GL Trial Balance'!$D$10:$D$400,"Posting") | L23: =SUMIFS('C19 GEG GL Trial Balance'!$AA$10:$AA$400,'C19 GEG GL Trial Balance'!$A$10:$A$400,$A23,'C19 GEG GL Trial Balance'!$D$10:$D$400,"Posting") | M23: =SUMIFS('C19 GEG GL Trial Balance'!$AB$10:$AB$400,'C19 GEG GL Trial Balance'!$A$10:$A$400,$A23,'C19 GEG GL Trial Balance'!$D$10:$D$400,"Posting") | N23: =SUMIFS('C19 GEG GL Trial Balance'!$AC$10:$AC$400,'C19 GEG GL Trial Balance'!$A$10:$A$400,$A23,'C19 GEG GL Trial Balance'!$D$10:$D$400,"Posting") | O23: =SUMIFS('C19 GEG GL Trial Balance'!$AD$10:$AD$400,'C19 GEG GL Trial Balance'!$A$10:$A$400,$A23,'C19 GEG GL Trial Balance'!$D$10:$D$400,"Posting") | P23: =SUM(D23:O23)
A24: 5108 | B24: Survei, geologi & grade control | D24: =SUMIFS('C19 GEG GL Trial Balance'!$S$10:$S$400,'C19 GEG GL Trial Balance'!$A$10:$A$400,$A24,'C19 GEG GL Trial Balance'!$D$10:$D$400,"Posting") | E24: =SUMIFS('C19 GEG GL Trial Balance'!$T$10:$T$400,'C19 GEG GL Trial Balance'!$A$10:$A$400,$A24,'C19 GEG GL Trial Balance'!$D$10:$D$400,"Posting") | F24: =SUMIFS('C19 GEG GL Trial Balance'!$U$10:$U$400,'C19 GEG GL Trial Balance'!$A$10:$A$400,$A24,'C19 GEG GL Trial Balance'!$D$10:$D$400,"Posting") | G24: =SUMIFS('C19 GEG GL Trial Balance'!$V$10:$V$400,'C19 GEG GL Trial Balance'!$A$10:$A$400,$A24,'C19 GEG GL Trial Balance'!$D$10:$D$400,"Posting") | H24: =SUMIFS('C19 GEG GL Trial Balance'!$W$10:$W$400,'C19 GEG GL Trial Balance'!$A$10:$A$400,$A24,'C19 GEG GL Trial Balance'!$D$10:$D$400,"Posting") | I24: =SUMIFS('C19 GEG GL Trial Balance'!$X$10:$X$400,'C19 GEG GL Trial Balance'!$A$10:$A$400,$A24,'C19 GEG GL Trial Balance'!$D$10:$D$400,"Posting") | J24: =SUMIFS('C19 GEG GL Trial Balance'!$Y$10:$Y$400,'C19 GEG GL Trial Balance'!$A$10:$A$400,$A24,'C19 GEG GL Trial Balance'!$D$10:$D$400,"Posting") | K24: =SUMIFS('C19 GEG GL Trial Balance'!$Z$10:$Z$400,'C19 GEG GL Trial Balance'!$A$10:$A$400,$A24,'C19 GEG GL Trial Balance'!$D$10:$D$400,"Posting") | L24: =SUMIFS('C19 GEG GL Trial Balance'!$AA$10:$AA$400,'C19 GEG GL Trial Balance'!$A$10:$A$400,$A24,'C19 GEG GL Trial Balance'!$D$10:$D$400,"Posting") | M24: =SUMIFS('C19 GEG GL Trial Balance'!$AB$10:$AB$400,'C19 GEG GL Trial Balance'!$A$10:$A$400,$A24,'C19 GEG GL Trial Balance'!$D$10:$D$400,"Posting") | N24: =SUMIFS('C19 GEG GL Trial Balance'!$AC$10:$AC$400,'C19 GEG GL Trial Balance'!$A$10:$A$400,$A24,'C19 GEG GL Trial Balance'!$D$10:$D$400,"Posting") | O24: =SUMIFS('C19 GEG GL Trial Balance'!$AD$10:$AD$400,'C19 GEG GL Trial Balance'!$A$10:$A$400,$A24,'C19 GEG GL Trial Balance'!$D$10:$D$400,"Posting") | P24: =SUM(D24:O24)
B25: Subtotal biaya penambangan | D25: =D17+D18+D19+D20+D21+D22+D23+D24 | E25: =E17+E18+E19+E20+E21+E22+E23+E24 | F25: =F17+F18+F19+F20+F21+F22+F23+F24 | G25: =G17+G18+G19+G20+G21+G22+G23+G24 | H25: =H17+H18+H19+H20+H21+H22+H23+H24 | I25: =I17+I18+I19+I20+I21+I22+I23+I24 | J25: =J17+J18+J19+J20+J21+J22+J23+J24 | K25: =K17+K18+K19+K20+K21+K22+K23+K24 | ... P25: =P17+P18+P19+P20+P21+P22+P23+P24
B26: B. Pengolahan & logistik
A27: 5201 | B27: Crushing & pengolahan (CPP) | D27: =SUMIFS('C19 GEG GL Trial Balance'!$S$10:$S$400,'C19 GEG GL Trial Balance'!$A$10:$A$400,$A27,'C19 GEG GL Trial Balance'!$D$10:$D$400,"Posting") | E27: =SUMIFS('C19 GEG GL Trial Balance'!$T$10:$T$400,'C19 GEG GL Trial Balance'!$A$10:$A$400,$A27,'C19 GEG GL Trial Balance'!$D$10:$D$400,"Posting") | F27: =SUMIFS('C19 GEG GL Trial Balance'!$U$10:$U$400,'C19 GEG GL Trial Balance'!$A$10:$A$400,$A27,'C19 GEG GL Trial Balance'!$D$10:$D$400,"Posting") | G27: =SUMIFS('C19 GEG GL Trial Balance'!$V$10:$V$400,'C19 GEG GL Trial Balance'!$A$10:$A$400,$A27,'C19 GEG GL Trial Balance'!$D$10:$D$400,"Posting") | H27: =SUMIFS('C19 GEG GL Trial Balance'!$W$10:$W$400,'C19 GEG GL Trial Balance'!$A$10:$A$400,$A27,'C19 GEG GL Trial Balance'!$D$10:$D$400,"Posting") | I27: =SUMIFS('C19 GEG GL Trial Balance'!$X$10:$X$400,'C19 GEG GL Trial Balance'!$A$10:$A$400,$A27,'C19 GEG GL Trial Balance'!$D$10:$D$400,"Posting") | J27: =SUMIFS('C19 GEG GL Trial Balance'!$Y$10:$Y$400,'C19 GEG GL Trial Balance'!$A$10:$A$400,$A27,'C19 GEG GL Trial Balance'!$D$10:$D$400,"Posting") | K27: =SUMIFS('C19 GEG GL Trial Balance'!$Z$10:$Z$400,'C19 GEG GL Trial Balance'!$A$10:$A$400,$A27,'C19 GEG GL Trial Balance'!$D$10:$D$400,"Posting") | L27: =SUMIFS('C19 GEG GL Trial Balance'!$AA$10:$AA$400,'C19 GEG GL Trial Balance'!$A$10:$A$400,$A27,'C19 GEG GL Trial Balance'!$D$10:$D$400,"Posting") | M27: =SUMIFS('C19 GEG GL Trial Balance'!$AB$10:$AB$400,'C19 GEG GL Trial Balance'!$A$10:$A$400,$A27,'C19 GEG GL Trial Balance'!$D$10:$D$400,"Posting") | N27: =SUMIFS('C19 GEG GL Trial Balance'!$AC$10:$AC$400,'C19 GEG GL Trial Balance'!$A$10:$A$400,$A27,'C19 GEG GL Trial Balance'!$D$10:$D$400,"Posting") | O27: =SUMIFS('C19 GEG GL Trial Balance'!$AD$10:$AD$400,'C19 GEG GL Trial Balance'!$A$10:$A$400,$A27,'C19 GEG GL Trial Balance'!$D$10:$D$400,"Posting") | P27: =SUM(D27:O27)
A28: 5202 | B28: Hauling tambang – pelabuhan | D28: =SUMIFS('C19 GEG GL Trial Balance'!$S$10:$S$400,'C19 GEG GL Trial Balance'!$A$10:$A$400,$A28,'C19 GEG GL Trial Balance'!$D$10:$D$400,"Posting") | E28: =SUMIFS('C19 GEG GL Trial Balance'!$T$10:$T$400,'C19 GEG GL Trial Balance'!$A$10:$A$400,$A28,'C19 GEG GL Trial Balance'!$D$10:$D$400,"Posting") | F28: =SUMIFS('C19 GEG GL Trial Balance'!$U$10:$U$400,'C19 GEG GL Trial Balance'!$A$10:$A$400,$A28,'C19 GEG GL Trial Balance'!$D$10:$D$400,"Posting") | G28: =SUMIFS('C19 GEG GL Trial Balance'!$V$10:$V$400,'C19 GEG GL Trial Balance'!$A$10:$A$400,$A28,'C19 GEG GL Trial Balance'!$D$10:$D$400,"Posting") | H28: =SUMIFS('C19 GEG GL Trial Balance'!$W$10:$W$400,'C19 GEG GL Trial Balance'!$A$10:$A$400,$A28,'C19 GEG GL Trial Balance'!$D$10:$D$400,"Posting") | I28: =SUMIFS('C19 GEG GL Trial Balance'!$X$10:$X$400,'C19 GEG GL Trial Balance'!$A$10:$A$400,$A28,'C19 GEG GL Trial Balance'!$D$10:$D$400,"Posting") | J28: =SUMIFS('C19 GEG GL Trial Balance'!$Y$10:$Y$400,'C19 GEG GL Trial Balance'!$A$10:$A$400,$A28,'C19 GEG GL Trial Balance'!$D$10:$D$400,"Posting") | K28: =SUMIFS('C19 GEG GL Trial Balance'!$Z$10:$Z$400,'C19 GEG GL Trial Balance'!$A$10:$A$400,$A28,'C19 GEG GL Trial Balance'!$D$10:$D$400,"Posting") | L28: =SUMIFS('C19 GEG GL Trial Balance'!$AA$10:$AA$400,'C19 GEG GL Trial Balance'!$A$10:$A$400,$A28,'C19 GEG GL Trial Balance'!$D$10:$D$400,"Posting") | M28: =SUMIFS('C19 GEG GL Trial Balance'!$AB$10:$AB$400,'C19 GEG GL Trial Balance'!$A$10:$A$400,$A28,'C19 GEG GL Trial Balance'!$D$10:$D$400,"Posting") | N28: =SUMIFS('C19 GEG GL Trial Balance'!$AC$10:$AC$400,'C19 GEG GL Trial Balance'!$A$10:$A$400,$A28,'C19 GEG GL Trial Balance'!$D$10:$D$400,"Posting") | O28: =SUMIFS('C19 GEG GL Trial Balance'!$AD$10:$AD$400,'C19 GEG GL Trial Balance'!$A$10:$A$400,$A28,'C19 GEG GL Trial Balance'!$D$10:$D$400,"Posting") | P28: =SUM(D28:O28)
A29: 5203 | B29: Penanganan pelabuhan & stockpile | D29: =SUMIFS('C19 GEG GL Trial Balance'!$S$10:$S$400,'C19 GEG GL Trial Balance'!$A$10:$A$400,$A29,'C19 GEG GL Trial Balance'!$D$10:$D$400,"Posting") | E29: =SUMIFS('C19 GEG GL Trial Balance'!$T$10:$T$400,'C19 GEG GL Trial Balance'!$A$10:$A$400,$A29,'C19 GEG GL Trial Balance'!$D$10:$D$400,"Posting") | F29: =SUMIFS('C19 GEG GL Trial Balance'!$U$10:$U$400,'C19 GEG GL Trial Balance'!$A$10:$A$400,$A29,'C19 GEG GL Trial Balance'!$D$10:$D$400,"Posting") | G29: =SUMIFS('C19 GEG GL Trial Balance'!$V$10:$V$400,'C19 GEG GL Trial Balance'!$A$10:$A$400,$A29,'C19 GEG GL Trial Balance'!$D$10:$D$400,"Posting") | H29: =SUMIFS('C19 GEG GL Trial Balance'!$W$10:$W$400,'C19 GEG GL Trial Balance'!$A$10:$A$400,$A29,'C19 GEG GL Trial Balance'!$D$10:$D$400,"Posting") | I29: =SUMIFS('C19 GEG GL Trial Balance'!$X$10:$X$400,'C19 GEG GL Trial Balance'!$A$10:$A$400,$A29,'C19 GEG GL Trial Balance'!$D$10:$D$400,"Posting") | J29: =SUMIFS('C19 GEG GL Trial Balance'!$Y$10:$Y$400,'C19 GEG GL Trial Balance'!$A$10:$A$400,$A29,'C19 GEG GL Trial Balance'!$D$10:$D$400,"Posting") | K29: =SUMIFS('C19 GEG GL Trial Balance'!$Z$10:$Z$400,'C19 GEG GL Trial Balance'!$A$10:$A$400,$A29,'C19 GEG GL Trial Balance'!$D$10:$D$400,"Posting") | L29: =SUMIFS('C19 GEG GL Trial Balance'!$AA$10:$AA$400,'C19 GEG GL Trial Balance'!$A$10:$A$400,$A29,'C19 GEG GL Trial Balance'!$D$10:$D$400,"Posting") | M29: =SUMIFS('C19 GEG GL Trial Balance'!$AB$10:$AB$400,'C19 GEG GL Trial Balance'!$A$10:$A$400,$A29,'C19 GEG GL Trial Balance'!$D$10:$D$400,"Posting") | N29: =SUMIFS('C19 GEG GL Trial Balance'!$AC$10:$AC$400,'C19 GEG GL Trial Balance'!$A$10:$A$400,$A29,'C19 GEG GL Trial Balance'!$D$10:$D$400,"Posting") | O29: =SUMIFS('C19 GEG GL Trial Balance'!$AD$10:$AD$400,'C19 GEG GL Trial Balance'!$A$10:$A$400,$A29,'C19 GEG GL Trial Balance'!$D$10:$D$400,"Posting") | P29: =SUM(D29:O29)
A30: 5204 | B30: Tongkang & transshipment (barging) | D30: =SUMIFS('C19 GEG GL Trial Balance'!$S$10:$S$400,'C19 GEG GL Trial Balance'!$A$10:$A$400,$A30,'C19 GEG GL Trial Balance'!$D$10:$D$400,"Posting") | E30: =SUMIFS('C19 GEG GL Trial Balance'!$T$10:$T$400,'C19 GEG GL Trial Balance'!$A$10:$A$400,$A30,'C19 GEG GL Trial Balance'!$D$10:$D$400,"Posting") | F30: =SUMIFS('C19 GEG GL Trial Balance'!$U$10:$U$400,'C19 GEG GL Trial Balance'!$A$10:$A$400,$A30,'C19 GEG GL Trial Balance'!$D$10:$D$400,"Posting") | G30: =SUMIFS('C19 GEG GL Trial Balance'!$V$10:$V$400,'C19 GEG GL Trial Balance'!$A$10:$A$400,$A30,'C19 GEG GL Trial Balance'!$D$10:$D$400,"Posting") | H30: =SUMIFS('C19 GEG GL Trial Balance'!$W$10:$W$400,'C19 GEG GL Trial Balance'!$A$10:$A$400,$A30,'C19 GEG GL Trial Balance'!$D$10:$D$400,"Posting") | I30: =SUMIFS('C19 GEG GL Trial Balance'!$X$10:$X$400,'C19 GEG GL Trial Balance'!$A$10:$A$400,$A30,'C19 GEG GL Trial Balance'!$D$10:$D$400,"Posting") | J30: =SUMIFS('C19 GEG GL Trial Balance'!$Y$10:$Y$400,'C19 GEG GL Trial Balance'!$A$10:$A$400,$A30,'C19 GEG GL Trial Balance'!$D$10:$D$400,"Posting") | K30: =SUMIFS('C19 GEG GL Trial Balance'!$Z$10:$Z$400,'C19 GEG GL Trial Balance'!$A$10:$A$400,$A30,'C19 GEG GL Trial Balance'!$D$10:$D$400,"Posting") | L30: =SUMIFS('C19 GEG GL Trial Balance'!$AA$10:$AA$400,'C19 GEG GL Trial Balance'!$A$10:$A$400,$A30,'C19 GEG GL Trial Balance'!$D$10:$D$400,"Posting") | M30: =SUMIFS('C19 GEG GL Trial Balance'!$AB$10:$AB$400,'C19 GEG GL Trial Balance'!$A$10:$A$400,$A30,'C19 GEG GL Trial Balance'!$D$10:$D$400,"Posting") | N30: =SUMIFS('C19 GEG GL Trial Balance'!$AC$10:$AC$400,'C19 GEG GL Trial Balance'!$A$10:$A$400,$A30,'C19 GEG GL Trial Balance'!$D$10:$D$400,"Posting") | O30: =SUMIFS('C19 GEG GL Trial Balance'!$AD$10:$AD$400,'C19 GEG GL Trial Balance'!$A$10:$A$400,$A30,'C19 GEG GL Trial Balance'!$D$10:$D$400,"Posting") | P30: =SUM(D30:O30)
B31: Subtotal pengolahan & logistik | D31: =D27+D28+D29+D30 | E31: =E27+E28+E29+E30 | F31: =F27+F28+F29+F30 | G31: =G27+G28+G29+G30 | H31: =H27+H28+H29+H30 | I31: =I27+I28+I29+I30 | J31: =J27+J28+J29+J30 | K31: =K27+K28+K29+K30 | ... P31: =P27+P28+P29+P30
B32: C. Royalti
A33: 5301 | B33: Royalti / PNBP (DHPB) | D33: =SUMIFS('C19 GEG GL Trial Balance'!$S$10:$S$400,'C19 GEG GL Trial Balance'!$A$10:$A$400,$A33,'C19 GEG GL Trial Balance'!$D$10:$D$400,"Posting") | E33: =SUMIFS('C19 GEG GL Trial Balance'!$T$10:$T$400,'C19 GEG GL Trial Balance'!$A$10:$A$400,$A33,'C19 GEG GL Trial Balance'!$D$10:$D$400,"Posting") | F33: =SUMIFS('C19 GEG GL Trial Balance'!$U$10:$U$400,'C19 GEG GL Trial Balance'!$A$10:$A$400,$A33,'C19 GEG GL Trial Balance'!$D$10:$D$400,"Posting") | G33: =SUMIFS('C19 GEG GL Trial Balance'!$V$10:$V$400,'C19 GEG GL Trial Balance'!$A$10:$A$400,$A33,'C19 GEG GL Trial Balance'!$D$10:$D$400,"Posting") | H33: =SUMIFS('C19 GEG GL Trial Balance'!$W$10:$W$400,'C19 GEG GL Trial Balance'!$A$10:$A$400,$A33,'C19 GEG GL Trial Balance'!$D$10:$D$400,"Posting") | I33: =SUMIFS('C19 GEG GL Trial Balance'!$X$10:$X$400,'C19 GEG GL Trial Balance'!$A$10:$A$400,$A33,'C19 GEG GL Trial Balance'!$D$10:$D$400,"Posting") | J33: =SUMIFS('C19 GEG GL Trial Balance'!$Y$10:$Y$400,'C19 GEG GL Trial Balance'!$A$10:$A$400,$A33,'C19 GEG GL Trial Balance'!$D$10:$D$400,"Posting") | K33: =SUMIFS('C19 GEG GL Trial Balance'!$Z$10:$Z$400,'C19 GEG GL Trial Balance'!$A$10:$A$400,$A33,'C19 GEG GL Trial Balance'!$D$10:$D$400,"Posting") | L33: =SUMIFS('C19 GEG GL Trial Balance'!$AA$10:$AA$400,'C19 GEG GL Trial Balance'!$A$10:$A$400,$A33,'C19 GEG GL Trial Balance'!$D$10:$D$400,"Posting") | M33: =SUMIFS('C19 GEG GL Trial Balance'!$AB$10:$AB$400,'C19 GEG GL Trial Balance'!$A$10:$A$400,$A33,'C19 GEG GL Trial Balance'!$D$10:$D$400,"Posting") | N33: =SUMIFS('C19 GEG GL Trial Balance'!$AC$10:$AC$400,'C19 GEG GL Trial Balance'!$A$10:$A$400,$A33,'C19 GEG GL Trial Balance'!$D$10:$D$400,"Posting") | O33: =SUMIFS('C19 GEG GL Trial Balance'!$AD$10:$AD$400,'C19 GEG GL Trial Balance'!$A$10:$A$400,$A33,'C19 GEG GL Trial Balance'!$D$10:$D$400,"Posting") | P33: =SUM(D33:O33)
B34: D. Overhead site
A35: 5401 | B35: Gaji & tunjangan karyawan site | D35: =SUMIFS('C19 GEG GL Trial Balance'!$S$10:$S$400,'C19 GEG GL Trial Balance'!$A$10:$A$400,$A35,'C19 GEG GL Trial Balance'!$D$10:$D$400,"Posting") | E35: =SUMIFS('C19 GEG GL Trial Balance'!$T$10:$T$400,'C19 GEG GL Trial Balance'!$A$10:$A$400,$A35,'C19 GEG GL Trial Balance'!$D$10:$D$400,"Posting") | F35: =SUMIFS('C19 GEG GL Trial Balance'!$U$10:$U$400,'C19 GEG GL Trial Balance'!$A$10:$A$400,$A35,'C19 GEG GL Trial Balance'!$D$10:$D$400,"Posting") | G35: =SUMIFS('C19 GEG GL Trial Balance'!$V$10:$V$400,'C19 GEG GL Trial Balance'!$A$10:$A$400,$A35,'C19 GEG GL Trial Balance'!$D$10:$D$400,"Posting") | H35: =SUMIFS('C19 GEG GL Trial Balance'!$W$10:$W$400,'C19 GEG GL Trial Balance'!$A$10:$A$400,$A35,'C19 GEG GL Trial Balance'!$D$10:$D$400,"Posting") | I35: =SUMIFS('C19 GEG GL Trial Balance'!$X$10:$X$400,'C19 GEG GL Trial Balance'!$A$10:$A$400,$A35,'C19 GEG GL Trial Balance'!$D$10:$D$400,"Posting") | J35: =SUMIFS('C19 GEG GL Trial Balance'!$Y$10:$Y$400,'C19 GEG GL Trial Balance'!$A$10:$A$400,$A35,'C19 GEG GL Trial Balance'!$D$10:$D$400,"Posting") | K35: =SUMIFS('C19 GEG GL Trial Balance'!$Z$10:$Z$400,'C19 GEG GL Trial Balance'!$A$10:$A$400,$A35,'C19 GEG GL Trial Balance'!$D$10:$D$400,"Posting") | L35: =SUMIFS('C19 GEG GL Trial Balance'!$AA$10:$AA$400,'C19 GEG GL Trial Balance'!$A$10:$A$400,$A35,'C19 GEG GL Trial Balance'!$D$10:$D$400,"Posting") | M35: =SUMIFS('C19 GEG GL Trial Balance'!$AB$10:$AB$400,'C19 GEG GL Trial Balance'!$A$10:$A$400,$A35,'C19 GEG GL Trial Balance'!$D$10:$D$400,"Posting") | N35: =SUMIFS('C19 GEG GL Trial Balance'!$AC$10:$AC$400,'C19 GEG GL Trial Balance'!$A$10:$A$400,$A35,'C19 GEG GL Trial Balance'!$D$10:$D$400,"Posting") | O35: =SUMIFS('C19 GEG GL Trial Balance'!$AD$10:$AD$400,'C19 GEG GL Trial Balance'!$A$10:$A$400,$A35,'C19 GEG GL Trial Balance'!$D$10:$D$400,"Posting") | P35: =SUM(D35:O35)
A36: 5402 | B36: Camp, mess & katering | D36: =SUMIFS('C19 GEG GL Trial Balance'!$S$10:$S$400,'C19 GEG GL Trial Balance'!$A$10:$A$400,$A36,'C19 GEG GL Trial Balance'!$D$10:$D$400,"Posting") | E36: =SUMIFS('C19 GEG GL Trial Balance'!$T$10:$T$400,'C19 GEG GL Trial Balance'!$A$10:$A$400,$A36,'C19 GEG GL Trial Balance'!$D$10:$D$400,"Posting") | F36: =SUMIFS('C19 GEG GL Trial Balance'!$U$10:$U$400,'C19 GEG GL Trial Balance'!$A$10:$A$400,$A36,'C19 GEG GL Trial Balance'!$D$10:$D$400,"Posting") | G36: =SUMIFS('C19 GEG GL Trial Balance'!$V$10:$V$400,'C19 GEG GL Trial Balance'!$A$10:$A$400,$A36,'C19 GEG GL Trial Balance'!$D$10:$D$400,"Posting") | H36: =SUMIFS('C19 GEG GL Trial Balance'!$W$10:$W$400,'C19 GEG GL Trial Balance'!$A$10:$A$400,$A36,'C19 GEG GL Trial Balance'!$D$10:$D$400,"Posting") | I36: =SUMIFS('C19 GEG GL Trial Balance'!$X$10:$X$400,'C19 GEG GL Trial Balance'!$A$10:$A$400,$A36,'C19 GEG GL Trial Balance'!$D$10:$D$400,"Posting") | J36: =SUMIFS('C19 GEG GL Trial Balance'!$Y$10:$Y$400,'C19 GEG GL Trial Balance'!$A$10:$A$400,$A36,'C19 GEG GL Trial Balance'!$D$10:$D$400,"Posting") | K36: =SUMIFS('C19 GEG GL Trial Balance'!$Z$10:$Z$400,'C19 GEG GL Trial Balance'!$A$10:$A$400,$A36,'C19 GEG GL Trial Balance'!$D$10:$D$400,"Posting") | L36: =SUMIFS('C19 GEG GL Trial Balance'!$AA$10:$AA$400,'C19 GEG GL Trial Balance'!$A$10:$A$400,$A36,'C19 GEG GL Trial Balance'!$D$10:$D$400,"Posting") | M36: =SUMIFS('C19 GEG GL Trial Balance'!$AB$10:$AB$400,'C19 GEG GL Trial Balance'!$A$10:$A$400,$A36,'C19 GEG GL Trial Balance'!$D$10:$D$400,"Posting") | N36: =SUMIFS('C19 GEG GL Trial Balance'!$AC$10:$AC$400,'C19 GEG GL Trial Balance'!$A$10:$A$400,$A36,'C19 GEG GL Trial Balance'!$D$10:$D$400,"Posting") | O36: =SUMIFS('C19 GEG GL Trial Balance'!$AD$10:$AD$400,'C19 GEG GL Trial Balance'!$A$10:$A$400,$A36,'C19 GEG GL Trial Balance'!$D$10:$D$400,"Posting") | P36: =SUM(D36:O36)
A37: 5403 | B37: K3 / HSE | D37: =SUMIFS('C19 GEG GL Trial Balance'!$S$10:$S$400,'C19 GEG GL Trial Balance'!$A$10:$A$400,$A37,'C19 GEG GL Trial Balance'!$D$10:$D$400,"Posting") | E37: =SUMIFS('C19 GEG GL Trial Balance'!$T$10:$T$400,'C19 GEG GL Trial Balance'!$A$10:$A$400,$A37,'C19 GEG GL Trial Balance'!$D$10:$D$400,"Posting") | F37: =SUMIFS('C19 GEG GL Trial Balance'!$U$10:$U$400,'C19 GEG GL Trial Balance'!$A$10:$A$400,$A37,'C19 GEG GL Trial Balance'!$D$10:$D$400,"Posting") | G37: =SUMIFS('C19 GEG GL Trial Balance'!$V$10:$V$400,'C19 GEG GL Trial Balance'!$A$10:$A$400,$A37,'C19 GEG GL Trial Balance'!$D$10:$D$400,"Posting") | H37: =SUMIFS('C19 GEG GL Trial Balance'!$W$10:$W$400,'C19 GEG GL Trial Balance'!$A$10:$A$400,$A37,'C19 GEG GL Trial Balance'!$D$10:$D$400,"Posting") | I37: =SUMIFS('C19 GEG GL Trial Balance'!$X$10:$X$400,'C19 GEG GL Trial Balance'!$A$10:$A$400,$A37,'C19 GEG GL Trial Balance'!$D$10:$D$400,"Posting") | J37: =SUMIFS('C19 GEG GL Trial Balance'!$Y$10:$Y$400,'C19 GEG GL Trial Balance'!$A$10:$A$400,$A37,'C19 GEG GL Trial Balance'!$D$10:$D$400,"Posting") | K37: =SUMIFS('C19 GEG GL Trial Balance'!$Z$10:$Z$400,'C19 GEG GL Trial Balance'!$A$10:$A$400,$A37,'C19 GEG GL Trial Balance'!$D$10:$D$400,"Posting") | L37: =SUMIFS('C19 GEG GL Trial Balance'!$AA$10:$AA$400,'C19 GEG GL Trial Balance'!$A$10:$A$400,$A37,'C19 GEG GL Trial Balance'!$D$10:$D$400,"Posting") | M37: =SUMIFS('C19 GEG GL Trial Balance'!$AB$10:$AB$400,'C19 GEG GL Trial Balance'!$A$10:$A$400,$A37,'C19 GEG GL Trial Balance'!$D$10:$D$400,"Posting") | N37: =SUMIFS('C19 GEG GL Trial Balance'!$AC$10:$AC$400,'C19 GEG GL Trial Balance'!$A$10:$A$400,$A37,'C19 GEG GL Trial Balance'!$D$10:$D$400,"Posting") | O37: =SUMIFS('C19 GEG GL Trial Balance'!$AD$10:$AD$400,'C19 GEG GL Trial Balance'!$A$10:$A$400,$A37,'C19 GEG GL Trial Balance'!$D$10:$D$400,"Posting") | P37: =SUM(D37:O37)
A38: 5404 | B38: Lingkungan & reklamasi (provisi) | D38: =SUMIFS('C19 GEG GL Trial Balance'!$S$10:$S$400,'C19 GEG GL Trial Balance'!$A$10:$A$400,$A38,'C19 GEG GL Trial Balance'!$D$10:$D$400,"Posting") | E38: =SUMIFS('C19 GEG GL Trial Balance'!$T$10:$T$400,'C19 GEG GL Trial Balance'!$A$10:$A$400,$A38,'C19 GEG GL Trial Balance'!$D$10:$D$400,"Posting") | F38: =SUMIFS('C19 GEG GL Trial Balance'!$U$10:$U$400,'C19 GEG GL Trial Balance'!$A$10:$A$400,$A38,'C19 GEG GL Trial Balance'!$D$10:$D$400,"Posting") | G38: =SUMIFS('C19 GEG GL Trial Balance'!$V$10:$V$400,'C19 GEG GL Trial Balance'!$A$10:$A$400,$A38,'C19 GEG GL Trial Balance'!$D$10:$D$400,"Posting") | H38: =SUMIFS('C19 GEG GL Trial Balance'!$W$10:$W$400,'C19 GEG GL Trial Balance'!$A$10:$A$400,$A38,'C19 GEG GL Trial Balance'!$D$10:$D$400,"Posting") | I38: =SUMIFS('C19 GEG GL Trial Balance'!$X$10:$X$400,'C19 GEG GL Trial Balance'!$A$10:$A$400,$A38,'C19 GEG GL Trial Balance'!$D$10:$D$400,"Posting") | J38: =SUMIFS('C19 GEG GL Trial Balance'!$Y$10:$Y$400,'C19 GEG GL Trial Balance'!$A$10:$A$400,$A38,'C19 GEG GL Trial Balance'!$D$10:$D$400,"Posting") | K38: =SUMIFS('C19 GEG GL Trial Balance'!$Z$10:$Z$400,'C19 GEG GL Trial Balance'!$A$10:$A$400,$A38,'C19 GEG GL Trial Balance'!$D$10:$D$400,"Posting") | L38: =SUMIFS('C19 GEG GL Trial Balance'!$AA$10:$AA$400,'C19 GEG GL Trial Balance'!$A$10:$A$400,$A38,'C19 GEG GL Trial Balance'!$D$10:$D$400,"Posting") | M38: =SUMIFS('C19 GEG GL Trial Balance'!$AB$10:$AB$400,'C19 GEG GL Trial Balance'!$A$10:$A$400,$A38,'C19 GEG GL Trial Balance'!$D$10:$D$400,"Posting") | N38: =SUMIFS('C19 GEG GL Trial Balance'!$AC$10:$AC$400,'C19 GEG GL Trial Balance'!$A$10:$A$400,$A38,'C19 GEG GL Trial Balance'!$D$10:$D$400,"Posting") | O38: =SUMIFS('C19 GEG GL Trial Balance'!$AD$10:$AD$400,'C19 GEG GL Trial Balance'!$A$10:$A$400,$A38,'C19 GEG GL Trial Balance'!$D$10:$D$400,"Posting") | P38: =SUM(D38:O38)
A39: 5405 | B39: PPM / CSR | D39: =SUMIFS('C19 GEG GL Trial Balance'!$S$10:$S$400,'C19 GEG GL Trial Balance'!$A$10:$A$400,$A39,'C19 GEG GL Trial Balance'!$D$10:$D$400,"Posting") | E39: =SUMIFS('C19 GEG GL Trial Balance'!$T$10:$T$400,'C19 GEG GL Trial Balance'!$A$10:$A$400,$A39,'C19 GEG GL Trial Balance'!$D$10:$D$400,"Posting") | F39: =SUMIFS('C19 GEG GL Trial Balance'!$U$10:$U$400,'C19 GEG GL Trial Balance'!$A$10:$A$400,$A39,'C19 GEG GL Trial Balance'!$D$10:$D$400,"Posting") | G39: =SUMIFS('C19 GEG GL Trial Balance'!$V$10:$V$400,'C19 GEG GL Trial Balance'!$A$10:$A$400,$A39,'C19 GEG GL Trial Balance'!$D$10:$D$400,"Posting") | H39: =SUMIFS('C19 GEG GL Trial Balance'!$W$10:$W$400,'C19 GEG GL Trial Balance'!$A$10:$A$400,$A39,'C19 GEG GL Trial Balance'!$D$10:$D$400,"Posting") | I39: =SUMIFS('C19 GEG GL Trial Balance'!$X$10:$X$400,'C19 GEG GL Trial Balance'!$A$10:$A$400,$A39,'C19 GEG GL Trial Balance'!$D$10:$D$400,"Posting") | J39: =SUMIFS('C19 GEG GL Trial Balance'!$Y$10:$Y$400,'C19 GEG GL Trial Balance'!$A$10:$A$400,$A39,'C19 GEG GL Trial Balance'!$D$10:$D$400,"Posting") | K39: =SUMIFS('C19 GEG GL Trial Balance'!$Z$10:$Z$400,'C19 GEG GL Trial Balance'!$A$10:$A$400,$A39,'C19 GEG GL Trial Balance'!$D$10:$D$400,"Posting") | L39: =SUMIFS('C19 GEG GL Trial Balance'!$AA$10:$AA$400,'C19 GEG GL Trial Balance'!$A$10:$A$400,$A39,'C19 GEG GL Trial Balance'!$D$10:$D$400,"Posting") | M39: =SUMIFS('C19 GEG GL Trial Balance'!$AB$10:$AB$400,'C19 GEG GL Trial Balance'!$A$10:$A$400,$A39,'C19 GEG GL Trial Balance'!$D$10:$D$400,"Posting") | N39: =SUMIFS('C19 GEG GL Trial Balance'!$AC$10:$AC$400,'C19 GEG GL Trial Balance'!$A$10:$A$400,$A39,'C19 GEG GL Trial Balance'!$D$10:$D$400,"Posting") | O39: =SUMIFS('C19 GEG GL Trial Balance'!$AD$10:$AD$400,'C19 GEG GL Trial Balance'!$A$10:$A$400,$A39,'C19 GEG GL Trial Balance'!$D$10:$D$400,"Posting") | P39: =SUM(D39:O39)
A40: 5406 | B40: Iuran tetap & kompensasi lahan | D40: =SUMIFS('C19 GEG GL Trial Balance'!$S$10:$S$400,'C19 GEG GL Trial Balance'!$A$10:$A$400,$A40,'C19 GEG GL Trial Balance'!$D$10:$D$400,"Posting") | E40: =SUMIFS('C19 GEG GL Trial Balance'!$T$10:$T$400,'C19 GEG GL Trial Balance'!$A$10:$A$400,$A40,'C19 GEG GL Trial Balance'!$D$10:$D$400,"Posting") | F40: =SUMIFS('C19 GEG GL Trial Balance'!$U$10:$U$400,'C19 GEG GL Trial Balance'!$A$10:$A$400,$A40,'C19 GEG GL Trial Balance'!$D$10:$D$400,"Posting") | G40: =SUMIFS('C19 GEG GL Trial Balance'!$V$10:$V$400,'C19 GEG GL Trial Balance'!$A$10:$A$400,$A40,'C19 GEG GL Trial Balance'!$D$10:$D$400,"Posting") | H40: =SUMIFS('C19 GEG GL Trial Balance'!$W$10:$W$400,'C19 GEG GL Trial Balance'!$A$10:$A$400,$A40,'C19 GEG GL Trial Balance'!$D$10:$D$400,"Posting") | I40: =SUMIFS('C19 GEG GL Trial Balance'!$X$10:$X$400,'C19 GEG GL Trial Balance'!$A$10:$A$400,$A40,'C19 GEG GL Trial Balance'!$D$10:$D$400,"Posting") | J40: =SUMIFS('C19 GEG GL Trial Balance'!$Y$10:$Y$400,'C19 GEG GL Trial Balance'!$A$10:$A$400,$A40,'C19 GEG GL Trial Balance'!$D$10:$D$400,"Posting") | K40: =SUMIFS('C19 GEG GL Trial Balance'!$Z$10:$Z$400,'C19 GEG GL Trial Balance'!$A$10:$A$400,$A40,'C19 GEG GL Trial Balance'!$D$10:$D$400,"Posting") | L40: =SUMIFS('C19 GEG GL Trial Balance'!$AA$10:$AA$400,'C19 GEG GL Trial Balance'!$A$10:$A$400,$A40,'C19 GEG GL Trial Balance'!$D$10:$D$400,"Posting") | M40: =SUMIFS('C19 GEG GL Trial Balance'!$AB$10:$AB$400,'C19 GEG GL Trial Balance'!$A$10:$A$400,$A40,'C19 GEG GL Trial Balance'!$D$10:$D$400,"Posting") | N40: =SUMIFS('C19 GEG GL Trial Balance'!$AC$10:$AC$400,'C19 GEG GL Trial Balance'!$A$10:$A$400,$A40,'C19 GEG GL Trial Balance'!$D$10:$D$400,"Posting") | O40: =SUMIFS('C19 GEG GL Trial Balance'!$AD$10:$AD$400,'C19 GEG GL Trial Balance'!$A$10:$A$400,$A40,'C19 GEG GL Trial Balance'!$D$10:$D$400,"Posting") | P40: =SUM(D40:O40)
B41: Subtotal overhead site | D41: =D35+D36+D37+D38+D39+D40 | E41: =E35+E36+E37+E38+E39+E40 | F41: =F35+F36+F37+F38+F39+F40 | G41: =G35+G36+G37+G38+G39+G40 | H41: =H35+H36+H37+H38+H39+H40 | I41: =I35+I36+I37+I38+I39+I40 | J41: =J35+J36+J37+J38+J39+J40 | K41: =K35+K36+K37+K38+K39+K40 | ... P41: =P35+P36+P37+P38+P39+P40
B42: E. Penyusutan & amortisasi
A43: 5501 | B43: Penyusutan aset tetap | D43: =SUMIFS('C19 GEG GL Trial Balance'!$S$10:$S$400,'C19 GEG GL Trial Balance'!$A$10:$A$400,$A43,'C19 GEG GL Trial Balance'!$D$10:$D$400,"Posting") | E43: =SUMIFS('C19 GEG GL Trial Balance'!$T$10:$T$400,'C19 GEG GL Trial Balance'!$A$10:$A$400,$A43,'C19 GEG GL Trial Balance'!$D$10:$D$400,"Posting") | F43: =SUMIFS('C19 GEG GL Trial Balance'!$U$10:$U$400,'C19 GEG GL Trial Balance'!$A$10:$A$400,$A43,'C19 GEG GL Trial Balance'!$D$10:$D$400,"Posting") | G43: =SUMIFS('C19 GEG GL Trial Balance'!$V$10:$V$400,'C19 GEG GL Trial Balance'!$A$10:$A$400,$A43,'C19 GEG GL Trial Balance'!$D$10:$D$400,"Posting") | H43: =SUMIFS('C19 GEG GL Trial Balance'!$W$10:$W$400,'C19 GEG GL Trial Balance'!$A$10:$A$400,$A43,'C19 GEG GL Trial Balance'!$D$10:$D$400,"Posting") | I43: =SUMIFS('C19 GEG GL Trial Balance'!$X$10:$X$400,'C19 GEG GL Trial Balance'!$A$10:$A$400,$A43,'C19 GEG GL Trial Balance'!$D$10:$D$400,"Posting") | J43: =SUMIFS('C19 GEG GL Trial Balance'!$Y$10:$Y$400,'C19 GEG GL Trial Balance'!$A$10:$A$400,$A43,'C19 GEG GL Trial Balance'!$D$10:$D$400,"Posting") | K43: =SUMIFS('C19 GEG GL Trial Balance'!$Z$10:$Z$400,'C19 GEG GL Trial Balance'!$A$10:$A$400,$A43,'C19 GEG GL Trial Balance'!$D$10:$D$400,"Posting") | L43: =SUMIFS('C19 GEG GL Trial Balance'!$AA$10:$AA$400,'C19 GEG GL Trial Balance'!$A$10:$A$400,$A43,'C19 GEG GL Trial Balance'!$D$10:$D$400,"Posting") | M43: =SUMIFS('C19 GEG GL Trial Balance'!$AB$10:$AB$400,'C19 GEG GL Trial Balance'!$A$10:$A$400,$A43,'C19 GEG GL Trial Balance'!$D$10:$D$400,"Posting") | N43: =SUMIFS('C19 GEG GL Trial Balance'!$AC$10:$AC$400,'C19 GEG GL Trial Balance'!$A$10:$A$400,$A43,'C19 GEG GL Trial Balance'!$D$10:$D$400,"Posting") | O43: =SUMIFS('C19 GEG GL Trial Balance'!$AD$10:$AD$400,'C19 GEG GL Trial Balance'!$A$10:$A$400,$A43,'C19 GEG GL Trial Balance'!$D$10:$D$400,"Posting") | P43: =SUM(D43:O43)
A44: 5502 | B44: Amortisasi properti pertambangan | D44: =SUMIFS('C19 GEG GL Trial Balance'!$S$10:$S$400,'C19 GEG GL Trial Balance'!$A$10:$A$400,$A44,'C19 GEG GL Trial Balance'!$D$10:$D$400,"Posting") | E44: =SUMIFS('C19 GEG GL Trial Balance'!$T$10:$T$400,'C19 GEG GL Trial Balance'!$A$10:$A$400,$A44,'C19 GEG GL Trial Balance'!$D$10:$D$400,"Posting") | F44: =SUMIFS('C19 GEG GL Trial Balance'!$U$10:$U$400,'C19 GEG GL Trial Balance'!$A$10:$A$400,$A44,'C19 GEG GL Trial Balance'!$D$10:$D$400,"Posting") | G44: =SUMIFS('C19 GEG GL Trial Balance'!$V$10:$V$400,'C19 GEG GL Trial Balance'!$A$10:$A$400,$A44,'C19 GEG GL Trial Balance'!$D$10:$D$400,"Posting") | H44: =SUMIFS('C19 GEG GL Trial Balance'!$W$10:$W$400,'C19 GEG GL Trial Balance'!$A$10:$A$400,$A44,'C19 GEG GL Trial Balance'!$D$10:$D$400,"Posting") | I44: =SUMIFS('C19 GEG GL Trial Balance'!$X$10:$X$400,'C19 GEG GL Trial Balance'!$A$10:$A$400,$A44,'C19 GEG GL Trial Balance'!$D$10:$D$400,"Posting") | J44: =SUMIFS('C19 GEG GL Trial Balance'!$Y$10:$Y$400,'C19 GEG GL Trial Balance'!$A$10:$A$400,$A44,'C19 GEG GL Trial Balance'!$D$10:$D$400,"Posting") | K44: =SUMIFS('C19 GEG GL Trial Balance'!$Z$10:$Z$400,'C19 GEG GL Trial Balance'!$A$10:$A$400,$A44,'C19 GEG GL Trial Balance'!$D$10:$D$400,"Posting") | L44: =SUMIFS('C19 GEG GL Trial Balance'!$AA$10:$AA$400,'C19 GEG GL Trial Balance'!$A$10:$A$400,$A44,'C19 GEG GL Trial Balance'!$D$10:$D$400,"Posting") | M44: =SUMIFS('C19 GEG GL Trial Balance'!$AB$10:$AB$400,'C19 GEG GL Trial Balance'!$A$10:$A$400,$A44,'C19 GEG GL Trial Balance'!$D$10:$D$400,"Posting") | N44: =SUMIFS('C19 GEG GL Trial Balance'!$AC$10:$AC$400,'C19 GEG GL Trial Balance'!$A$10:$A$400,$A44,'C19 GEG GL Trial Balance'!$D$10:$D$400,"Posting") | O44: =SUMIFS('C19 GEG GL Trial Balance'!$AD$10:$AD$400,'C19 GEG GL Trial Balance'!$A$10:$A$400,$A44,'C19 GEG GL Trial Balance'!$D$10:$D$400,"Posting") | P44: =SUM(D44:O44)
A45: 5503 | B45: Amortisasi biaya pengupasan tangguhan | D45: =SUMIFS('C19 GEG GL Trial Balance'!$S$10:$S$400,'C19 GEG GL Trial Balance'!$A$10:$A$400,$A45,'C19 GEG GL Trial Balance'!$D$10:$D$400,"Posting") | E45: =SUMIFS('C19 GEG GL Trial Balance'!$T$10:$T$400,'C19 GEG GL Trial Balance'!$A$10:$A$400,$A45,'C19 GEG GL Trial Balance'!$D$10:$D$400,"Posting") | F45: =SUMIFS('C19 GEG GL Trial Balance'!$U$10:$U$400,'C19 GEG GL Trial Balance'!$A$10:$A$400,$A45,'C19 GEG GL Trial Balance'!$D$10:$D$400,"Posting") | G45: =SUMIFS('C19 GEG GL Trial Balance'!$V$10:$V$400,'C19 GEG GL Trial Balance'!$A$10:$A$400,$A45,'C19 GEG GL Trial Balance'!$D$10:$D$400,"Posting") | H45: =SUMIFS('C19 GEG GL Trial Balance'!$W$10:$W$400,'C19 GEG GL Trial Balance'!$A$10:$A$400,$A45,'C19 GEG GL Trial Balance'!$D$10:$D$400,"Posting") | I45: =SUMIFS('C19 GEG GL Trial Balance'!$X$10:$X$400,'C19 GEG GL Trial Balance'!$A$10:$A$400,$A45,'C19 GEG GL Trial Balance'!$D$10:$D$400,"Posting") | J45: =SUMIFS('C19 GEG GL Trial Balance'!$Y$10:$Y$400,'C19 GEG GL Trial Balance'!$A$10:$A$400,$A45,'C19 GEG GL Trial Balance'!$D$10:$D$400,"Posting") | K45: =SUMIFS('C19 GEG GL Trial Balance'!$Z$10:$Z$400,'C19 GEG GL Trial Balance'!$A$10:$A$400,$A45,'C19 GEG GL Trial Balance'!$D$10:$D$400,"Posting") | L45: =SUMIFS('C19 GEG GL Trial Balance'!$AA$10:$AA$400,'C19 GEG GL Trial Balance'!$A$10:$A$400,$A45,'C19 GEG GL Trial Balance'!$D$10:$D$400,"Posting") | M45: =SUMIFS('C19 GEG GL Trial Balance'!$AB$10:$AB$400,'C19 GEG GL Trial Balance'!$A$10:$A$400,$A45,'C19 GEG GL Trial Balance'!$D$10:$D$400,"Posting") | N45: =SUMIFS('C19 GEG GL Trial Balance'!$AC$10:$AC$400,'C19 GEG GL Trial Balance'!$A$10:$A$400,$A45,'C19 GEG GL Trial Balance'!$D$10:$D$400,"Posting") | O45: =SUMIFS('C19 GEG GL Trial Balance'!$AD$10:$AD$400,'C19 GEG GL Trial Balance'!$A$10:$A$400,$A45,'C19 GEG GL Trial Balance'!$D$10:$D$400,"Posting") | P45: =SUM(D45:O45)
B46: Subtotal penyusutan & amortisasi | D46: =D43+D44+D45 | E46: =E43+E44+E45 | F46: =F43+F44+F45 | G46: =G43+G44+G45 | H46: =H43+H44+H45 | I46: =I43+I44+I45 | J46: =J43+J44+J45 | K46: =K43+K44+K45 | ... P46: =P43+P44+P45
B47: Total biaya produksi | D47: =D25+D31+D33+D41+D46 | E47: =E25+E31+E33+E41+E46 | F47: =F25+F31+F33+F41+F46 | G47: =G25+G31+G33+G41+G46 | H47: =H25+H31+H33+H41+H46 | I47: =I25+I31+I33+I41+I46 | J47: =J25+J31+J33+J41+J46 | K47: =K25+K31+K33+K41+K46 | ... P47: =P25+P31+P33+P41+P46
A48: 5601 | B48: Perubahan persediaan batubara (awal – akhir) | D48: =SUMIFS('C19 GEG GL Trial Balance'!$S$10:$S$400,'C19 GEG GL Trial Balance'!$A$10:$A$400,$A48,'C19 GEG GL Trial Balance'!$D$10:$D$400,"Posting") | E48: =SUMIFS('C19 GEG GL Trial Balance'!$T$10:$T$400,'C19 GEG GL Trial Balance'!$A$10:$A$400,$A48,'C19 GEG GL Trial Balance'!$D$10:$D$400,"Posting") | F48: =SUMIFS('C19 GEG GL Trial Balance'!$U$10:$U$400,'C19 GEG GL Trial Balance'!$A$10:$A$400,$A48,'C19 GEG GL Trial Balance'!$D$10:$D$400,"Posting") | G48: =SUMIFS('C19 GEG GL Trial Balance'!$V$10:$V$400,'C19 GEG GL Trial Balance'!$A$10:$A$400,$A48,'C19 GEG GL Trial Balance'!$D$10:$D$400,"Posting") | H48: =SUMIFS('C19 GEG GL Trial Balance'!$W$10:$W$400,'C19 GEG GL Trial Balance'!$A$10:$A$400,$A48,'C19 GEG GL Trial Balance'!$D$10:$D$400,"Posting") | I48: =SUMIFS('C19 GEG GL Trial Balance'!$X$10:$X$400,'C19 GEG GL Trial Balance'!$A$10:$A$400,$A48,'C19 GEG GL Trial Balance'!$D$10:$D$400,"Posting") | J48: =SUMIFS('C19 GEG GL Trial Balance'!$Y$10:$Y$400,'C19 GEG GL Trial Balance'!$A$10:$A$400,$A48,'C19 GEG GL Trial Balance'!$D$10:$D$400,"Posting") | K48: =SUMIFS('C19 GEG GL Trial Balance'!$Z$10:$Z$400,'C19 GEG GL Trial Balance'!$A$10:$A$400,$A48,'C19 GEG GL Trial Balance'!$D$10:$D$400,"Posting") | L48: =SUMIFS('C19 GEG GL Trial Balance'!$AA$10:$AA$400,'C19 GEG GL Trial Balance'!$A$10:$A$400,$A48,'C19 GEG GL Trial Balance'!$D$10:$D$400,"Posting") | M48: =SUMIFS('C19 GEG GL Trial Balance'!$AB$10:$AB$400,'C19 GEG GL Trial Balance'!$A$10:$A$400,$A48,'C19 GEG GL Trial Balance'!$D$10:$D$400,"Posting") | N48: =SUMIFS('C19 GEG GL Trial Balance'!$AC$10:$AC$400,'C19 GEG GL Trial Balance'!$A$10:$A$400,$A48,'C19 GEG GL Trial Balance'!$D$10:$D$400,"Posting") | O48: =SUMIFS('C19 GEG GL Trial Balance'!$AD$10:$AD$400,'C19 GEG GL Trial Balance'!$A$10:$A$400,$A48,'C19 GEG GL Trial Balance'!$D$10:$D$400,"Posting") | P48: =SUM(D48:O48)
B49: BEBAN POKOK PENDAPATAN | D49: =D47+D48 | E49: =E47+E48 | F49: =F47+F48 | G49: =G47+G48 | H49: =H47+H48 | I49: =I47+I48 | J49: =J47+J48 | K49: =K47+K48 | ... P49: =P47+P48
B50: LABA KOTOR | D50: =D14-D49 | E50: =E14-E49 | F50: =F14-F49 | G50: =G14-G49 | H50: =H14-H49 | I50: =I14-I49 | J50: =J14-J49 | K50: =K14-K49 | ... P50: =P14-P49
B51: Marjin laba kotor | D51: =IFERROR(D50/D14,0) | E51: =IFERROR(E50/E14,0) | F51: =IFERROR(F50/F14,0) | G51: =IFERROR(G50/G14,0) | H51: =IFERROR(H50/H14,0) | I51: =IFERROR(I50/I14,0) | J51: =IFERROR(J50/J14,0) | K51: =IFERROR(K50/K14,0) | ... P51: =IFERROR(P50/P14,0)
A52: BEBAN USAHA
B53: Beban penjualan
A54: 6101 | B54: Pengapalan laut (penjualan CIF) | D54: =SUMIFS('C19 GEG GL Trial Balance'!$S$10:$S$400,'C19 GEG GL Trial Balance'!$A$10:$A$400,$A54,'C19 GEG GL Trial Balance'!$D$10:$D$400,"Posting") | E54: =SUMIFS('C19 GEG GL Trial Balance'!$T$10:$T$400,'C19 GEG GL Trial Balance'!$A$10:$A$400,$A54,'C19 GEG GL Trial Balance'!$D$10:$D$400,"Posting") | F54: =SUMIFS('C19 GEG GL Trial Balance'!$U$10:$U$400,'C19 GEG GL Trial Balance'!$A$10:$A$400,$A54,'C19 GEG GL Trial Balance'!$D$10:$D$400,"Posting") | G54: =SUMIFS('C19 GEG GL Trial Balance'!$V$10:$V$400,'C19 GEG GL Trial Balance'!$A$10:$A$400,$A54,'C19 GEG GL Trial Balance'!$D$10:$D$400,"Posting") | H54: =SUMIFS('C19 GEG GL Trial Balance'!$W$10:$W$400,'C19 GEG GL Trial Balance'!$A$10:$A$400,$A54,'C19 GEG GL Trial Balance'!$D$10:$D$400,"Posting") | I54: =SUMIFS('C19 GEG GL Trial Balance'!$X$10:$X$400,'C19 GEG GL Trial Balance'!$A$10:$A$400,$A54,'C19 GEG GL Trial Balance'!$D$10:$D$400,"Posting") | J54: =SUMIFS('C19 GEG GL Trial Balance'!$Y$10:$Y$400,'C19 GEG GL Trial Balance'!$A$10:$A$400,$A54,'C19 GEG GL Trial Balance'!$D$10:$D$400,"Posting") | K54: =SUMIFS('C19 GEG GL Trial Balance'!$Z$10:$Z$400,'C19 GEG GL Trial Balance'!$A$10:$A$400,$A54,'C19 GEG GL Trial Balance'!$D$10:$D$400,"Posting") | L54: =SUMIFS('C19 GEG GL Trial Balance'!$AA$10:$AA$400,'C19 GEG GL Trial Balance'!$A$10:$A$400,$A54,'C19 GEG GL Trial Balance'!$D$10:$D$400,"Posting") | M54: =SUMIFS('C19 GEG GL Trial Balance'!$AB$10:$AB$400,'C19 GEG GL Trial Balance'!$A$10:$A$400,$A54,'C19 GEG GL Trial Balance'!$D$10:$D$400,"Posting") | N54: =SUMIFS('C19 GEG GL Trial Balance'!$AC$10:$AC$400,'C19 GEG GL Trial Balance'!$A$10:$A$400,$A54,'C19 GEG GL Trial Balance'!$D$10:$D$400,"Posting") | O54: =SUMIFS('C19 GEG GL Trial Balance'!$AD$10:$AD$400,'C19 GEG GL Trial Balance'!$A$10:$A$400,$A54,'C19 GEG GL Trial Balance'!$D$10:$D$400,"Posting") | P54: =SUM(D54:O54)
A55: 6102 | B55: Komisi agen penjualan | D55: =SUMIFS('C19 GEG GL Trial Balance'!$S$10:$S$400,'C19 GEG GL Trial Balance'!$A$10:$A$400,$A55,'C19 GEG GL Trial Balance'!$D$10:$D$400,"Posting") | E55: =SUMIFS('C19 GEG GL Trial Balance'!$T$10:$T$400,'C19 GEG GL Trial Balance'!$A$10:$A$400,$A55,'C19 GEG GL Trial Balance'!$D$10:$D$400,"Posting") | F55: =SUMIFS('C19 GEG GL Trial Balance'!$U$10:$U$400,'C19 GEG GL Trial Balance'!$A$10:$A$400,$A55,'C19 GEG GL Trial Balance'!$D$10:$D$400,"Posting") | G55: =SUMIFS('C19 GEG GL Trial Balance'!$V$10:$V$400,'C19 GEG GL Trial Balance'!$A$10:$A$400,$A55,'C19 GEG GL Trial Balance'!$D$10:$D$400,"Posting") | H55: =SUMIFS('C19 GEG GL Trial Balance'!$W$10:$W$400,'C19 GEG GL Trial Balance'!$A$10:$A$400,$A55,'C19 GEG GL Trial Balance'!$D$10:$D$400,"Posting") | I55: =SUMIFS('C19 GEG GL Trial Balance'!$X$10:$X$400,'C19 GEG GL Trial Balance'!$A$10:$A$400,$A55,'C19 GEG GL Trial Balance'!$D$10:$D$400,"Posting") | J55: =SUMIFS('C19 GEG GL Trial Balance'!$Y$10:$Y$400,'C19 GEG GL Trial Balance'!$A$10:$A$400,$A55,'C19 GEG GL Trial Balance'!$D$10:$D$400,"Posting") | K55: =SUMIFS('C19 GEG GL Trial Balance'!$Z$10:$Z$400,'C19 GEG GL Trial Balance'!$A$10:$A$400,$A55,'C19 GEG GL Trial Balance'!$D$10:$D$400,"Posting") | L55: =SUMIFS('C19 GEG GL Trial Balance'!$AA$10:$AA$400,'C19 GEG GL Trial Balance'!$A$10:$A$400,$A55,'C19 GEG GL Trial Balance'!$D$10:$D$400,"Posting") | M55: =SUMIFS('C19 GEG GL Trial Balance'!$AB$10:$AB$400,'C19 GEG GL Trial Balance'!$A$10:$A$400,$A55,'C19 GEG GL Trial Balance'!$D$10:$D$400,"Posting") | N55: =SUMIFS('C19 GEG GL Trial Balance'!$AC$10:$AC$400,'C19 GEG GL Trial Balance'!$A$10:$A$400,$A55,'C19 GEG GL Trial Balance'!$D$10:$D$400,"Posting") | O55: =SUMIFS('C19 GEG GL Trial Balance'!$AD$10:$AD$400,'C19 GEG GL Trial Balance'!$A$10:$A$400,$A55,'C19 GEG GL Trial Balance'!$D$10:$D$400,"Posting") | P55: =SUM(D55:O55)
A56: 6103 | B56: Surveyor independen & analisa kualitas | D56: =SUMIFS('C19 GEG GL Trial Balance'!$S$10:$S$400,'C19 GEG GL Trial Balance'!$A$10:$A$400,$A56,'C19 GEG GL Trial Balance'!$D$10:$D$400,"Posting") | E56: =SUMIFS('C19 GEG GL Trial Balance'!$T$10:$T$400,'C19 GEG GL Trial Balance'!$A$10:$A$400,$A56,'C19 GEG GL Trial Balance'!$D$10:$D$400,"Posting") | F56: =SUMIFS('C19 GEG GL Trial Balance'!$U$10:$U$400,'C19 GEG GL Trial Balance'!$A$10:$A$400,$A56,'C19 GEG GL Trial Balance'!$D$10:$D$400,"Posting") | G56: =SUMIFS('C19 GEG GL Trial Balance'!$V$10:$V$400,'C19 GEG GL Trial Balance'!$A$10:$A$400,$A56,'C19 GEG GL Trial Balance'!$D$10:$D$400,"Posting") | H56: =SUMIFS('C19 GEG GL Trial Balance'!$W$10:$W$400,'C19 GEG GL Trial Balance'!$A$10:$A$400,$A56,'C19 GEG GL Trial Balance'!$D$10:$D$400,"Posting") | I56: =SUMIFS('C19 GEG GL Trial Balance'!$X$10:$X$400,'C19 GEG GL Trial Balance'!$A$10:$A$400,$A56,'C19 GEG GL Trial Balance'!$D$10:$D$400,"Posting") | J56: =SUMIFS('C19 GEG GL Trial Balance'!$Y$10:$Y$400,'C19 GEG GL Trial Balance'!$A$10:$A$400,$A56,'C19 GEG GL Trial Balance'!$D$10:$D$400,"Posting") | K56: =SUMIFS('C19 GEG GL Trial Balance'!$Z$10:$Z$400,'C19 GEG GL Trial Balance'!$A$10:$A$400,$A56,'C19 GEG GL Trial Balance'!$D$10:$D$400,"Posting") | L56: =SUMIFS('C19 GEG GL Trial Balance'!$AA$10:$AA$400,'C19 GEG GL Trial Balance'!$A$10:$A$400,$A56,'C19 GEG GL Trial Balance'!$D$10:$D$400,"Posting") | M56: =SUMIFS('C19 GEG GL Trial Balance'!$AB$10:$AB$400,'C19 GEG GL Trial Balance'!$A$10:$A$400,$A56,'C19 GEG GL Trial Balance'!$D$10:$D$400,"Posting") | N56: =SUMIFS('C19 GEG GL Trial Balance'!$AC$10:$AC$400,'C19 GEG GL Trial Balance'!$A$10:$A$400,$A56,'C19 GEG GL Trial Balance'!$D$10:$D$400,"Posting") | O56: =SUMIFS('C19 GEG GL Trial Balance'!$AD$10:$AD$400,'C19 GEG GL Trial Balance'!$A$10:$A$400,$A56,'C19 GEG GL Trial Balance'!$D$10:$D$400,"Posting") | P56: =SUM(D56:O56)
A57: 6104 | B57: Demurrage | D57: =SUMIFS('C19 GEG GL Trial Balance'!$S$10:$S$400,'C19 GEG GL Trial Balance'!$A$10:$A$400,$A57,'C19 GEG GL Trial Balance'!$D$10:$D$400,"Posting") | E57: =SUMIFS('C19 GEG GL Trial Balance'!$T$10:$T$400,'C19 GEG GL Trial Balance'!$A$10:$A$400,$A57,'C19 GEG GL Trial Balance'!$D$10:$D$400,"Posting") | F57: =SUMIFS('C19 GEG GL Trial Balance'!$U$10:$U$400,'C19 GEG GL Trial Balance'!$A$10:$A$400,$A57,'C19 GEG GL Trial Balance'!$D$10:$D$400,"Posting") | G57: =SUMIFS('C19 GEG GL Trial Balance'!$V$10:$V$400,'C19 GEG GL Trial Balance'!$A$10:$A$400,$A57,'C19 GEG GL Trial Balance'!$D$10:$D$400,"Posting") | H57: =SUMIFS('C19 GEG GL Trial Balance'!$W$10:$W$400,'C19 GEG GL Trial Balance'!$A$10:$A$400,$A57,'C19 GEG GL Trial Balance'!$D$10:$D$400,"Posting") | I57: =SUMIFS('C19 GEG GL Trial Balance'!$X$10:$X$400,'C19 GEG GL Trial Balance'!$A$10:$A$400,$A57,'C19 GEG GL Trial Balance'!$D$10:$D$400,"Posting") | J57: =SUMIFS('C19 GEG GL Trial Balance'!$Y$10:$Y$400,'C19 GEG GL Trial Balance'!$A$10:$A$400,$A57,'C19 GEG GL Trial Balance'!$D$10:$D$400,"Posting") | K57: =SUMIFS('C19 GEG GL Trial Balance'!$Z$10:$Z$400,'C19 GEG GL Trial Balance'!$A$10:$A$400,$A57,'C19 GEG GL Trial Balance'!$D$10:$D$400,"Posting") | L57: =SUMIFS('C19 GEG GL Trial Balance'!$AA$10:$AA$400,'C19 GEG GL Trial Balance'!$A$10:$A$400,$A57,'C19 GEG GL Trial Balance'!$D$10:$D$400,"Posting") | M57: =SUMIFS('C19 GEG GL Trial Balance'!$AB$10:$AB$400,'C19 GEG GL Trial Balance'!$A$10:$A$400,$A57,'C19 GEG GL Trial Balance'!$D$10:$D$400,"Posting") | N57: =SUMIFS('C19 GEG GL Trial Balance'!$AC$10:$AC$400,'C19 GEG GL Trial Balance'!$A$10:$A$400,$A57,'C19 GEG GL Trial Balance'!$D$10:$D$400,"Posting") | O57: =SUMIFS('C19 GEG GL Trial Balance'!$AD$10:$AD$400,'C19 GEG GL Trial Balance'!$A$10:$A$400,$A57,'C19 GEG GL Trial Balance'!$D$10:$D$400,"Posting") | P57: =SUM(D57:O57)
A58: 6105 | B58: Dokumen ekspor & pungutan | D58: =SUMIFS('C19 GEG GL Trial Balance'!$S$10:$S$400,'C19 GEG GL Trial Balance'!$A$10:$A$400,$A58,'C19 GEG GL Trial Balance'!$D$10:$D$400,"Posting") | E58: =SUMIFS('C19 GEG GL Trial Balance'!$T$10:$T$400,'C19 GEG GL Trial Balance'!$A$10:$A$400,$A58,'C19 GEG GL Trial Balance'!$D$10:$D$400,"Posting") | F58: =SUMIFS('C19 GEG GL Trial Balance'!$U$10:$U$400,'C19 GEG GL Trial Balance'!$A$10:$A$400,$A58,'C19 GEG GL Trial Balance'!$D$10:$D$400,"Posting") | G58: =SUMIFS('C19 GEG GL Trial Balance'!$V$10:$V$400,'C19 GEG GL Trial Balance'!$A$10:$A$400,$A58,'C19 GEG GL Trial Balance'!$D$10:$D$400,"Posting") | H58: =SUMIFS('C19 GEG GL Trial Balance'!$W$10:$W$400,'C19 GEG GL Trial Balance'!$A$10:$A$400,$A58,'C19 GEG GL Trial Balance'!$D$10:$D$400,"Posting") | I58: =SUMIFS('C19 GEG GL Trial Balance'!$X$10:$X$400,'C19 GEG GL Trial Balance'!$A$10:$A$400,$A58,'C19 GEG GL Trial Balance'!$D$10:$D$400,"Posting") | J58: =SUMIFS('C19 GEG GL Trial Balance'!$Y$10:$Y$400,'C19 GEG GL Trial Balance'!$A$10:$A$400,$A58,'C19 GEG GL Trial Balance'!$D$10:$D$400,"Posting") | K58: =SUMIFS('C19 GEG GL Trial Balance'!$Z$10:$Z$400,'C19 GEG GL Trial Balance'!$A$10:$A$400,$A58,'C19 GEG GL Trial Balance'!$D$10:$D$400,"Posting") | L58: =SUMIFS('C19 GEG GL Trial Balance'!$AA$10:$AA$400,'C19 GEG GL Trial Balance'!$A$10:$A$400,$A58,'C19 GEG GL Trial Balance'!$D$10:$D$400,"Posting") | M58: =SUMIFS('C19 GEG GL Trial Balance'!$AB$10:$AB$400,'C19 GEG GL Trial Balance'!$A$10:$A$400,$A58,'C19 GEG GL Trial Balance'!$D$10:$D$400,"Posting") | N58: =SUMIFS('C19 GEG GL Trial Balance'!$AC$10:$AC$400,'C19 GEG GL Trial Balance'!$A$10:$A$400,$A58,'C19 GEG GL Trial Balance'!$D$10:$D$400,"Posting") | O58: =SUMIFS('C19 GEG GL Trial Balance'!$AD$10:$AD$400,'C19 GEG GL Trial Balance'!$A$10:$A$400,$A58,'C19 GEG GL Trial Balance'!$D$10:$D$400,"Posting") | P58: =SUM(D58:O58)
A59: 6106 | B59: Pemasaran & promosi | D59: =SUMIFS('C19 GEG GL Trial Balance'!$S$10:$S$400,'C19 GEG GL Trial Balance'!$A$10:$A$400,$A59,'C19 GEG GL Trial Balance'!$D$10:$D$400,"Posting") | E59: =SUMIFS('C19 GEG GL Trial Balance'!$T$10:$T$400,'C19 GEG GL Trial Balance'!$A$10:$A$400,$A59,'C19 GEG GL Trial Balance'!$D$10:$D$400,"Posting") | F59: =SUMIFS('C19 GEG GL Trial Balance'!$U$10:$U$400,'C19 GEG GL Trial Balance'!$A$10:$A$400,$A59,'C19 GEG GL Trial Balance'!$D$10:$D$400,"Posting") | G59: =SUMIFS('C19 GEG GL Trial Balance'!$V$10:$V$400,'C19 GEG GL Trial Balance'!$A$10:$A$400,$A59,'C19 GEG GL Trial Balance'!$D$10:$D$400,"Posting") | H59: =SUMIFS('C19 GEG GL Trial Balance'!$W$10:$W$400,'C19 GEG GL Trial Balance'!$A$10:$A$400,$A59,'C19 GEG GL Trial Balance'!$D$10:$D$400,"Posting") | I59: =SUMIFS('C19 GEG GL Trial Balance'!$X$10:$X$400,'C19 GEG GL Trial Balance'!$A$10:$A$400,$A59,'C19 GEG GL Trial Balance'!$D$10:$D$400,"Posting") | J59: =SUMIFS('C19 GEG GL Trial Balance'!$Y$10:$Y$400,'C19 GEG GL Trial Balance'!$A$10:$A$400,$A59,'C19 GEG GL Trial Balance'!$D$10:$D$400,"Posting") | K59: =SUMIFS('C19 GEG GL Trial Balance'!$Z$10:$Z$400,'C19 GEG GL Trial Balance'!$A$10:$A$400,$A59,'C19 GEG GL Trial Balance'!$D$10:$D$400,"Posting") | L59: =SUMIFS('C19 GEG GL Trial Balance'!$AA$10:$AA$400,'C19 GEG GL Trial Balance'!$A$10:$A$400,$A59,'C19 GEG GL Trial Balance'!$D$10:$D$400,"Posting") | M59: =SUMIFS('C19 GEG GL Trial Balance'!$AB$10:$AB$400,'C19 GEG GL Trial Balance'!$A$10:$A$400,$A59,'C19 GEG GL Trial Balance'!$D$10:$D$400,"Posting") | N59: =SUMIFS('C19 GEG GL Trial Balance'!$AC$10:$AC$400,'C19 GEG GL Trial Balance'!$A$10:$A$400,$A59,'C19 GEG GL Trial Balance'!$D$10:$D$400,"Posting") | O59: =SUMIFS('C19 GEG GL Trial Balance'!$AD$10:$AD$400,'C19 GEG GL Trial Balance'!$A$10:$A$400,$A59,'C19 GEG GL Trial Balance'!$D$10:$D$400,"Posting") | P59: =SUM(D59:O59)
B60: Subtotal beban penjualan | D60: =D54+D55+D56+D57+D58+D59 | E60: =E54+E55+E56+E57+E58+E59 | F60: =F54+F55+F56+F57+F58+F59 | G60: =G54+G55+G56+G57+G58+G59 | H60: =H54+H55+H56+H57+H58+H59 | I60: =I54+I55+I56+I57+I58+I59 | J60: =J54+J55+J56+J57+J58+J59 | K60: =K54+K55+K56+K57+K58+K59 | ... P60: =P54+P55+P56+P57+P58+P59
B61: Beban umum & administrasi
A62: 6201 | B62: Gaji & tunjangan kantor pusat | D62: =SUMIFS('C19 GEG GL Trial Balance'!$S$10:$S$400,'C19 GEG GL Trial Balance'!$A$10:$A$400,$A62,'C19 GEG GL Trial Balance'!$D$10:$D$400,"Posting") | E62: =SUMIFS('C19 GEG GL Trial Balance'!$T$10:$T$400,'C19 GEG GL Trial Balance'!$A$10:$A$400,$A62,'C19 GEG GL Trial Balance'!$D$10:$D$400,"Posting") | F62: =SUMIFS('C19 GEG GL Trial Balance'!$U$10:$U$400,'C19 GEG GL Trial Balance'!$A$10:$A$400,$A62,'C19 GEG GL Trial Balance'!$D$10:$D$400,"Posting") | G62: =SUMIFS('C19 GEG GL Trial Balance'!$V$10:$V$400,'C19 GEG GL Trial Balance'!$A$10:$A$400,$A62,'C19 GEG GL Trial Balance'!$D$10:$D$400,"Posting") | H62: =SUMIFS('C19 GEG GL Trial Balance'!$W$10:$W$400,'C19 GEG GL Trial Balance'!$A$10:$A$400,$A62,'C19 GEG GL Trial Balance'!$D$10:$D$400,"Posting") | I62: =SUMIFS('C19 GEG GL Trial Balance'!$X$10:$X$400,'C19 GEG GL Trial Balance'!$A$10:$A$400,$A62,'C19 GEG GL Trial Balance'!$D$10:$D$400,"Posting") | J62: =SUMIFS('C19 GEG GL Trial Balance'!$Y$10:$Y$400,'C19 GEG GL Trial Balance'!$A$10:$A$400,$A62,'C19 GEG GL Trial Balance'!$D$10:$D$400,"Posting") | K62: =SUMIFS('C19 GEG GL Trial Balance'!$Z$10:$Z$400,'C19 GEG GL Trial Balance'!$A$10:$A$400,$A62,'C19 GEG GL Trial Balance'!$D$10:$D$400,"Posting") | L62: =SUMIFS('C19 GEG GL Trial Balance'!$AA$10:$AA$400,'C19 GEG GL Trial Balance'!$A$10:$A$400,$A62,'C19 GEG GL Trial Balance'!$D$10:$D$400,"Posting") | M62: =SUMIFS('C19 GEG GL Trial Balance'!$AB$10:$AB$400,'C19 GEG GL Trial Balance'!$A$10:$A$400,$A62,'C19 GEG GL Trial Balance'!$D$10:$D$400,"Posting") | N62: =SUMIFS('C19 GEG GL Trial Balance'!$AC$10:$AC$400,'C19 GEG GL Trial Balance'!$A$10:$A$400,$A62,'C19 GEG GL Trial Balance'!$D$10:$D$400,"Posting") | O62: =SUMIFS('C19 GEG GL Trial Balance'!$AD$10:$AD$400,'C19 GEG GL Trial Balance'!$A$10:$A$400,$A62,'C19 GEG GL Trial Balance'!$D$10:$D$400,"Posting") | P62: =SUM(D62:O62)
A63: 6202 | B63: Jasa profesional | D63: =SUMIFS('C19 GEG GL Trial Balance'!$S$10:$S$400,'C19 GEG GL Trial Balance'!$A$10:$A$400,$A63,'C19 GEG GL Trial Balance'!$D$10:$D$400,"Posting") | E63: =SUMIFS('C19 GEG GL Trial Balance'!$T$10:$T$400,'C19 GEG GL Trial Balance'!$A$10:$A$400,$A63,'C19 GEG GL Trial Balance'!$D$10:$D$400,"Posting") | F63: =SUMIFS('C19 GEG GL Trial Balance'!$U$10:$U$400,'C19 GEG GL Trial Balance'!$A$10:$A$400,$A63,'C19 GEG GL Trial Balance'!$D$10:$D$400,"Posting") | G63: =SUMIFS('C19 GEG GL Trial Balance'!$V$10:$V$400,'C19 GEG GL Trial Balance'!$A$10:$A$400,$A63,'C19 GEG GL Trial Balance'!$D$10:$D$400,"Posting") | H63: =SUMIFS('C19 GEG GL Trial Balance'!$W$10:$W$400,'C19 GEG GL Trial Balance'!$A$10:$A$400,$A63,'C19 GEG GL Trial Balance'!$D$10:$D$400,"Posting") | I63: =SUMIFS('C19 GEG GL Trial Balance'!$X$10:$X$400,'C19 GEG GL Trial Balance'!$A$10:$A$400,$A63,'C19 GEG GL Trial Balance'!$D$10:$D$400,"Posting") | J63: =SUMIFS('C19 GEG GL Trial Balance'!$Y$10:$Y$400,'C19 GEG GL Trial Balance'!$A$10:$A$400,$A63,'C19 GEG GL Trial Balance'!$D$10:$D$400,"Posting") | K63: =SUMIFS('C19 GEG GL Trial Balance'!$Z$10:$Z$400,'C19 GEG GL Trial Balance'!$A$10:$A$400,$A63,'C19 GEG GL Trial Balance'!$D$10:$D$400,"Posting") | L63: =SUMIFS('C19 GEG GL Trial Balance'!$AA$10:$AA$400,'C19 GEG GL Trial Balance'!$A$10:$A$400,$A63,'C19 GEG GL Trial Balance'!$D$10:$D$400,"Posting") | M63: =SUMIFS('C19 GEG GL Trial Balance'!$AB$10:$AB$400,'C19 GEG GL Trial Balance'!$A$10:$A$400,$A63,'C19 GEG GL Trial Balance'!$D$10:$D$400,"Posting") | N63: =SUMIFS('C19 GEG GL Trial Balance'!$AC$10:$AC$400,'C19 GEG GL Trial Balance'!$A$10:$A$400,$A63,'C19 GEG GL Trial Balance'!$D$10:$D$400,"Posting") | O63: =SUMIFS('C19 GEG GL Trial Balance'!$AD$10:$AD$400,'C19 GEG GL Trial Balance'!$A$10:$A$400,$A63,'C19 GEG GL Trial Balance'!$D$10:$D$400,"Posting") | P63: =SUM(D63:O63)
A64: 6203 | B64: Sewa kantor | D64: =SUMIFS('C19 GEG GL Trial Balance'!$S$10:$S$400,'C19 GEG GL Trial Balance'!$A$10:$A$400,$A64,'C19 GEG GL Trial Balance'!$D$10:$D$400,"Posting") | E64: =SUMIFS('C19 GEG GL Trial Balance'!$T$10:$T$400,'C19 GEG GL Trial Balance'!$A$10:$A$400,$A64,'C19 GEG GL Trial Balance'!$D$10:$D$400,"Posting") | F64: =SUMIFS('C19 GEG GL Trial Balance'!$U$10:$U$400,'C19 GEG GL Trial Balance'!$A$10:$A$400,$A64,'C19 GEG GL Trial Balance'!$D$10:$D$400,"Posting") | G64: =SUMIFS('C19 GEG GL Trial Balance'!$V$10:$V$400,'C19 GEG GL Trial Balance'!$A$10:$A$400,$A64,'C19 GEG GL Trial Balance'!$D$10:$D$400,"Posting") | H64: =SUMIFS('C19 GEG GL Trial Balance'!$W$10:$W$400,'C19 GEG GL Trial Balance'!$A$10:$A$400,$A64,'C19 GEG GL Trial Balance'!$D$10:$D$400,"Posting") | I64: =SUMIFS('C19 GEG GL Trial Balance'!$X$10:$X$400,'C19 GEG GL Trial Balance'!$A$10:$A$400,$A64,'C19 GEG GL Trial Balance'!$D$10:$D$400,"Posting") | J64: =SUMIFS('C19 GEG GL Trial Balance'!$Y$10:$Y$400,'C19 GEG GL Trial Balance'!$A$10:$A$400,$A64,'C19 GEG GL Trial Balance'!$D$10:$D$400,"Posting") | K64: =SUMIFS('C19 GEG GL Trial Balance'!$Z$10:$Z$400,'C19 GEG GL Trial Balance'!$A$10:$A$400,$A64,'C19 GEG GL Trial Balance'!$D$10:$D$400,"Posting") | L64: =SUMIFS('C19 GEG GL Trial Balance'!$AA$10:$AA$400,'C19 GEG GL Trial Balance'!$A$10:$A$400,$A64,'C19 GEG GL Trial Balance'!$D$10:$D$400,"Posting") | M64: =SUMIFS('C19 GEG GL Trial Balance'!$AB$10:$AB$400,'C19 GEG GL Trial Balance'!$A$10:$A$400,$A64,'C19 GEG GL Trial Balance'!$D$10:$D$400,"Posting") | N64: =SUMIFS('C19 GEG GL Trial Balance'!$AC$10:$AC$400,'C19 GEG GL Trial Balance'!$A$10:$A$400,$A64,'C19 GEG GL Trial Balance'!$D$10:$D$400,"Posting") | O64: =SUMIFS('C19 GEG GL Trial Balance'!$AD$10:$AD$400,'C19 GEG GL Trial Balance'!$A$10:$A$400,$A64,'C19 GEG GL Trial Balance'!$D$10:$D$400,"Posting") | P64: =SUM(D64:O64)
A65: 6204 | B65: Perjalanan dinas | D65: =SUMIFS('C19 GEG GL Trial Balance'!$S$10:$S$400,'C19 GEG GL Trial Balance'!$A$10:$A$400,$A65,'C19 GEG GL Trial Balance'!$D$10:$D$400,"Posting") | E65: =SUMIFS('C19 GEG GL Trial Balance'!$T$10:$T$400,'C19 GEG GL Trial Balance'!$A$10:$A$400,$A65,'C19 GEG GL Trial Balance'!$D$10:$D$400,"Posting") | F65: =SUMIFS('C19 GEG GL Trial Balance'!$U$10:$U$400,'C19 GEG GL Trial Balance'!$A$10:$A$400,$A65,'C19 GEG GL Trial Balance'!$D$10:$D$400,"Posting") | G65: =SUMIFS('C19 GEG GL Trial Balance'!$V$10:$V$400,'C19 GEG GL Trial Balance'!$A$10:$A$400,$A65,'C19 GEG GL Trial Balance'!$D$10:$D$400,"Posting") | H65: =SUMIFS('C19 GEG GL Trial Balance'!$W$10:$W$400,'C19 GEG GL Trial Balance'!$A$10:$A$400,$A65,'C19 GEG GL Trial Balance'!$D$10:$D$400,"Posting") | I65: =SUMIFS('C19 GEG GL Trial Balance'!$X$10:$X$400,'C19 GEG GL Trial Balance'!$A$10:$A$400,$A65,'C19 GEG GL Trial Balance'!$D$10:$D$400,"Posting") | J65: =SUMIFS('C19 GEG GL Trial Balance'!$Y$10:$Y$400,'C19 GEG GL Trial Balance'!$A$10:$A$400,$A65,'C19 GEG GL Trial Balance'!$D$10:$D$400,"Posting") | K65: =SUMIFS('C19 GEG GL Trial Balance'!$Z$10:$Z$400,'C19 GEG GL Trial Balance'!$A$10:$A$400,$A65,'C19 GEG GL Trial Balance'!$D$10:$D$400,"Posting") | L65: =SUMIFS('C19 GEG GL Trial Balance'!$AA$10:$AA$400,'C19 GEG GL Trial Balance'!$A$10:$A$400,$A65,'C19 GEG GL Trial Balance'!$D$10:$D$400,"Posting") | M65: =SUMIFS('C19 GEG GL Trial Balance'!$AB$10:$AB$400,'C19 GEG GL Trial Balance'!$A$10:$A$400,$A65,'C19 GEG GL Trial Balance'!$D$10:$D$400,"Posting") | N65: =SUMIFS('C19 GEG GL Trial Balance'!$AC$10:$AC$400,'C19 GEG GL Trial Balance'!$A$10:$A$400,$A65,'C19 GEG GL Trial Balance'!$D$10:$D$400,"Posting") | O65: =SUMIFS('C19 GEG GL Trial Balance'!$AD$10:$AD$400,'C19 GEG GL Trial Balance'!$A$10:$A$400,$A65,'C19 GEG GL Trial Balance'!$D$10:$D$400,"Posting") | P65: =SUM(D65:O65)
A66: 6205 | B66: Asuransi | D66: =SUMIFS('C19 GEG GL Trial Balance'!$S$10:$S$400,'C19 GEG GL Trial Balance'!$A$10:$A$400,$A66,'C19 GEG GL Trial Balance'!$D$10:$D$400,"Posting") | E66: =SUMIFS('C19 GEG GL Trial Balance'!$T$10:$T$400,'C19 GEG GL Trial Balance'!$A$10:$A$400,$A66,'C19 GEG GL Trial Balance'!$D$10:$D$400,"Posting") | F66: =SUMIFS('C19 GEG GL Trial Balance'!$U$10:$U$400,'C19 GEG GL Trial Balance'!$A$10:$A$400,$A66,'C19 GEG GL Trial Balance'!$D$10:$D$400,"Posting") | G66: =SUMIFS('C19 GEG GL Trial Balance'!$V$10:$V$400,'C19 GEG GL Trial Balance'!$A$10:$A$400,$A66,'C19 GEG GL Trial Balance'!$D$10:$D$400,"Posting") | H66: =SUMIFS('C19 GEG GL Trial Balance'!$W$10:$W$400,'C19 GEG GL Trial Balance'!$A$10:$A$400,$A66,'C19 GEG GL Trial Balance'!$D$10:$D$400,"Posting") | I66: =SUMIFS('C19 GEG GL Trial Balance'!$X$10:$X$400,'C19 GEG GL Trial Balance'!$A$10:$A$400,$A66,'C19 GEG GL Trial Balance'!$D$10:$D$400,"Posting") | J66: =SUMIFS('C19 GEG GL Trial Balance'!$Y$10:$Y$400,'C19 GEG GL Trial Balance'!$A$10:$A$400,$A66,'C19 GEG GL Trial Balance'!$D$10:$D$400,"Posting") | K66: =SUMIFS('C19 GEG GL Trial Balance'!$Z$10:$Z$400,'C19 GEG GL Trial Balance'!$A$10:$A$400,$A66,'C19 GEG GL Trial Balance'!$D$10:$D$400,"Posting") | L66: =SUMIFS('C19 GEG GL Trial Balance'!$AA$10:$AA$400,'C19 GEG GL Trial Balance'!$A$10:$A$400,$A66,'C19 GEG GL Trial Balance'!$D$10:$D$400,"Posting") | M66: =SUMIFS('C19 GEG GL Trial Balance'!$AB$10:$AB$400,'C19 GEG GL Trial Balance'!$A$10:$A$400,$A66,'C19 GEG GL Trial Balance'!$D$10:$D$400,"Posting") | N66: =SUMIFS('C19 GEG GL Trial Balance'!$AC$10:$AC$400,'C19 GEG GL Trial Balance'!$A$10:$A$400,$A66,'C19 GEG GL Trial Balance'!$D$10:$D$400,"Posting") | O66: =SUMIFS('C19 GEG GL Trial Balance'!$AD$10:$AD$400,'C19 GEG GL Trial Balance'!$A$10:$A$400,$A66,'C19 GEG GL Trial Balance'!$D$10:$D$400,"Posting") | P66: =SUM(D66:O66)
A67: 6206 | B67: Pajak, perizinan & iuran | D67: =SUMIFS('C19 GEG GL Trial Balance'!$S$10:$S$400,'C19 GEG GL Trial Balance'!$A$10:$A$400,$A67,'C19 GEG GL Trial Balance'!$D$10:$D$400,"Posting") | E67: =SUMIFS('C19 GEG GL Trial Balance'!$T$10:$T$400,'C19 GEG GL Trial Balance'!$A$10:$A$400,$A67,'C19 GEG GL Trial Balance'!$D$10:$D$400,"Posting") | F67: =SUMIFS('C19 GEG GL Trial Balance'!$U$10:$U$400,'C19 GEG GL Trial Balance'!$A$10:$A$400,$A67,'C19 GEG GL Trial Balance'!$D$10:$D$400,"Posting") | G67: =SUMIFS('C19 GEG GL Trial Balance'!$V$10:$V$400,'C19 GEG GL Trial Balance'!$A$10:$A$400,$A67,'C19 GEG GL Trial Balance'!$D$10:$D$400,"Posting") | H67: =SUMIFS('C19 GEG GL Trial Balance'!$W$10:$W$400,'C19 GEG GL Trial Balance'!$A$10:$A$400,$A67,'C19 GEG GL Trial Balance'!$D$10:$D$400,"Posting") | I67: =SUMIFS('C19 GEG GL Trial Balance'!$X$10:$X$400,'C19 GEG GL Trial Balance'!$A$10:$A$400,$A67,'C19 GEG GL Trial Balance'!$D$10:$D$400,"Posting") | J67: =SUMIFS('C19 GEG GL Trial Balance'!$Y$10:$Y$400,'C19 GEG GL Trial Balance'!$A$10:$A$400,$A67,'C19 GEG GL Trial Balance'!$D$10:$D$400,"Posting") | K67: =SUMIFS('C19 GEG GL Trial Balance'!$Z$10:$Z$400,'C19 GEG GL Trial Balance'!$A$10:$A$400,$A67,'C19 GEG GL Trial Balance'!$D$10:$D$400,"Posting") | L67: =SUMIFS('C19 GEG GL Trial Balance'!$AA$10:$AA$400,'C19 GEG GL Trial Balance'!$A$10:$A$400,$A67,'C19 GEG GL Trial Balance'!$D$10:$D$400,"Posting") | M67: =SUMIFS('C19 GEG GL Trial Balance'!$AB$10:$AB$400,'C19 GEG GL Trial Balance'!$A$10:$A$400,$A67,'C19 GEG GL Trial Balance'!$D$10:$D$400,"Posting") | N67: =SUMIFS('C19 GEG GL Trial Balance'!$AC$10:$AC$400,'C19 GEG GL Trial Balance'!$A$10:$A$400,$A67,'C19 GEG GL Trial Balance'!$D$10:$D$400,"Posting") | O67: =SUMIFS('C19 GEG GL Trial Balance'!$AD$10:$AD$400,'C19 GEG GL Trial Balance'!$A$10:$A$400,$A67,'C19 GEG GL Trial Balance'!$D$10:$D$400,"Posting") | P67: =SUM(D67:O67)
A68: 6207 | B68: Teknologi informasi & komunikasi | D68: =SUMIFS('C19 GEG GL Trial Balance'!$S$10:$S$400,'C19 GEG GL Trial Balance'!$A$10:$A$400,$A68,'C19 GEG GL Trial Balance'!$D$10:$D$400,"Posting") | E68: =SUMIFS('C19 GEG GL Trial Balance'!$T$10:$T$400,'C19 GEG GL Trial Balance'!$A$10:$A$400,$A68,'C19 GEG GL Trial Balance'!$D$10:$D$400,"Posting") | F68: =SUMIFS('C19 GEG GL Trial Balance'!$U$10:$U$400,'C19 GEG GL Trial Balance'!$A$10:$A$400,$A68,'C19 GEG GL Trial Balance'!$D$10:$D$400,"Posting") | G68: =SUMIFS('C19 GEG GL Trial Balance'!$V$10:$V$400,'C19 GEG GL Trial Balance'!$A$10:$A$400,$A68,'C19 GEG GL Trial Balance'!$D$10:$D$400,"Posting") | H68: =SUMIFS('C19 GEG GL Trial Balance'!$W$10:$W$400,'C19 GEG GL Trial Balance'!$A$10:$A$400,$A68,'C19 GEG GL Trial Balance'!$D$10:$D$400,"Posting") | I68: =SUMIFS('C19 GEG GL Trial Balance'!$X$10:$X$400,'C19 GEG GL Trial Balance'!$A$10:$A$400,$A68,'C19 GEG GL Trial Balance'!$D$10:$D$400,"Posting") | J68: =SUMIFS('C19 GEG GL Trial Balance'!$Y$10:$Y$400,'C19 GEG GL Trial Balance'!$A$10:$A$400,$A68,'C19 GEG GL Trial Balance'!$D$10:$D$400,"Posting") | K68: =SUMIFS('C19 GEG GL Trial Balance'!$Z$10:$Z$400,'C19 GEG GL Trial Balance'!$A$10:$A$400,$A68,'C19 GEG GL Trial Balance'!$D$10:$D$400,"Posting") | L68: =SUMIFS('C19 GEG GL Trial Balance'!$AA$10:$AA$400,'C19 GEG GL Trial Balance'!$A$10:$A$400,$A68,'C19 GEG GL Trial Balance'!$D$10:$D$400,"Posting") | M68: =SUMIFS('C19 GEG GL Trial Balance'!$AB$10:$AB$400,'C19 GEG GL Trial Balance'!$A$10:$A$400,$A68,'C19 GEG GL Trial Balance'!$D$10:$D$400,"Posting") | N68: =SUMIFS('C19 GEG GL Trial Balance'!$AC$10:$AC$400,'C19 GEG GL Trial Balance'!$A$10:$A$400,$A68,'C19 GEG GL Trial Balance'!$D$10:$D$400,"Posting") | O68: =SUMIFS('C19 GEG GL Trial Balance'!$AD$10:$AD$400,'C19 GEG GL Trial Balance'!$A$10:$A$400,$A68,'C19 GEG GL Trial Balance'!$D$10:$D$400,"Posting") | P68: =SUM(D68:O68)
A69: 6208 | B69: Penyusutan aset kantor | D69: =SUMIFS('C19 GEG GL Trial Balance'!$S$10:$S$400,'C19 GEG GL Trial Balance'!$A$10:$A$400,$A69,'C19 GEG GL Trial Balance'!$D$10:$D$400,"Posting") | E69: =SUMIFS('C19 GEG GL Trial Balance'!$T$10:$T$400,'C19 GEG GL Trial Balance'!$A$10:$A$400,$A69,'C19 GEG GL Trial Balance'!$D$10:$D$400,"Posting") | F69: =SUMIFS('C19 GEG GL Trial Balance'!$U$10:$U$400,'C19 GEG GL Trial Balance'!$A$10:$A$400,$A69,'C19 GEG GL Trial Balance'!$D$10:$D$400,"Posting") | G69: =SUMIFS('C19 GEG GL Trial Balance'!$V$10:$V$400,'C19 GEG GL Trial Balance'!$A$10:$A$400,$A69,'C19 GEG GL Trial Balance'!$D$10:$D$400,"Posting") | H69: =SUMIFS('C19 GEG GL Trial Balance'!$W$10:$W$400,'C19 GEG GL Trial Balance'!$A$10:$A$400,$A69,'C19 GEG GL Trial Balance'!$D$10:$D$400,"Posting") | I69: =SUMIFS('C19 GEG GL Trial Balance'!$X$10:$X$400,'C19 GEG GL Trial Balance'!$A$10:$A$400,$A69,'C19 GEG GL Trial Balance'!$D$10:$D$400,"Posting") | J69: =SUMIFS('C19 GEG GL Trial Balance'!$Y$10:$Y$400,'C19 GEG GL Trial Balance'!$A$10:$A$400,$A69,'C19 GEG GL Trial Balance'!$D$10:$D$400,"Posting") | K69: =SUMIFS('C19 GEG GL Trial Balance'!$Z$10:$Z$400,'C19 GEG GL Trial Balance'!$A$10:$A$400,$A69,'C19 GEG GL Trial Balance'!$D$10:$D$400,"Posting") | L69: =SUMIFS('C19 GEG GL Trial Balance'!$AA$10:$AA$400,'C19 GEG GL Trial Balance'!$A$10:$A$400,$A69,'C19 GEG GL Trial Balance'!$D$10:$D$400,"Posting") | M69: =SUMIFS('C19 GEG GL Trial Balance'!$AB$10:$AB$400,'C19 GEG GL Trial Balance'!$A$10:$A$400,$A69,'C19 GEG GL Trial Balance'!$D$10:$D$400,"Posting") | N69: =SUMIFS('C19 GEG GL Trial Balance'!$AC$10:$AC$400,'C19 GEG GL Trial Balance'!$A$10:$A$400,$A69,'C19 GEG GL Trial Balance'!$D$10:$D$400,"Posting") | O69: =SUMIFS('C19 GEG GL Trial Balance'!$AD$10:$AD$400,'C19 GEG GL Trial Balance'!$A$10:$A$400,$A69,'C19 GEG GL Trial Balance'!$D$10:$D$400,"Posting") | P69: =SUM(D69:O69)
A70: 6209 | B70: Beban umum lainnya | D70: =SUMIFS('C19 GEG GL Trial Balance'!$S$10:$S$400,'C19 GEG GL Trial Balance'!$A$10:$A$400,$A70,'C19 GEG GL Trial Balance'!$D$10:$D$400,"Posting") | E70: =SUMIFS('C19 GEG GL Trial Balance'!$T$10:$T$400,'C19 GEG GL Trial Balance'!$A$10:$A$400,$A70,'C19 GEG GL Trial Balance'!$D$10:$D$400,"Posting") | F70: =SUMIFS('C19 GEG GL Trial Balance'!$U$10:$U$400,'C19 GEG GL Trial Balance'!$A$10:$A$400,$A70,'C19 GEG GL Trial Balance'!$D$10:$D$400,"Posting") | G70: =SUMIFS('C19 GEG GL Trial Balance'!$V$10:$V$400,'C19 GEG GL Trial Balance'!$A$10:$A$400,$A70,'C19 GEG GL Trial Balance'!$D$10:$D$400,"Posting") | H70: =SUMIFS('C19 GEG GL Trial Balance'!$W$10:$W$400,'C19 GEG GL Trial Balance'!$A$10:$A$400,$A70,'C19 GEG GL Trial Balance'!$D$10:$D$400,"Posting") | I70: =SUMIFS('C19 GEG GL Trial Balance'!$X$10:$X$400,'C19 GEG GL Trial Balance'!$A$10:$A$400,$A70,'C19 GEG GL Trial Balance'!$D$10:$D$400,"Posting") | J70: =SUMIFS('C19 GEG GL Trial Balance'!$Y$10:$Y$400,'C19 GEG GL Trial Balance'!$A$10:$A$400,$A70,'C19 GEG GL Trial Balance'!$D$10:$D$400,"Posting") | K70: =SUMIFS('C19 GEG GL Trial Balance'!$Z$10:$Z$400,'C19 GEG GL Trial Balance'!$A$10:$A$400,$A70,'C19 GEG GL Trial Balance'!$D$10:$D$400,"Posting") | L70: =SUMIFS('C19 GEG GL Trial Balance'!$AA$10:$AA$400,'C19 GEG GL Trial Balance'!$A$10:$A$400,$A70,'C19 GEG GL Trial Balance'!$D$10:$D$400,"Posting") | M70: =SUMIFS('C19 GEG GL Trial Balance'!$AB$10:$AB$400,'C19 GEG GL Trial Balance'!$A$10:$A$400,$A70,'C19 GEG GL Trial Balance'!$D$10:$D$400,"Posting") | N70: =SUMIFS('C19 GEG GL Trial Balance'!$AC$10:$AC$400,'C19 GEG GL Trial Balance'!$A$10:$A$400,$A70,'C19 GEG GL Trial Balance'!$D$10:$D$400,"Posting") | O70: =SUMIFS('C19 GEG GL Trial Balance'!$AD$10:$AD$400,'C19 GEG GL Trial Balance'!$A$10:$A$400,$A70,'C19 GEG GL Trial Balance'!$D$10:$D$400,"Posting") | P70: =SUM(D70:O70)
B71: Subtotal beban umum & administrasi | D71: =D62+D63+D64+D65+D66+D67+D68+D69+D70 | E71: =E62+E63+E64+E65+E66+E67+E68+E69+E70 | F71: =F62+F63+F64+F65+F66+F67+F68+F69+F70 | G71: =G62+G63+G64+G65+G66+G67+G68+G69+G70 | H71: =H62+H63+H64+H65+H66+H67+H68+H69+H70 | I71: =I62+I63+I64+I65+I66+I67+I68+I69+I70 | J71: =J62+J63+J64+J65+J66+J67+J68+J69+J70 | K71: =K62+K63+K64+K65+K66+K67+K68+K69+K70 | ... P71: =P62+P63+P64+P65+P66+P67+P68+P69+P70
B72: TOTAL BEBAN USAHA | D72: =D60+D71 | E72: =E60+E71 | F72: =F60+F71 | G72: =G60+G71 | H72: =H60+H71 | I72: =I60+I71 | J72: =J60+J71 | K72: =K60+K71 | ... P72: =P60+P71
B73: LABA USAHA | D73: =D50-D72 | E73: =E50-E72 | F73: =F50-F72 | G73: =G50-G72 | H73: =H50-H72 | I73: =I50-I72 | J73: =J50-J72 | K73: =K50-K72 | ... P73: =P50-P72
B74: Marjin laba usaha | D74: =IFERROR(D73/D14,0) | E74: =IFERROR(E73/E14,0) | F74: =IFERROR(F73/F14,0) | G74: =IFERROR(G73/G14,0) | H74: =IFERROR(H73/H14,0) | I74: =IFERROR(I73/I14,0) | J74: =IFERROR(J73/J14,0) | K74: =IFERROR(K73/K14,0) | ... P74: =IFERROR(P73/P14,0)
A75: PENDAPATAN (BEBAN) LAIN-LAIN
